Workbook
Name _1_Colour: 'PRINT OTHER'!$D$153:$I$153
Name _1_Colour: 'PRINT APPAREL'!#REF!
Name _2_000: EMBROIDERY!$D$51:$CX$51
Name _2_000: TRANSFERS!#REF!
Name _2_000: [1]SCREENPRINT!#REF!
Name A2PRINT: '[2]WORKING SCREENPRINT GRID'!$D$98:$AS$113
Name A2SCREEN: '[2]WORKING SCREENPRINT GRID'!$D$114:$AS$116
Name A3PRINT: '[2]WORKING SCREENPRINT GRID'!$D$76:$AS$91
Name A3SCREEN: '[2]WORKING SCREENPRINT GRID'!$D$92:$AS$94
Name A4PRINT: '[2]WORKING SCREENPRINT GRID'!$D$54:$AS$69
Name A4SCREEN: '[2]WORKING SCREENPRINT GRID'!$D$70:$AS$72
Name A6PRINT: '[2]WORKING SCREENPRINT GRID'!$D$32:$AS$47
Name A6SCREEN: '[2]WORKING SCREENPRINT GRID'!$D$48:$AS$50
Name ADDSCREEB: 'PRINT OTHER'!$U$125:$U$126
Name ADDSCREEB: 'PRINT APPAREL'!$T$66:$T$67
Name ADDSCREEN: EMBROIDERY!#REF!
Name ADDSCREEN: TRANSFERS!#REF!
Name ADDSCREEN: [1]SCREENPRINT!$C$54:$IO$56
Name BREAKCOLOURS: EMBROIDERY!#REF!
Name BREAKCOLOURS: 'PRINT OTHER'!$F$114:$L$114
Name BREAKCOLOURS: TRANSFERS!#REF!
Name BREAKCOLOURS: 'PRINT APPAREL'!$F$55:$K$55
Name BREAKCOLOURS2: EMBROIDERY!#REF!
Name BREAKCOLOURS2: TRANSFERS!#REF!
Name BREAKCOLOURS2: [1]SCREENPRINT!$E$116:$J$116
Name BREAKDOWN: EMBROIDERY!#REF!
Name BREAKDOWN: 'PRINT OTHER'!$E$115:$E$123
Name BREAKDOWN: TRANSFERS!#REF!
Name BREAKDOWN: 'PRINT APPAREL'!$E$56:$E$64
Name BREAKDOWN3LOCATIONS: EMBROIDERY!$F$38:$K$38
Name BREAKDOWN3LOCATIONS: TRANSFERS!#REF!
Name BREAKDOWN3LOCATIONS: [1]SCREENPRINT!#REF!
Name BREAKDOWN3PRICING: EMBROIDERY!$F$39:$K$47
Name BREAKDOWN3PRICING: TRANSFERS!#REF!
Name BREAKDOWN3PRICING: [1]SCREENPRINT!#REF!
Name BREAKDOWNTABLE: EMBROIDERY!#REF!
Name BREAKDOWNTABLE: 'PRINT OTHER'!$F$115:$L$123
Name BREAKDOWNTABLE: TRANSFERS!#REF!
Name BREAKDOWNTABLE: 'PRINT APPAREL'!$F$56:$K$64
Name BREAKDOWNTABLE2: EMBROIDERY!#REF!
Name BREAKDOWNTABLE2: TRANSFERS!#REF!
Name BREAKDOWNTABLE2: [1]SCREENPRINT!$E$117:$J$125
Name BREAKDOWNTABLE3: EMBROIDERY!$C$39:$E$47
Name BREAKDOWNTABLE3: TRANSFERS!#REF!
Name BREAKDOWNTABLE3: [1]SCREENPRINT!#REF!
Name CAPSOPTIONS: EMBROIDERY!$B$76:$B$79
Name CAPSPRICE: EMBROIDERY!$C$76:$C$79
Name COLOURS: '[2]WORKING SCREENPRINT GRID'!$D$31:$AS$31
Name DIGITISINGCOSTS: TRANSFERS!#REF!
Name DIGITISINGCOSTS: EMBROIDERY!$C$69:$EV$71
Name DIGITISINGOPTIONS: TRANSFERS!#REF!
Name DIGITISINGOPTIONS: EMBROIDERY!$B$69:$B$71
Name EMBPRICING: EMBROIDERY!$D$52:$CX$67
Name EMBPRICING: TRANSFERS!#REF!
Name EMBPRICING: [1]SCREENPRINT!#REF!
Name EMBQTY: TRANSFERS!#REF!
Name EMBQTY: EMBROIDERY!$B$52:$B$67
Name EMBROIDERYCOSTS: TRANSFERS!#REF!
Name EMBROIDERYCOSTS: EMBROIDERY!$C$52:$EV$67
Name FILM_TRANSFERA7_105X75mm: TRANSFERS!$C$50:$X$60

Sheet WORKING WHOLESALE GRID
A1: PRINT - APPAREL
D2: A61 COLOURLIGHT | E2: A61 COLOURSTANDARD | F2: A61 COLOUR POLY | G2: A61 COLOURBLOCKER | H2: A61 COLOURWATERBASED | I2: A61 COLOURSPECIALTY | J2: A62 COLOURLIGHT | K2: A62 COLOURSTANDARD | L2: A62 COLOURPOLY | M2: A62 COLOURBLOCKER | N2: A62 COLOURWATERBASED | O2: A63 COLOURLIGHT | P2: A63 COLOURSTANDARD | Q2: A63 COLOURPOLY | R2: A63 COLOURBLOCKER | S2: A63 COLOURWATERBASED | T2: A64 COLOURLIGHT | U2: A64 COLOURSTANDARD | V2: A64 COLOURPOLY | W2: A64 COLOURBLOCKER | X2: A64 COLOURWATERBASED | Y2: A65 COLOURLIGHT | Z2: A65 COLOURSTANDARD | AA2: A65 COLOURPOLY | AB2: A65 COLOURBLOCKER | AC2: A65 COLOURWATERBASED | AD2: A66 COLOURLIGHT | AE2: A66 COLOURSTANDARD | AF2: A66 COLOURPOLY | AG2: A66 COLOURBLOCKER | AH2: A66 COLOURWATERBASED | AI2: A67 COLOURLIGHT | AJ2: A67 COLOURSTANDARD | AK2: A67 COLOURPOLY | AL2: A67 COLOURBLOCKER | AM2: A67 COLOURWATERBASED | AN2: A68 COLOURLIGHT | AO2: A68 COLOURSTANDARD | AP2: A68 COLOURPOLY | AQ2: A68 COLOURBLOCKER | AR2: A68 COLOURWATERBASED | AS2: A69 COLOURLIGHT | AT2: A69 COLOURSTANDARD | AU2: A69 COLOURPOLY | AV2: A69 COLOURBLOCKER | AW2: A69 COLOURWATERBASED | AX2: A610 COLOURLIGHT | AY2: A610 COLOURSTANDARD | AZ2: A610 COLOURPOLY | BA2: A610 COLOURBLOCKER | BB2: A610 COLOURWATERBASED | BC2: A51 COLOURLIGHT | BD2: A51 COLOURSTANDARD | BE2: A51 COLOURPOLY | BF2: A51 COLOURBLOCKER | BG2: ` | BH2: A51 COLOURSPECIALTY | BI2: A52 COLOURSLIGHT | BJ2: A52 COLOURSSTANDARD | BK2: A52 COLOURSPOLY | BL2: A52 COLOURBLOCKER | BM2: A52 COLOURSWATERBASED | BN2: A53 COLOURSLIGHT | BO2: A53 COLOURSSTANDARD | BP2: A53 COLOURSPOLY | BQ2: A53 COLOURBLOCKER | BR2: A53 COLOURSWATERBASED | BS2: A54 COLOURSLIGHT | BT2: A54 COLOURSSTANDARD | BU2: A54 COLOURSPOLY | BV2: A54 COLOURBLOCKER | BW2: A54 COLOURSWATERBASED | BX2: A55 COLOURSLIGHT | BY2: A55 COLOURSSTANDARD | BZ2: A55 COLOURSPOLY | CA2: A55 COLOURBLOCKER | CB2: A55 COLOURSWATERBASED | CC2: A56 COLOURSLIGHT | CD2: A56 COLOURSSTANDARD | CE2: A56 COLOURSPOLY | CF2: A56 COLOURBLOCKER | CG2: A56 COLOURSWATERBASED | CH2: A57 COLOURSLIGHT | CI2: A57 COLOURSSTANDARD | CJ2: A57 COLOURSPOLY | CK2: A557 COLOURBLOCKER | CL2: A57 COLOURSWATERBASED | CM2: A58 COLOURSLIGHT | CN2: A58 COLOURSSTANDARD | CO2: A58 COLOURSPOLY | CP2: A58 COLOURBLOCKER | CQ2: A58 COLOURSWATERBASED | CR2: A59 COLOURSLIGHT | CS2: A59 COLOURSSTANDARD | CT2: A59 COLOURSPOLY | CU2: A59 COLOURBLOCKER | CV2: A59 COLOURSWATERBASED | CW2: A510 COLOURSLIGHT | CX2: A510 COLOURSSTANDARD | CY2: A510 COLOURSPOLY | CZ2: A510 COLOURBLOCKER | DA2: A510 COLOURSWATERBASED | DB2: A4 A41 COLOURLIGHT | DC2: A41 COLOURSTANDARD | DD2: A41 COLOURPOLY | DE2: A41 COLOURBLOCKER | DF2: A41 COLOURWATERBASED | DG2: A41 COLOURSPECIALTY | DH2: A42 COLOURLIGHT | DI2: A42 COLOURSTANDARD | DJ2: A42 COLOURPOLY | DK2: A42 COLOURBLOCKER | DL2: A42 COLOURWATERBASED | DM2: A43 COLOURLIGHT | DN2: A43 COLOURSTANDARD | DO2: A43 COLOURPOLY | DP2: A43 COLOURBLOCKER | DQ2: A43 COLOURWATERBASED | DR2: A44 COLOURLIGHT | DS2: A44 COLOURSTANDARD | DT2: A44 COLOURPOLY | DU2: A44 COLOURBLOCKER | DV2: A44 COLOURWATERBASED | DW2: A45 COLOURLIGHT | DX2: A45 COLOURSTANDARD | DY2: A45 COLOURPOLY | DZ2: A45 COLOURBLOCKER | EA2: A45 COLOURWATERBASED | EB2: A46 COLOURLIGHT | EC2: A46 COLOURSTANDARD | ED2: A46 COLOURPOLY | EE2: A46 COLOURBLOCKER | EF2: A46 COLOURWATERBASED | EG2: A47 COLOURLIGHT | EH2: A47 COLOURSTANDARD | EI2: A47 COLOURPOLY | EJ2: A47 COLOURBLOCKER | EK2: A47 COLOURWATERBASED | EL2: A48 COLOURLIGHT | EM2: A48 COLOURSTANDARD | EN2: A48 COLOURPOLY | EO2: A48 COLOURBLOCKER | EP2: A48 COLOURWATERBASED | EQ2: A49 COLOURLIGHT | ER2: A49 COLOURSTANDARD | ES2: A49 COLOURPOLY | ET2: A49 COLOURBLOCKER | EU2: A49 COLOURWATERBASED | EV2: A410 COLOURLIGHT | EW2: A410 COLOURSTANDARD | EX2: A410 COLOURPOLY | EY2: A410 COLOURBLOCKER | EZ2: A410 COLOURWATERBASED | FA2: A31 COLOURLIGHT | FB2: A31 COLOURSTANDARD | FC2: A31 COLOURPOLY | FD2: A31 COLOURBLOCKER | FE2: A31 COLOURWATERBASED | FF2: A31 COLOURSPECIALTY | FG2: A32 COLOURLIGHT | FH2: A32 COLOURSTANDARD | FI2: A32 COLOURPOLY | FJ2: A32 COLOURBLOCKER | FK2: A32 COLOURWATERBASED | FL2: A33 COLOURLIGHT | FM2: A33 COLOURSTANDARD | FN2: A33 COLOURPOLY | FO2: A33 COLOURBLOCKER | FP2: A33 COLOURWATERBASED | FQ2: A34 COLOURLIGHT | FR2: A34 COLOURSTANDARD | FS2: A34 COLOURPOLY | FT2: A34 COLOURBLOCKER | FU2: A34 COLOURWATERBASED | FV2: A35 COLOURLIGHT | FW2: A35 COLOURSTANDARD | FX2: A35 COLOURPOLY | FY2: A35 COLOURBLOCKER | FZ2: A35 COLOURWATERBASED | GA2: A36 COLOURLIGHT | GB2: A36 COLOURSTANDARD | GC2: A36 COLOURPOLY | GD2: A36 COLOURBLOCKER | GE2: A36 COLOURWATERBASED | GF2: A37 COLOURLIGHT | GG2: A37 COLOURSTANDARD | GH2: A37 COLOURPOLY | GI2: A37 COLOURBLOCKER | GJ2: A37 COLOURWATERBASED | GK2: A38 COLOURLIGHT | GL2: A38 COLOURSTANDARD | GM2: A38 COLOURPOLY | GN2: A38 COLOURBLOCKER | GO2: A38 COLOURWATERBASED | GP2: A39 COLOURLIGHT | GQ2: A39 COLOURSTANDARD | GR2: A39 COLOURPOLY | GS2: A39 COLOURBLOCKER | GT2: A39 COLOURWATERBASED | GU2: A310 COLOURLIGHT | GV2: A310 COLOURSTANDARD | GW2: A310 COLOURPOLY | GX2: A310 COLOURBLOCKER | GY2: A310 COLOURWATERBASED | GZ2: A21 COLOURLIGHT | HA2: A21 COLOURSTANDARD | HB2: A21 COLOURPOLY | HC2: A21 COLOURBLOCKER | HD2: A21 COLOURWATERBASED | HE2: A21 COLOURSPECIALTY | HF2: A22 COLOUR LIGHT | HG2: A22 COLOURSTANDARD | HH2: A22 COLOURPOLY | HI2: A22 COLOURBLOCKER | HJ2: A22 COLOURWATERBASED | HK2: A23 COLOURLIGHT | HL2: A23 COLOURSTANDARD | HM2: A23 COLOURPOLY | HN2: A23COLOURBLOCKER | HO2: A23 COLOURWATERBASED | HP2: A24 COLOURLIGHT | HQ2: A24 COLOURSTANDARD | HR2: A24 COLOURPOLY | HS2: A24 COLOURBLOCKER | HT2: A24 COLOURWATERBASED | HU2: A25 COLOURLIGHT | HV2: A25 COLOURSTANDARD | HW2: A25 COLOURPOLY | HX2: A25 COLOURBLOCKER | HY2: A25 COLOURWATERBASED | HZ2: A26 COLOURLIGHT | IA2: A26 COLOURSTANDARD | IB2: A26 COLOURPOLY | IC2: A26 COLOURBLOCKER | ID2: A26 COLOURWATERBASED | IE2: A27 COLOURLIGHT | IF2: A27 COLOURSTANDARD | IG2: A27 COLOURPOLY | IH2: A27 COLOURBLOCKER | II2: A27 COLOURWATERBASED | IJ2: A28 COLOURLIGHT | IK2: A28 COLOURSTANDARD | IL2: A28 COLOURPOLY | IM2: A28 COLOURBLOCKER | IN2: A28 COLOURWATERBASED | IO2: A29 COLOURLIGHT | IP2: A29 COLOURSTANDARD | IQ2: A29 COLOURPOLY | IR2: A29 COLOURBLOCKER | IS2: A29 COLOURWATERBASED | IT2: A210 COLOURLIGHT | IU2: A210 COLOURSTANDARD | IV2: A210 COLOURPOLY | IW2: A210 COLOURBLOCKER | IX2: A210 COLOURWATERBASED | JB2: A6WB | JC2: A5WB | JD2: A4WB | JE2: A3WB | JF2: A2WB
A3: Quantity breaks | B3: 1 to 4 | D3: 35.06111 | E3: 52.510181 | F3: 70.04694 | G3: 87.693887 | I3: =SUM(D3:G3)/2.5 -> 98.124847 | J3: 52.510181 | K3: 70.04694 | L3: 87.693887 | M3: 105.4398 | O3: 70.04694 | P3: 87.693887 | Q3: 105.4398 | R3: 123.27325 | T3: 87.693887 | U3: 105.4398 | V3: 123.27325 | W3: 141.21704 | Y3: 105.4398 | Z3: 123.27325 | AA3: 141.21704 | AB3: 159.25978 | AD3: 123.27325 | AE3: 141.21704 | AF3: 159.25978 | AG3: 175.21377 | AI3: 141.21704 | AJ3: 159.25978 | AK3: 175.21377 | AL3: 191.24853 | AN3: 159.25978 | AO3: 175.21377 | AP3: 191.24853 | AQ3: 207.36406 | AS3: 175.21377 | AT3: 191.24853 | AU3: 207.36406 | AV3: 223.56036 | AX3: 191.24853 | AY3: 207.36406 | AZ3: 223.56036 | BC3: 36.173659 | BD3: 53.636846 | BE3: 71.195694 | BF3: 88.860914 | BG3: 0 | BH3: =SUM(BC3:BF3)/2.5 -> 99.946845 | BI3: 53.636846 | BJ3: 71.195694 | BK3: 88.860914 | BL3: 106.62521 | BM3: 0 | BN3: 71.195694 | BO3: 88.860914 | BP3: 106.62521 | BQ3: 124.48116 | BR3: 0 | BS3: 88.860914 | BT3: 106.62521 | BU3: 124.48116 | BV3: 142.43956 | BW3: 0 | BX3: 106.62521 | BY3: 124.48116 | BZ3: 142.43956 | CA3: 160.50104 | CB3: 0 | CC3: 124.48116 | CD3: 142.43956 | CE3: 160.50104 | CF3: 176.46021 | CG3: 0 | CH3: 142.43956 | CI3: 160.50104 | CJ3: 176.46021 | CK3: 192.50015 | CL3: 0 | CM3: 160.50104 | CN3: 176.46021 | CO3: 192.50015 | CP3: 208.62086 | CQ3: 0 | CR3: 176.46021 | CS3: 192.50015 | CT3: 208.62086 | CU3: 224.82234 | CV3: 0 | CW3: 192.50015 | CX3: 208.62086 | CY3: 224.82234 | DA3: 0 | DB3: 40.162898 | DC3: 59.575379 | DD3: 79.098325 | DE3: 98.720557 | DG3: =SUM(DB3:DE3)/2.5 -> 111.02286 | DH3: 59.575379 | DI3: 79.098325 | DJ3: 98.720557 | DK3: 118.44208 | DM3: 79.098325 | DN3: 98.720557 | DO3: 118.44208 | DP3: 138.26288 | DR3: 98.720557 | DS3: 118.44208 | DT3: 138.26288 | DU3: 158.17151 | DW3: 118.44208 | DX3: 138.26288 | DY3: 158.17151 | DZ3: 178.19084 | EB3: 138.26288 | EC3: 158.17151 | ED3: 178.19084 | EE3: 196.08272 | EG3: 158.17151 | EH3: 178.19084 | EI3: 196.08272 | EJ3: 214.05536 | EL3: 178.19084 | EM3: 196.08272 | EN3: 214.05536 | EO3: 232.10877 | EQ3: 196.08272 | ER3: 214.05536 | ES3: 232.10877 | ET3: 250.24295 | EV3: 214.05536 | EW3: 232.10877 | EX3: 250.24295 | FA3: 48.321804 | FB3: 72.474736 | FC3: 96.762841 | FD3: 121.17414 | FF3: =SUM(FA3:FD3)/2.5 -> 135.49341 | FG3: 72.474736 | FH3: 96.762841 | FI3: 121.17414 | FJ3: 145.70864 | FL3: 96.762841 | FM3: 121.17414 | FN3: 145.70864 | FO3: 170.35409 | FQ3: 121.17414 | FR3: 145.70864 | FS3: 170.35409 | FT3: 195.13493 | FV3: 145.70864 | FW3: 170.35409 | FX3: 195.13493 | FY3: 220.02662 | GA3: 170.35409 | GB3: 195.13493 | GC3: 220.02662 | GD3: 239.95202 | GF3: 195.13493 | GG3: 220.02662 | GH3: 239.95202 | GI3: 259.95818 | GK3: 220.02662 | GL3: 239.95202 | GM3: 259.95818 | GN3: 280.04511 | GP3: 239.95202 | GQ3: 259.95818 | GR3: 280.04511 | GS3: 300.21282 | GU3: 259.95818 | GV3: 280.04511 | GW3: 300.21282 | GZ3: 82.715472 | HA3: 120.51165 | HB3: 158.55347 | HC3: 196.81777 | HE3: =SUM(GZ3:HC3)/2.5 -> 223.43935 | HF3: 120.51165 | HG3: 158.55347 | HH3: 196.81777 | HI3: 235.30456 | HK3: 158.55347 | HL3: 196.81777 | HM3: 235.30456 | HN3: 274.00159 | HP3: 196.81777 | HQ3: 235.30456 | HR3: 274.00159 | HS3: 312.92182 | HU3: 235.30456 | HV3: 274.00159 | HW3: 312.92182 | HX3: 352.06362 | HZ3: 274.00159 | IA3: 312.92182 | IB3: 352.06362 | IC3: 384.11166 | IE3: 312.92182 | IF3: 352.06362 | IG3: 384.11166 | IH3: 416.32123 | IJ3: 352.06362 | IK3: 384.11166 | IL3: 416.32123 | IM3: 448.69235 | IO3: 384.11166 | IP3: 416.32123 | IQ3: 448.69235 | IR3: 481.225 | IT3: 416.32123 | IU3: 448.69235 | IV3: 481.225 | JB3: N/A | JC3: N/A | JD3: N/A | JE3: N/A | JF3: N/A
B4: 5 to 9 | D4: 14.409261 | E4: 21.208089 | F4: 28.03014 | G4: 34.896555 | I4: =SUM(D4:G4)/2.5 -> 39.417618 | J4: 21.208089 | K4: 28.03014 | L4: 34.896555 | M4: 41.796786 | O4: 28.03014 | P4: 34.896555 | Q4: 41.796786 | R4: 48.720103 | T4: 34.896555 | U4: 41.796786 | V4: 48.720103 | W4: 55.687921 | Y4: 41.796786 | Z4: 48.720103 | AA4: 55.687921 | AB4: 62.689556 | AD4: 48.720103 | AE4: 55.687921 | AF4: 62.689556 | AG4: 69.819057 | AI4: 55.687921 | AJ4: 62.689556 | AK4: 69.819057 | AL4: 76.983173 | AN4: 62.689556 | AO4: 69.819057 | AP4: 76.983173 | AQ4: 84.181905 | AS4: 69.819057 | AT4: 76.983173 | AU4: 84.181905 | AV4: 91.415252 | AX4: 76.983173 | AY4: 84.181905 | AZ4: 91.415252 | BC4: 15.13048 | BD4: 21.941244 | BE4: 28.782724 | BF4: 35.664984 | BG4: 0 | BH4: =SUM(BC4:BF4)/2.5 -> 40.607773 | BI4: 21.941244 | BJ4: 28.782724 | BK4: 35.664984 | BL4: 42.58117 | BM4: 0 | BN4: 28.782724 | BO4: 35.664984 | BP4: 42.58117 | BQ4: 49.524307 | BR4: 0 | BS4: 35.664984 | BT4: 42.58117 | BU4: 49.524307 | BV4: 56.504543 | BW4: 0 | BX4: 42.58117 | BY4: 49.524307 | BZ4: 56.504543 | CA4: 63.52246 | CB4: 0 | CC4: 49.524307 | CD4: 56.504543 | CE4: 63.52246 | CF4: 70.655512 | CG4: 0 | CH4: 56.504543 | CI4: 63.52246 | CJ4: 70.655512 | CK4: 77.82318 | CL4: 0 | CM4: 63.52246 | CN4: 70.655512 | CO4: 77.82318 | CP4: 85.025464 | CQ4: 0 | CR4: 70.655512 | CS4: 77.82318 | CT4: 85.025464 | CU4: 92.262362 | CV4: 0 | CW4: 77.82318 | CX4: 85.025464 | CY4: 92.262362 | DA4: 0 | DB4: 17.431425 | DC4: 25.225895 | DD4: 33.064994 | DE4: 40.938221 | DG4: =SUM(DB4:DE4)/2.5 -> 46.664214 | DH4: 25.225895 | DI4: 33.064994 | DJ4: 40.938221 | DK4: 48.845576 | DM4: 33.064994 | DN4: 40.938221 | DO4: 48.845576 | DP4: 56.78706 | DR4: 40.938221 | DS4: 48.845576 | DT4: 56.78706 | DU4: 64.751894 | DW4: 48.845576 | DX4: 56.78706 | DY4: 64.751894 | DZ4: 72.761588 | EB4: 56.78706 | EC4: 64.751894 | ED4: 72.761588 | EE4: 80.862775 | EG4: 64.751894 | EH4: 72.761588 | EI4: 80.862775 | EJ4: 88.998578 | EL4: 72.761588 | EM4: 80.862775 | EN4: 88.998578 | EO4: 97.168996 | EQ4: 80.862775 | ER4: 88.998578 | ES4: 97.168996 | ET4: 105.37403 | EV4: 88.998578 | EW4: 97.168996 | EX4: 105.37403 | FA4: 26.63296 | FB4: 38.074575 | FC4: 49.588548 | FD4: 61.159877 | FF4: =SUM(FA4:FD4)/2.5 -> 70.182384 | FG4: 38.074575 | FH4: 49.588548 | FI4: 61.159877 | FJ4: 72.788564 | FL4: 49.588548 | FM4: 61.159877 | FN4: 72.788564 | FO4: 84.459278 | FQ4: 61.159877 | FR4: 72.788564 | FS4: 84.459278 | FT4: 96.202613 | FV4: 72.788564 | FW4: 84.459278 | FX4: 96.202613 | FY4: 107.98784 | GA4: 84.459278 | GB4: 96.202613 | GC4: 107.98784 | GD4: 117.16798 | GF4: 96.202613 | GG4: 107.98784 | GH4: 117.16798 | GI4: 126.38274 | GK4: 107.98784 | GL4: 117.16798 | GM4: 126.38274 | GN4: 135.63211 | GP4: 117.16798 | GQ4: 126.38274 | GR4: 135.63211 | GS4: 144.9161 | GU4: 126.38274 | GV4: 135.63211 | GW4: 144.9161 | GZ4: 41.179769 | HA4: 57.53124 | HB4: 73.999696 | HC4: 90.559637 | HE4: =SUM(GZ4:HC4)/2.5 -> 105.30814 | HF4: 57.53124 | HG4: 73.999696 | HH4: 90.559637 | HI4: 107.21106 | HK4: 73.999696 | HL4: 90.559637 | HM4: 107.21106 | HN4: 123.93865 | HP4: 90.559637 | HQ4: 107.21106 | HR4: 123.93865 | HS4: 140.7622 | HU4: 107.21106 | HV4: 123.93865 | HW4: 140.7622 | HX4: 157.67251 | HZ4: 123.93865 | IA4: 140.7622 | IB4: 157.67251 | IC4: 172.06922 | IE4: 140.7622 | IF4: 157.67251 | IG4: 172.06922 | IH4: 186.53517 | IJ4: 157.67251 | IK4: 172.06922 | IL4: 186.53517 | IM4: 201.07034 | IO4: 172.06922 | IP4: 186.53517 | IQ4: 201.07034 | IR4: 215.67475 | IT4: 186.53517 | IU4: 201.07034 | IV4: 215.67475 | JB4: N/A | JC4: N/A | JD4: N/A | JE4: N/A | JF4: N/A
B5: 10 to 14 | D5: 8.968734 | E5: 12.908511 | F5: 16.859548 | G5: 20.84166 | I5: =SUM(D5:G5)/2.5 -> 23.831381 | J5: 12.908511 | K5: 16.859548 | L5: 20.84166 | M5: 24.844961 | O5: 16.859548 | P5: 20.84166 | Q5: 24.844961 | R5: 28.859389 | T5: 20.84166 | U5: 24.844961 | V5: 28.859389 | W5: 32.905025 | Y5: 24.844961 | Z5: 28.859389 | AA5: 32.905025 | AB5: 36.971851 | AD5: 28.859389 | AE5: 32.905025 | AF5: 36.971851 | AG5: 40.834128 | AI5: 32.905025 | AJ5: 36.971851 | AK5: 40.834128 | AL5: 44.715635 | AN5: 36.971851 | AO5: 40.834128 | AP5: 44.715635 | AQ5: 48.616374 | AS5: 40.834128 | AT5: 44.715635 | AU5: 48.616374 | AV5: 52.536343 | AX5: 44.715635 | AY5: 48.616374 | AZ5: 52.536343 | BC5: 9.2223332 | BD5: 13.171468 | BE5: 17.138886 | BF5: 21.134024 | BG5: 0 | BH5: =SUM(BC5:BF5)/2.5 -> 24.266684 | BI5: 13.171468 | BJ5: 17.138886 | BK5: 21.134024 | BL5: 25.150456 | BM5: 0 | BN5: 17.138886 | BO5: 21.134024 | BP5: 25.150456 | BQ5: 29.181641 | BR5: 0 | BS5: 21.134024 | BT5: 25.150456 | BU5: 29.181641 | BV5: 33.237095 | BW5: 0 | BX5: 25.150456 | BY5: 29.181641 | BZ5: 33.237095 | CA5: 37.317364 | CB5: 0 | CC5: 29.181641 | CD5: 33.237095 | CE5: 37.317364 | CF5: 41.181146 | CG5: 0 | CH5: 33.237095 | CI5: 37.317364 | CJ5: 41.181146 | CK5: 45.06416 | CL5: 0 | CM5: 37.317364 | CN5: 41.181146 | CO5: 45.06416 | CP5: 48.966403 | CQ5: 0 | CR5: 41.181146 | CS5: 45.06416 | CT5: 48.966403 | CU5: 52.887878 | CV5: 0 | CW5: 45.06416 | CX5: 48.966403 | CY5: 52.887878 | DA5: 0 | DB5: 10.077919 | DC5: 14.429046 | DD5: 18.811502 | DE5: 23.215447 | DG5: =SUM(DB5:DE5)/2.5 -> 26.613566 | DH5: 14.429046 | DI5: 18.811502 | DJ5: 23.215447 | DK5: 27.64088 | DM5: 18.811502 | DN5: 23.215447 | DO5: 27.64088 | DP5: 32.0878 | DR5: 23.215447 | DS5: 27.64088 | DT5: 32.0878 | DU5: 36.546102 | DW5: 27.64088 | DX5: 32.0878 | DY5: 36.546102 | DZ5: 41.035955 | EB5: 32.0878 | EC5: 36.546102 | ED5: 41.035955 | EE5: 45.287149 | EG5: 36.546102 | EH5: 41.035955 | EI5: 45.287149 | EJ5: 49.557573 | EL5: 41.035955 | EM5: 45.287149 | EN5: 49.557573 | EO5: 53.847228 | EQ5: 45.287149 | ER5: 49.557573 | ES5: 53.847228 | ET5: 58.156114 | EV5: 49.557573 | EW5: 53.847228 | EX5: 58.156114 | FA5: 14.855441 | FB5: 21.045622 | FC5: 27.277819 | FD5: 33.543475 | FF5: =SUM(FA5:FD5)/2.5 -> 38.688943 | FG5: 21.045622 | FH5: 27.277819 | FI5: 33.543475 | FJ5: 39.842588 | FL5: 27.277819 | FM5: 33.543475 | FN5: 39.842588 | FO5: 46.16641 | FQ5: 33.543475 | FR5: 39.842588 | FS5: 46.16641 | FT5: 52.532402 | FV5: 39.842588 | FW5: 46.16641 | FX5: 52.532402 | FY5: 58.923025 | GA5: 46.16641 | GB5: 52.532402 | GC5: 58.923025 | GD5: 63.716169 | GF5: 52.532402 | GG5: 58.923025 | GH5: 63.716169 | GI5: 68.528543 | GK5: 58.923025 | GL5: 63.716169 | GM5: 68.528543 | GN5: 73.360148 | GP5: 63.716169 | GQ5: 68.528543 | GR5: 73.360148 | GS5: 78.210983 | GU5: 68.528543 | GV5: 73.360148 | GW5: 78.210983 | GZ5: 23.491052 | HA5: 32.590053 | HB5: 41.762399 | HC5: 50.989691 | HE5: =SUM(GZ5:HC5)/2.5 -> 59.533278 | HF5: 32.590053 | HG5: 41.762399 | HH5: 50.989691 | HI5: 60.27193 | HK5: 41.762399 | HL5: 50.989691 | HM5: 60.27193 | HN5: 69.600365 | HP5: 50.989691 | HQ5: 60.27193 | HR5: 69.600365 | HS5: 78.982351 | HU5: 60.27193 | HV5: 69.600365 | HW5: 78.982351 | HX5: 88.420519 | HZ5: 69.600365 | IA5: 78.982351 | IB5: 88.420519 | IC5: 96.022548 | IE5: 78.982351 | IF5: 88.420519 | IG5: 96.022548 | IH5: 103.66304 | IJ5: 88.420519 | IK5: 96.022548 | IL5: 103.66304 | IM5: 111.34199 | IO5: 96.022548 | IP5: 103.66304 | IQ5: 111.34199 | IR5: 119.0594 | IT5: 103.66304 | IU5: 111.34199 | IV5: 119.0594 | JB5: N/A | JC5: N/A | JD5: N/A | JE5: N/A | JF5: N/A
B6: 15 to 24 | D6: 6.1721482 | E6: 8.6050747 | F6: 11.043716 | G6: 13.506602 | I6: =SUM(D6:G6)/2.5 -> 15.731016 | J6: 8.6050747 | K6: 11.043716 | L6: 13.506602 | M6: 15.984489 | O6: 11.043716 | P6: 13.506602 | Q6: 15.984489 | R6: 18.467963 | T6: 13.506602 | U6: 15.984489 | V6: 18.467963 | W6: 20.97581 | Y6: 15.984489 | Z6: 18.467963 | AA6: 20.97581 | AB6: 23.498658 | AD6: 18.467963 | AE6: 20.97581 | AF6: 23.498658 | AG6: 26.079764 | AI6: 20.97581 | AJ6: 23.498658 | AK6: 26.079764 | AL6: 28.676254 | AN6: 23.498658 | AO6: 26.079764 | AP6: 28.676254 | AQ6: 31.288129 | AS6: 26.079764 | AT6: 28.676254 | AU6: 31.288129 | AV6: 33.915389 | AX6: 28.676254 | AY6: 31.288129 | AZ6: 33.915389 | BC6: 6.3437497 | BD6: 8.7851494 | BE6: 11.238834 | BF6: 13.713629 | BG6: 0 | BH6: =SUM(BC6:BF6)/2.5 -> 16.032545 | BI6: 8.7851494 | BJ6: 11.238834 | BK6: 13.713629 | BL6: 16.203525 | BM6: 0 | BN6: 11.238834 | BO6: 13.713629 | BP6: 16.203525 | BQ6: 18.702403 | BR6: 0 | BS6: 13.713629 | BT6: 16.203525 | BU6: 18.702403 | BV6: 21.219163 | BW6: 0 | BX6: 16.203525 | BY6: 18.702403 | BZ6: 21.219163 | CA6: 23.754319 | CB6: 0 | CC6: 18.702403 | CD6: 21.219163 | CE6: 23.754319 | CF6: 26.336564 | CG6: 0 | CH6: 21.219163 | CI6: 23.754319 | CJ6: 26.336564 | CK6: 28.934193 | CL6: 0 | CM6: 23.754319 | CN6: 26.336564 | CO6: 28.934193 | CP6: 31.547207 | CQ6: 0 | CR6: 26.336564 | CS6: 28.934193 | CT6: 31.547207 | CU6: 34.175606 | CV6: 0 | CW6: 28.934193 | CX6: 31.547207 | CY6: 34.175606 | DA6: 0 | DB6: 6.8547459 | DC6: 9.5041893 | DD6: 12.178121 | DE6: 14.86734 | DG6: =SUM(DB6:DE6)/2.5 -> 17.361758 | DH6: 9.5041893 | DI6: 12.178121 | DJ6: 14.86734 | DK6: 17.571845 | DM6: 12.178121 | DN6: 14.86734 | DO6: 17.571845 | DP6: 20.291636 | DR6: 14.86734 | DS6: 17.571845 | DT6: 20.291636 | DU6: 23.017258 | DW6: 17.571845 | DX6: 20.291636 | DY6: 23.017258 | DZ6: 25.767581 | EB6: 20.291636 | EC6: 23.017258 | ED6: 25.767581 | EE6: 28.544248 | EG6: 23.017258 | EH6: 25.767581 | EI6: 28.544248 | EJ6: 31.3363 | EL6: 25.767581 | EM6: 28.544248 | EN6: 31.3363 | EO6: 34.143736 | EQ6: 28.544248 | ER6: 31.3363 | ES6: 34.143736 | ET6: 36.966558 | EV6: 31.3363 | EW6: 34.143736 | EX6: 36.966558 | FA6: 9.6673605 | FB6: 13.229577 | FC6: 16.821922 | FD6: 20.43603 | FF6: =SUM(FA6:FD6)/2.5 -> 24.061955 | FG6: 13.229577 | FH6: 16.821922 | FI6: 20.43603 | FJ6: 24.071901 | FL6: 16.821922 | FM6: 20.43603 | FN6: 24.071901 | FO6: 27.720978 | FQ6: 20.43603 | FR6: 24.071901 | FS6: 27.720978 | FT6: 31.400337 | FV6: 24.071901 | FW6: 27.720978 | FX6: 31.400337 | FY6: 35.092825 | GA6: 27.720978 | GB6: 31.400337 | GC6: 35.092825 | GD6: 38.096485 | GF6: 31.400337 | GG6: 35.092825 | GH6: 38.096485 | GI6: 41.11553 | GK6: 35.092825 | GL6: 38.096485 | GM6: 41.11553 | GN6: 44.149959 | GP6: 38.096485 | GQ6: 41.11553 | GR6: 44.149959 | GS6: 47.199773 | GU6: 41.11553 | GV6: 44.149959 | GW6: 47.199773 | GZ6: 15.849029 | HA6: 21.387612 | HB6: 26.980812 | HC6: 32.611062 | HE6: =SUM(GZ6:HC6)/2.5 -> 38.731406 | HF6: 21.387612 | HG6: 26.980812 | HH6: 32.611062 | HI6: 38.278361 | HK6: 26.980812 | HL6: 32.611062 | HM6: 38.278361 | HN6: 43.974153 | HP6: 32.611062 | HQ6: 38.278361 | HR6: 43.974153 | HS6: 49.706057 | HU6: 38.278361 | HV6: 43.974153 | HW6: 49.706057 | HX6: 55.475791 | HZ6: 43.974153 | IA6: 49.706057 | IB6: 55.475791 | IC6: 60.583041 | IE6: 49.706057 | IF6: 55.475791 | IG6: 60.583041 | IH6: 65.721061 | IJ6: 55.475791 | IK6: 60.583041 | IL6: 65.721061 | IM6: 70.889849 | IO6: 60.583041 | IP6: 65.721061 | IQ6: 70.889849 | IR6: 76.089407 | IT6: 65.721061 | IU6: 70.889849 | IV6: 76.089407 | JB6: N/A | JC6: N/A | JD6: N/A | JE6: N/A | JF6: N/A
B7: 25 to 49 | D7: 4.274334 | E7: 5.7784726 | F7: 7.2840895 | G7: 8.8086311 | I7: =SUM(D7:G7)/2.5 -> 10.458211 | J7: 5.7784726 | K7: 7.2840895 | L7: 8.8086311 | M7: 10.343394 | O7: 7.2840895 | P7: 8.8086311 | Q7: 10.343394 | R7: 11.879515 | T7: 8.8086311 | U7: 10.343394 | V7: 11.879515 | W7: 13.434681 | Y7: 10.343394 | Z7: 11.879515 | AA7: 13.434681 | AB7: 15.000069 | AD7: 11.879515 | AE7: 13.434681 | AF7: 15.000069 | AG7: 16.722168 | AI7: 13.434681 | AJ7: 15.000069 | AK7: 16.722168 | AL7: 18.455804 | AN7: 15.000069 | AO7: 16.722168 | AP7: 18.455804 | AQ7: 20.20098 | AS7: 16.722168 | AT7: 18.455804 | AU7: 20.20098 | AV7: 21.957693 | AX7: 18.455804 | AY7: 20.20098 | AZ7: 21.957693 | BC7: 4.4382448 | BD7: 5.9503817 | BE7: 7.4701846 | BF7: 9.0059614 | BG7: 0 | BH7: =SUM(BC7:BF7)/2.5 -> 10.745909 | BI7: 5.9503817 | BJ7: 7.4701846 | BK7: 9.0059614 | BL7: 10.552055 | BM7: 0 | BN7: 7.4701846 | BO7: 9.0059614 | BP7: 10.552055 | BQ7: 12.102704 | BR7: 0 | BS7: 9.0059614 | BT7: 10.552055 | BU7: 12.102704 | BV7: 13.66629 | BW7: 0 | BX7: 10.552055 | BY7: 12.102704 | BZ7: 13.66629 | CA7: 15.243295 | CB7: 0 | CC7: 12.102704 | CD7: 13.66629 | CE7: 15.243295 | CF7: 16.966491 | CG7: 0 | CH7: 13.66629 | CI7: 15.243295 | CJ7: 16.966491 | CK7: 18.701226 | CL7: 0 | CM7: 15.243295 | CN7: 16.966491 | CO7: 18.701226 | CP7: 20.447499 | CQ7: 0 | CR7: 16.966491 | CS7: 18.701226 | CT7: 20.447499 | CU7: 22.205311 | CV7: 0 | CW7: 18.701226 | CX7: 20.447499 | CY7: 22.205311 | DA7: 0 | DB7: 4.8388043 | DC7: 6.4619493 | DD7: 8.1042511 | DE7: 9.7570473 | DG7: =SUM(DB7:DE7)/2.5 -> 11.664821 | DH7: 6.4619493 | DI7: 8.1042511 | DJ7: 9.7570473 | DK7: 11.420338 | DM7: 8.1042511 | DN7: 9.7570473 | DO7: 11.420338 | DP7: 13.094122 | DR7: 9.7570473 | DS7: 11.420338 | DT7: 13.094122 | DU7: 14.769497 | DW7: 11.420338 | DX7: 13.094122 | DY7: 14.769497 | DZ7: 16.46423 | EB7: 13.094122 | EC7: 14.769497 | ED7: 16.46423 | EE7: 18.285619 | EG7: 14.769497 | EH7: 16.46423 | EI7: 18.285619 | EJ7: 20.118547 | EL7: 16.46423 | EM7: 18.285619 | EN7: 20.118547 | EO7: 21.963014 | EQ7: 18.285619 | ER7: 20.118547 | ES7: 21.963014 | ET7: 23.819019 | EV7: 20.118547 | EW7: 21.963014 | EX7: 23.819019 | FA7: 7.7329349 | FB7: 10.23866 | FC7: 12.770719 | FD7: 15.320449 | FF7: =SUM(FA7:FD7)/2.5 -> 18.425105 | FG7: 10.23866 | FH7: 12.770719 | FI7: 15.320449 | FJ7: 17.887852 | FL7: 12.770719 | FM7: 15.320449 | FN7: 17.887852 | FO7: 20.464062 | FQ7: 15.320449 | FR7: 17.887852 | FS7: 20.464062 | FT7: 23.066768 | FV7: 17.887852 | FW7: 20.464062 | FX7: 23.066768 | FY7: 25.678201 | GA7: 20.464062 | GB7: 23.066768 | GC7: 25.678201 | GD7: 27.63387 | GF7: 23.066768 | GG7: 25.678201 | GH7: 27.63387 | GI7: 29.601077 | GK7: 25.678201 | GL7: 27.63387 | GM7: 29.601077 | GN7: 31.579822 | GP7: 27.63387 | GQ7: 29.601077 | GR7: 31.579822 | GS7: 33.570106 | GU7: 29.601077 | GV7: 31.579822 | GW7: 33.570106 | GZ7: 12.283278 | HA7: 16.123686 | HB7: 20.009585 | HC7: 23.92365 | HE7: =SUM(GZ7:HC7)/2.5 -> 28.93608 | HF7: 16.123686 | HG7: 20.009585 | HH7: 23.92365 | HI7: 27.865882 | HK7: 20.009585 | HL7: 23.92365 | HM7: 27.865882 | HN7: 31.827415 | HP7: 23.92365 | HQ7: 27.865882 | HR7: 31.827415 | HS7: 35.817034 | HU7: 27.865882 | HV7: 31.827415 | HW7: 35.817034 | HX7: 39.834738 | HZ7: 31.827415 | IA7: 35.817034 | IB7: 39.834738 | IC7: 43.323335 | IE7: 35.817034 | IF7: 39.834738 | IG7: 43.323335 | IH7: 46.835008 | IJ7: 39.834738 | IK7: 43.323335 | IL7: 46.835008 | IM7: 50.369759 | IO7: 43.323335 | IP7: 46.835008 | IQ7: 50.369759 | IR7: 53.927586 | IT7: 46.835008 | IU7: 50.369759 | IV7: 53.927586 | JB7: N/A | JC7: N/A | JD7: N/A | JE7: N/A | JF7: N/A
B8: 50 to 74 | D8: 3.3825833 | E8: 4.4736061 | F8: 5.5644053 | G8: 6.6720211 | H8: =E8+$JB8 -> 5.5505291 | I8: =SUM(D8:G8)/2.5 -> 8.0370463 | J8: 4.4736061 | K8: 5.5644053 | L8: 6.6720211 | M8: 7.7879533 | N8: =K8+$JB8 -> 6.6413284 | O8: 5.5644053 | P8: 6.6720211 | Q8: 7.7879533 | R8: 8.9035422 | S8: =P8+$JB8 -> 7.7489441 | T8: 6.6720211 | U8: 7.7879533 | V8: 8.9035422 | W8: 10.036068 | X8: =U8+$JB8 -> 8.8648764 | Y8: 7.7879533 | Z8: 8.9035422 | AA8: 10.036068 | AB8: 11.176909 | AC8: =Z8+$JB8 -> 9.9804652 | AD8: 8.9035422 | AE8: 10.036068 | AF8: 11.176909 | AG8: 12.341983 | AH8: =AE8+$JB8 -> 11.112991 | AI8: 10.036068 | AJ8: 11.176909 | AK8: 12.341983 | AL8: 13.515518 | AM8: =AJ8+$JB8 -> 12.253832 | AN8: 11.176909 | AO8: 12.341983 | AP8: 13.515518 | AQ8: 14.697514 | AR8: =AO8+$JB8 -> 13.418906 | AS8: 12.341983 | AT8: 13.515518 | AU8: 14.697514 | AV8: 15.887972 | AW8: =AT8+$JB8 -> 14.592441 | AX8: 13.515518 | AY8: 14.697514 | AZ8: 15.887972 | BB8: =AY8+$JB$8 -> 15.774437 | BC8: 3.5108687 | BD8: 4.6095636 | BE8: 5.7140795 | BF8: 6.8325314 | BG8: =BD8+$JC8 -> 6.3018712 | BH8: =SUM(BC8:BF8)/2.5 -> 8.2668172 | BI8: 4.6095636 | BJ8: 5.7140795 | BK8: 6.8325314 | BL8: 7.9593944 | BM8: =BJ8+$JC8 -> 7.4063872 | BN8: 5.7140795 | BO8: 6.8325314 | BP8: 7.9593944 | BQ8: 9.0890394 | BR8: =BO8+$JC8 -> 8.5248391 | BS8: 6.8325314 | BT8: 7.9593944 | BU8: 9.0890394 | BV8: 10.229653 | BW8: =BT8+$JC8 -> 9.6517021 | BX8: 7.9593944 | BY8: 9.0890394 | BZ8: 10.229653 | CA8: 11.381709 | CB8: =BY8+$JC8 -> 10.781347 | CC8: 9.0890394 | CD8: 10.229653 | CE8: 11.381709 | CF8: 12.54772 | CG8: =CD8+$JC8 -> 11.921961 | CH8: 10.229653 | CI8: 11.381709 | CJ8: 12.54772 | CK8: 13.722192 | CL8: =CI8+$JC8 -> 13.074017 | CM8: 11.381709 | CN8: 12.54772 | CO8: 13.722192 | CP8: 14.905126 | CQ8: =CN8+$JC8 -> 14.240028 | CR8: 12.54772 | CS8: 13.722192 | CT8: 14.905126 | CU8: 16.096522 | CV8: =CS8+$JC8 -> 15.4145 | CW8: 13.722192 | CX8: 14.905126 | CY8: 16.096522 | DA8: =CX8+$JC8 -> 16.597434 | DB8: 3.7875744 | DC8: 4.9389791 | DD8: 6.1074304 | DE8: 7.2844682 | DF8: =DC8+$JB8 -> 6.0159022 | DG8: =SUM(DB8:DE8)/2.5 -> 8.8473808 | DH8: 4.9389791 | DI8: 6.1074304 | DJ8: 7.2844682 | DK8: 8.4700925 | DL8: =DI8+$JD8 -> 9.4920458 | DM8: 6.1074304 | DN8: 7.2844682 | DO8: 8.4700925 | DP8: 9.6643034 | DQ8: =DN8+$JD8 -> 10.669084 | DR8: 7.2844682 | DS8: 8.4700925 | DT8: 9.6643034 | DU8: 10.858401 | DV8: =DS8+$JD8 -> 11.854708 | DW8: 8.4700925 | DX8: 9.6643034 | DY8: 10.858401 | DZ8: 12.069745 | EA8: =DX8+$JD8 -> 13.048919 | EB8: 9.6643034 | EC8: 10.858401 | ED8: 12.069745 | EE8: 13.275958 | EF8: =EC8+$JD8 -> 14.243016 | EG8: 10.858401 | EH8: 12.069745 | EI8: 13.275958 | EJ8: 14.490632 | EK8: =EH8+$JD8 -> 15.45436 | EL8: 12.069745 | EM8: 13.275958 | EN8: 14.490632 | EO8: 15.713768 | EP8: =EM8+$JD8 -> 16.660573 | EQ8: 13.275958 | ER8: 14.490632 | ES8: 15.713768 | ET8: 16.945366 | EU8: =ER8+$JD8 -> 17.875248 | EV8: 14.490632 | EW8: 15.713768 | EX8: 16.945366 | EZ8: =EW8+$JD8 -> 19.098384 | FA8: 6.0230384 | FB8: 7.6822246 | FC8: 9.3625966 | FD8: 11.055694 | FE8: =FB8+$JE8 -> 14.451455 | FF8: =SUM(FA8:FD8)/2.5 -> 13.649422 | FG8: 7.6822246 | FH8: 9.3625966 | FI8: 11.055694 | FJ8: 12.761518 | FK8: =FH8+$JE8 -> 16.131827 | FL8: 9.3625966 | FM8: 11.055694 | FN8: 12.761518 | FO8: 14.471407 | FP8: =FM8+$JE8 -> 17.824925 | FQ8: 11.055694 | FR8: 12.761518 | FS8: 14.471407 | FT8: 16.202642 | FU8: =FR8+$JE8 -> 19.530749 | FV8: 12.761518 | FW8: 14.471407 | FX8: 16.202642 | FY8: 17.937863 | FZ8: =FW8+$JE8 -> 21.240638 | GA8: 14.471407 | GB8: 16.202642 | GC8: 17.937863 | GD8: 19.226512 | GE8: =GB8+$JE8 -> 22.971873 | GF8: 16.202642 | GG8: 17.937863 | GH8: 19.226512 | GI8: 20.523623 | GJ8: =GG8+$JE8 -> 24.707094 | GK8: 17.937863 | GL8: 19.226512 | GM8: 20.523623 | GN8: 21.829195 | GO8: =GL8+$JE8 -> 25.995743 | GP8: 19.226512 | GQ8: 20.523623 | GR8: 21.829195 | GS8: 23.143229 | GT8: =GQ8+$JE8 -> 27.292854 | GU8: 20.523623 | GV8: 21.829195 | GW8: 23.143229 | GY8: =GV8+$JE8 -> 28.598426 | GZ8: 9.6759974 | HA8: 12.351973 | HB8: 15.066181 | HC8: 17.801701 | HD8: =HA8+$JF8 -> 20.044281 | HE8: =SUM(GZ8:HC8)/2.5 -> 21.958341 | HF8: 12.351973 | HG8: 15.066181 | HH8: 17.801701 | HI8: 20.558533 | HJ8: =HG8+$JF8 -> 22.758489 | HK8: 15.066181 | HL8: 17.801701 | HM8: 20.558533 | HN8: 23.328018 | HO8: =HL8+$JF8 -> 25.494009 | HP8: 17.801701 | HQ8: 20.558533 | HR8: 23.328018 | HS8: 26.118735 | HT8: =HQ8+$JF8 -> 28.250841 | HU8: 20.558533 | HV8: 23.328018 | HW8: 26.118735 | HX8: 28.930684 | HY8: =HV8+$JF8 -> 31.020326 | HZ8: 23.328018 | IA8: 26.118735 | IB8: 28.930684 | IC8: 31.290931 | ID8: =IA8+$JF8 -> 33.811043 | IE8: 26.118735 | IF8: 28.930684 | IG8: 31.290931 | IH8: 33.668101 | II8: =IF8+$JF8 -> 36.622992 | IJ8: 28.930684 | IK8: 31.290931 | IL8: 33.668101 | IM8: 36.062194 | IN8: =IK8+$JF8 -> 38.983239 | IO8: 31.290931 | IP8: 33.668101 | IQ8: 36.062194 | IR8: 38.473211 | IS8: =IP8+$JF8 -> 41.360409 | IT8: 33.668101 | IU8: 36.062194 | IV8: 38.473211 | IX8: =IU8+$JF8 -> 43.754502 | JB8: 1.0769231 | JC8: 1.6923077 | JD8: 3.3846154 | JE8: 6.7692308 | JF8: 7.6923077
B9: 75 to99 | D9: 2.9350143 | E9: 3.8216713 | F9: 4.7074059 | G9: 5.6088565 | H9: =E9+$JB9 -> 4.7447483 | I9: =SUM(D9:G9)/2.5 -> 6.8291792 | J9: 3.8216713 | K9: 4.7074059 | L9: 5.6088565 | M9: 6.5177236 | N9: =K9+$JB9 -> 5.6304828 | O9: 4.7074059 | P9: 5.6088565 | Q9: 6.5177236 | R9: 7.4255495 | S9: =P9+$JB9 -> 6.5319334 | T9: 5.6088565 | U9: 6.5177236 | V9: 7.4255495 | W9: 8.3492102 | X9: =U9+$JB9 -> 7.4408006 | Y9: 6.5177236 | Z9: 7.4255495 | AA9: 8.3492102 | AB9: 9.2802875 | AC9: =Z9+$JB9 -> 8.3486264 | AD9: 7.4255495 | AE9: 8.3492102 | AF9: 9.2802875 | AG9: 10.248628 | AH9: =AE9+$JB9 -> 9.2722871 | AI9: 8.3492102 | AJ9: 9.2802875 | AK9: 10.248628 | AL9: 11.224661 | AM9: =AJ9+$JB9 -> 10.203364 | AN9: 9.2802875 | AO9: 10.248628 | AP9: 11.224661 | AQ9: 12.208386 | AR9: =AO9+$JB9 -> 11.171705 | AS9: 10.248628 | AT9: 11.224661 | AU9: 12.208386 | AV9: 13.199804 | AW9: =AT9+$JB9 -> 12.147738 | AX9: 11.224661 | AY9: 12.208386 | AZ9: 13.199804 | BB9: =AY9+$JB$8 -> 13.285309 | BC9: 3.057879 | BD9: 3.9520242 | BE9: 4.8511501 | BF9: 5.7631808 | BG9: =BD9+$JC9 -> 5.4904857 | BH9: =SUM(BC9:BF9)/2.5 -> 7.0496936 | BI9: 3.9520242 | BJ9: 4.8511501 | BK9: 5.7631808 | BL9: 6.6827217 | BM9: =BJ9+$JC9 -> 6.3896116 | BN9: 4.8511501 | BO9: 5.7631808 | BP9: 6.6827217 | BQ9: 7.6042752 | BR9: =BO9+$JC9 -> 7.3016423 | BS9: 5.7631808 | BT9: 6.6827217 | BU9: 7.6042752 | BV9: 8.5358365 | BW9: =BT9+$JC9 -> 8.2211832 | BX9: 6.6827217 | BY9: 7.6042752 | BZ9: 8.5358365 | CA9: 9.4778684 | CB9: =BY9+$JC9 -> 9.1427367 | CC9: 7.6042752 | CD9: 8.5358365 | CE9: 9.4778684 | CF9: 10.447126 | CG9: =CD9+$JC9 -> 10.074298 | CH9: 8.5358365 | CI9: 9.4778684 | CJ9: 10.447126 | CK9: 11.424076 | CL9: =CI9+$JC9 -> 11.01633 | CM9: 9.4778684 | CN9: 10.447126 | CO9: 11.424076 | CP9: 12.408718 | CQ9: =CN9+$JC9 -> 11.985587 | CR9: 10.447126 | CS9: 11.424076 | CT9: 12.408718 | CU9: 13.401052 | CV9: =CS9+$JC9 -> 12.962537 | CW9: 11.424076 | CX9: 12.408718 | CY9: 13.401052 | DA9: =CX9+$JC9 -> 13.947179 | DB9: 3.3052869 | DC9: 4.2325695 | DD9: 5.1757959 | DE9: 6.1267062 | DF9: =DC9+$JB9 -> 5.1556464 | DG9: =SUM(DB9:DE9)/2.5 -> 7.5361434 | DH9: 4.2325695 | DI9: 5.1757959 | DJ9: 6.1267062 | DK9: 7.0853006 | DL9: =DI9+$JD9 -> 8.2527189 | DM9: 5.1757959 | DN9: 6.1267062 | DO9: 7.0853006 | DP9: 8.0515789 | DQ9: =DN9+$JD9 -> 9.2036293 | DR9: 6.1267062 | DS9: 7.0853006 | DT9: 8.0515789 | DU9: 9.0170437 | DV9: =DS9+$JD9 -> 10.162224 | DW9: 7.0853006 | DX9: 8.0515789 | DY9: 9.0170437 | DZ9: 9.9986504 | EA9: =DX9+$JD9 -> 11.128502 | EB9: 8.0515789 | EC9: 9.0170437 | ED9: 9.9986504 | EE9: 10.988841 | EF9: =EC9+$JD9 -> 12.093967 | EG9: 9.0170437 | EH9: 9.9986504 | EI9: 10.988841 | EJ9: 11.986725 | EK9: =EH9+$JD9 -> 13.075573 | EL9: 9.9986504 | EM9: 10.988841 | EN9: 11.986725 | EO9: 12.9923 | EP9: =EM9+$JD9 -> 14.065764 | EQ9: 10.988841 | ER9: 11.986725 | ES9: 12.9923 | ET9: 14.005568 | EU9: =ER9+$JD9 -> 15.063648 | EV9: 11.986725 | EW9: 12.9923 | EX9: 14.005568 | EZ9: =EW9+$JD9 -> 16.069223 | FA9: 4.9365294 | FB9: 6.153748 | FC9: 7.389178 | FD9: 8.6348001 | FE9: =FB9+$JE9 -> 12.307594 | FF9: =SUM(FA9:FD9)/2.5 -> 10.845702 | FG9: 6.153748 | FH9: 7.389178 | FI9: 8.6348001 | FJ9: 9.8906145 | FK9: =FH9+$JE9 -> 13.543024 | FL9: 7.389178 | FM9: 8.6348001 | FN9: 9.8906145 | FO9: 11.148409 | FP9: =FM9+$JE9 -> 14.788646 | FQ9: 8.6348001 | FR9: 9.8906145 | FS9: 11.148409 | FT9: 12.42457 | FU9: =FR9+$JE9 -> 16.044461 | FV9: 9.8906145 | FW9: 11.148409 | FX9: 12.42457 | FY9: 13.702634 | FZ9: =FW9+$JE9 -> 17.302256 | GA9: 11.148409 | GB9: 12.42457 | GC9: 13.702634 | GD9: 14.728529 | GE9: =GB9+$JE9 -> 18.578416 | GF9: 12.42457 | GG9: 13.702634 | GH9: 14.728529 | GI9: 15.762117 | GJ9: =GG9+$JE9 -> 19.85648 | GK9: 13.702634 | GL9: 14.728529 | GM9: 15.762117 | GN9: 16.803398 | GO9: =GL9+$JE9 -> 20.882375 | GP9: 14.728529 | GQ9: 15.762117 | GR9: 16.803398 | GS9: 17.85237 | GT9: =GQ9+$JE9 -> 21.915963 | GU9: 15.762117 | GV9: 16.803398 | GW9: 17.85237 | GY9: =GV9+$JE9 -> 22.957244 | GZ9: 8.184124 | HA9: 10.270933 | HB9: 12.391897 | HC9: 14.530737 | HD9: =HA9+$JF9 -> 17.19401 | HE9: =SUM(GZ9:HC9)/2.5 -> 18.151076 | HF9: 10.270933 | HG9: 12.391897 | HH9: 14.530737 | HI9: 16.687454 | HJ9: =HG9+$JF9 -> 19.314974 | HK9: 12.391897 | HL9: 14.530737 | HM9: 16.687454 | HN9: 18.853835 | HO9: =HL9+$JF9 -> 21.453814 | HP9: 14.530737 | HQ9: 16.687454 | HR9: 18.853835 | HS9: 21.037767 | HT9: =HQ9+$JF9 -> 23.61053 | HU9: 16.687454 | HV9: 18.853835 | HW9: 21.037767 | HX9: 23.239746 | HY9: =HV9+$JF9 -> 25.776911 | HZ9: 18.853835 | IA9: 21.037767 | IB9: 23.239746 | IC9: 25.19814 | ID9: =IA9+$JF9 -> 27.960844 | IE9: 21.037767 | IF9: 23.239746 | IG9: 25.19814 | IH9: 27.171919 | II9: =IF9+$JF9 -> 30.162823 | IJ9: 23.239746 | IK9: 25.19814 | IL9: 27.171919 | IM9: 29.161082 | IN9: =IK9+$JF9 -> 32.121217 | IO9: 25.19814 | IP9: 27.171919 | IQ9: 29.161082 | IR9: 31.165631 | IS9: =IP9+$JF9 -> 34.094996 | IT9: 27.171919 | IU9: 29.161082 | IV9: 31.165631 | IX9: =IU9+$JF9 -> 36.084159 | JB9: 0.92307692 | JC9: 1.5384615 | JD9: 3.0769231 | JE9: 6.1538462 | JF9: 6.9230769
B10: 100 to 249 | D10: 2.4673085 | E10: 3.1420665 | F10: 3.8149296 | G10: 4.5023353 | H10: =E10+$JB10 -> 3.9112973 | I10: =SUM(D10:G10)/2.5 -> 5.570656 | J10: 3.1420665 | K10: 3.8149296 | L10: 4.5023353 | M10: 5.1960846 | N10: =K10+$JB10 -> 4.5841603 | O10: 3.8149296 | P10: 4.5023353 | Q10: 5.1960846 | R10: 5.8878213 | S10: =P10+$JB10 -> 5.2715661 | T10: 4.5023353 | U10: 5.1960846 | V10: 5.8878213 | W10: 6.5942183 | X10: =U10+$JB10 -> 5.9653154 | Y10: 5.1960846 | Z10: 5.8878213 | AA10: 6.5942183 | AB10: 7.3069589 | AC10: =Z10+$JB10 -> 6.657052 | AD10: 5.8878213 | AE10: 6.5942183 | AF10: 7.3069589 | AG10: 8.0886371 | AH10: =AE10+$JB10 -> 7.3634491 | AI10: 6.5942183 | AJ10: 7.3069589 | AK10: 8.0886371 | AL10: 8.8772383 | AM10: =AJ10+$JB10 -> 8.0761897 | AN10: 7.3069589 | AO10: 8.0886371 | AP10: 8.8772383 | AQ10: 9.6727626 | AR10: =AO10+$JB10 -> 8.8578678 | AS10: 8.0886371 | AT10: 8.8772383 | AU10: 9.6727626 | AV10: 10.47521 | AW10: =AT10+$JB10 -> 9.6464691 | AX10: 8.8772383 | AY10: 9.6727626 | AZ10: 10.47521 | BB10: =AY10+$JB$8 -> 10.749686 | BC10: 2.584075 | BD10: 3.2715907 | BE10: 3.9630951 | BF10: 4.6664167 | BG10: =BD10+$JC10 -> 4.6562061 | BH10: =SUM(BC10:BF10)/2.5 -> 5.794071 | BI10: 3.2715907 | BJ10: 3.9630951 | BK10: 4.6664167 | BL10: 5.376226 | BM10: =BJ10+$JC10 -> 5.3477105 | BN10: 3.9630951 | BO10: 4.6664167 | BP10: 5.376226 | BQ10: 6.0870914 | BR10: =BO10+$JC10 -> 6.0510321 | BS10: 4.6664167 | BT10: 5.376226 | BU10: 6.0870914 | BV10: 6.8069122 | BW10: =BT10+$JC10 -> 6.7608414 | BX10: 5.376226 | BY10: 6.0870914 | BZ10: 6.8069122 | CA10: 7.5361452 | CB10: =BY10+$JC10 -> 7.4717068 | CC10: 6.0870914 | CD10: 6.8069122 | CE10: 7.5361452 | CF10: 8.3188894 | CG10: =CD10+$JC10 -> 8.1915276 | CH10: 6.8069122 | CI10: 7.5361452 | CJ10: 8.3188894 | CK10: 9.1085566 | CL10: =CI10+$JC10 -> 8.9207606 | CM10: 7.5361452 | CN10: 8.3188894 | CO10: 9.1085566 | CP10: 9.9051469 | CQ10: =CN10+$JC10 -> 9.7035048 | CR10: 8.3188894 | CS10: 9.1085566 | CT10: 9.9051469 | CU10: 10.70866 | CV10: =CS10+$JC10 -> 10.493172 | CW10: 9.1085566 | CX10: 9.9051469 | CY10: 10.70866 | DA10: =CX10+$JC10 -> 11.289762 | DB10: 2.800927 | DC10: 3.5121356 | DD10: 4.2382597 | DE10: 4.9711393 | DF10: =DC10+$JB10 -> 4.2813664 | DG10: =SUM(DB10:DE10)/2.5 -> 6.2089846 | DH10: 3.5121356 | DI10: 4.2382597 | DJ10: 4.9711393 | DK10: 5.7107742 | DL10: =DI10+$JD10 -> 7.0074905 | DM10: 4.2382597 | DN10: 4.9711393 | DO10: 5.7107742 | DP10: 6.4571646 | DQ10: =DN10+$JD10 -> 7.74037 | DR10: 4.9711393 | DS10: 5.7107742 | DT10: 6.4571646 | DU10: 7.201915 | DV10: =DS10+$JD10 -> 8.480005 | DW10: 5.7107742 | DX10: 6.4571646 | DY10: 7.201915 | DZ10: 7.961777 | EA10: =DX10+$JD10 -> 9.2263954 | EB10: 6.4571646 | EC10: 7.201915 | ED10: 7.961777 | EE10: 8.7465009 | EF10: =EC10+$JD10 -> 9.9711458 | EG10: 7.201915 | EH10: 7.961777 | EI10: 8.7465009 | EJ10: 9.5381478 | EK10: =EH10+$JD10 -> 10.731008 | EL10: 7.961777 | EM10: 8.7465009 | EN10: 9.5381478 | EO10: 10.336718 | EP10: =EM10+$JD10 -> 11.515732 | EQ10: 8.7465009 | ER10: 9.5381478 | ES10: 10.336718 | ET10: 11.142211 | EU10: =ER10+$JD10 -> 12.307379 | EV10: 9.5381478 | EW10: 10.336718 | EX10: 11.142211 | EZ10: =EW10+$JD10 -> 13.105949 | FA10: 4.3113587 | FB10: 5.2834257 | FC10: 6.2718656 | FD10: 7.2694785 | FE10: =FB10+$JE10 -> 10.821887 | FF10: =SUM(FA10:FD10)/2.5 -> 9.2544514 | FG10: 5.2834257 | FH10: 6.2718656 | FI10: 7.2694785 | FJ10: 8.2762643 | FK10: =FH10+$JE10 -> 11.810327 | FL10: 6.2718656 | FM10: 7.2694785 | FN10: 8.2762643 | FO10: 9.28485 | FP10: =FM10+$JE10 -> 12.80794 | FQ10: 7.2694785 | FR10: 8.2762643 | FS10: 9.28485 | FT10: 10.309947 | FU10: =FR10+$JE10 -> 13.814726 | FV10: 8.2762643 | FW10: 9.28485 | FX10: 10.309947 | FY10: 11.336775 | FZ10: =FW10+$JE10 -> 14.823312 | GA10: 9.28485 | GB10: 10.309947 | GC10: 11.336775 | GD10: 12.137196 | GE10: =GB10+$JE10 -> 15.848409 | GF10: 10.309947 | GG10: 11.336775 | GH10: 12.137196 | GI10: 12.944541 | GJ10: =GG10+$JE10 -> 16.875236 | GK10: 11.336775 | GL10: 12.137196 | GM10: 12.944541 | GN10: 13.758809 | GO10: =GL10+$JE10 -> 17.675658 | GP10: 12.137196 | GQ10: 12.944541 | GR10: 13.758809 | GS10: 14.579999 | GT10: =GQ10+$JE10 -> 18.483003 | GU10: 12.944541 | GV10: 13.758809 | GW10: 14.579999 | GY10: =GV10+$JE10 -> 19.29727 | GZ10: 7.1122857 | HA10: 8.7955613 | HB10: 10.510125 | HC10: 12.240618 | HD10: =HA10+$JF10 -> 14.949407 | HE10: =SUM(GZ10:HC10)/2.5 -> 15.463436 | HF10: 8.7955613 | HG10: 10.510125 | HH10: 12.240618 | HI10: 13.987039 | HJ10: =HG10+$JF10 -> 16.663972 | HK10: 10.510125 | HL10: 12.240618 | HM10: 13.987039 | HN10: 15.742015 | HO10: =HL10+$JF10 -> 18.394464 | HP10: 12.240618 | HQ10: 13.987039 | HR10: 15.742015 | HS10: 17.511862 | HT10: =HQ10+$JF10 -> 20.140885 | HU10: 13.987039 | HV10: 15.742015 | HW10: 17.511862 | HX10: 19.298552 | HY10: =HV10+$JF10 -> 21.895861 | HZ10: 15.742015 | IA10: 17.511862 | IB10: 19.298552 | IC10: 20.883697 | ID10: =IA10+$JF10 -> 23.665708 | IE10: 17.511862 | IF10: 19.298552 | IG10: 20.883697 | IH10: 22.482689 | II10: =IF10+$JF10 -> 25.452398 | IJ10: 19.298552 | IK10: 20.883697 | IL10: 22.482689 | IM10: 24.095526 | IN10: =IK10+$JF10 -> 27.037543 | IO10: 20.883697 | IP10: 22.482689 | IQ10: 24.095526 | IR10: 25.72221 | IS10: =IP10+$JF10 -> 28.636535 | IT10: 22.482689 | IU10: 24.095526 | IV10: 25.72221 | IX10: =IU10+$JF10 -> 30.249373 | JB10: 0.76923077 | JC10: 1.3846154 | JD10: 2.7692308 | JE10: 5.5384615 | JF10: 6.1538462
B11: 250 to 499 | D11: 2.1655423 | E11: 2.7542058 | F11: 3.3402777 | G11: 3.9399955 | H11: =E11+$JB11 -> 3.4465135 | I11: =SUM(D11:G11)/2.5 -> 4.8800085 | J11: 2.7542058 | K11: 3.3402777 | L11: 3.9399955 | M11: 4.5452598 | N11: =K11+$JB11 -> 4.0325854 | O11: 3.3402777 | P11: 3.9399955 | Q11: 4.5452598 | R11: 5.1478159 | S11: =P11+$JB11 -> 4.6323031 | T11: 3.9399955 | U11: 4.5452598 | V11: 5.1478159 | W11: 5.7641344 | X11: =U11+$JB11 -> 5.2375675 | Y11: 4.5452598 | Z11: 5.1478159 | AA11: 5.7641344 | AB11: 6.3859996 | AC11: =Z11+$JB11 -> 5.8401236 | AD11: 5.1478159 | AE11: 5.7641344 | AF11: 6.3859996 | AG11: 7.078848 | AH11: =AE11+$JB11 -> 6.4564421 | AI11: 5.7641344 | AJ11: 6.3859996 | AK11: 7.078848 | AL11: 7.7778504 | AM11: =AJ11+$JB11 -> 7.0783073 | AN11: 6.3859996 | AO11: 7.078848 | AP11: 7.7778504 | AQ11: 8.4830065 | AR11: =AO11+$JB11 -> 7.7711557 | AS11: 7.078848 | AT11: 7.7778504 | AU11: 8.4830065 | AV11: 9.1943166 | AW11: =AT11+$JB11 -> 8.4701581 | AX11: 7.7778504 | AY11: 8.4830065 | AZ11: 9.1943166 | BB11: =AY11+$JB$8 -> 9.5599296 | BC11: 2.272748 | BD11: 2.8739761 | BE11: 3.4784248 | BF11: 4.0938274 | BG11: =BD11+$JC11 -> 4.1047453 | BH11: =SUM(BC11:BF11)/2.5 -> 5.0875905 | BI11: 2.8739761 | BJ11: 3.4784248 | BK11: 4.0938274 | BL11: 4.7149194 | BM11: =BJ11+$JC11 -> 4.709194 | BN11: 3.4784248 | BO11: 4.0938274 | BP11: 4.7149194 | BQ11: 5.336335 | BR11: =BO11+$JC11 -> 5.3245967 | BS11: 4.0938274 | BT11: 4.7149194 | BU11: 5.336335 | BV11: 5.9658776 | BW11: =BT11+$JC11 -> 5.9456886 | BX11: 4.7149194 | BY11: 5.336335 | BZ11: 5.9658776 | CA11: 6.6039986 | CB11: =BY11+$JC11 -> 6.5671043 | CC11: 5.336335 | CD11: 5.9658776 | CE11: 6.6039986 | CF11: 7.2978634 | CG11: =CD11+$JC11 -> 7.1966468 | CH11: 5.9658776 | CI11: 6.6039986 | CJ11: 7.2978634 | CK11: 7.997882 | CL11: =CI11+$JC11 -> 7.8347678 | CM11: 6.6039986 | CN11: 7.2978634 | CO11: 7.997882 | CP11: 8.7040545 | CQ11: =CN11+$JC11 -> 8.5286326 | CR11: 7.2978634 | CS11: 7.997882 | CT11: 8.7040545 | CU11: 9.4163808 | CV11: =CS11+$JC11 -> 9.2286513 | CW11: 7.997882 | CX11: 8.7040545 | CY11: 9.4163808 | DA11: =CX11+$JC11 -> 9.9348237 | DB11: 2.4718442 | DC11: 3.0964065 | DD11: 3.7349837 | DE11: 4.3795154 | DF11: =DC11+$JB11 -> 3.7887142 | DG11: =SUM(DB11:DE11)/2.5 -> 5.4730999 | DH11: 3.0964065 | DI11: 3.7349837 | DJ11: 4.3795154 | DK11: 5.0300015 | DL11: =DI11+$JD11 -> 6.1965222 | DM11: 3.7349837 | DN11: 4.3795154 | DO11: 5.0300015 | DP11: 5.6864421 | DQ11: =DN11+$JD11 -> 6.8410539 | DR11: 4.3795154 | DS11: 5.0300015 | DT11: 5.6864421 | DU11: 6.3405434 | DV11: =DS11+$JD11 -> 7.49154 | DW11: 5.0300015 | DX11: 5.6864421 | DY11: 6.3405434 | DZ11: 7.0088539 | EA11: =DX11+$JD11 -> 8.1479805 | EB11: 5.6864421 | EC11: 6.3405434 | ED11: 7.0088539 | EE11: 7.7046062 | EF11: =EC11+$JD11 -> 8.8020818 | EG11: 6.3405434 | EH11: 7.0088539 | EI11: 7.7046062 | EJ11: 8.4065122 | EK11: =EH11+$JD11 -> 9.4703924 | EL11: 7.0088539 | EM11: 7.7046062 | EN11: 8.4065122 | EO11: 9.1145722 | EP11: =EM11+$JD11 -> 10.166145 | EQ11: 7.7046062 | ER11: 8.4065122 | ES11: 9.1145722 | ET11: 9.8287859 | EU11: =ER11+$JD11 -> 10.868051 | EV11: 8.4065122 | EW11: 9.1145722 | EX11: 9.8287859 | EZ11: =EW11+$JD11 -> 11.576111 | FA11: 3.8708954 | FB11: 4.7437073 | FC11: 5.6312393 | FD11: 6.527027 | FE11: =FB11+$JE11 -> 9.6667843 | FF11: =SUM(FA11:FD11)/2.5 -> 8.3091476 | FG11: 4.7437073 | FH11: 5.6312393 | FI11: 6.527027 | FJ11: 7.4310703 | FK11: =FH11+$JE11 -> 10.554316 | FL11: 5.6312393 | FM11: 6.527027 | FN11: 7.4310703 | FO11: 8.3367491 | FP11: =FM11+$JE11 -> 11.450104 | FQ11: 6.527027 | FR11: 7.4310703 | FS11: 8.3367491 | FT11: 9.2572726 | FU11: =FR11+$JE11 -> 12.354147 | FV11: 7.4310703 | FW11: 8.3367491 | FX11: 9.2572726 | FY11: 10.179369 | FZ11: =FW11+$JE11 -> 13.259826 | GA11: 8.3367491 | GB11: 9.2572726 | GC11: 10.179369 | GD11: 10.898191 | GE11: =GB11+$JE11 -> 14.18035 | GF11: 9.2572726 | GG11: 10.179369 | GH11: 10.898191 | GI11: 11.623243 | GJ11: =GG11+$JE11 -> 15.102446 | GK11: 10.179369 | GL11: 10.898191 | GM11: 11.623243 | GN11: 12.354527 | GO11: =GL11+$JE11 -> 15.821268 | GP11: 10.898191 | GQ11: 11.623243 | GR11: 12.354527 | GS11: 13.092041 | GT11: =GQ11+$JE11 -> 16.54632 | GU11: 11.623243 | GV11: 12.354527 | GW11: 13.092041 | GY11: =GV11+$JE11 -> 17.277603 | GZ11: 6.3427396 | HA11: 7.8401138 | HB11: 9.3662231 | HC11: 10.906542 | HD11: =HA11+$JF11 -> 13.378575 | HE11: =SUM(GZ11:HC11)/2.5 -> 13.782248 | HF11: 7.8401138 | HG11: 9.3662231 | HH11: 10.906542 | HI11: 12.461072 | HJ11: =HG11+$JF11 -> 14.904685 | HK11: 9.3662231 | HL11: 10.906542 | HM11: 12.461072 | HN11: 14.023191 | HO11: =HL11+$JF11 -> 16.445004 | HP11: 10.906542 | HQ11: 12.461072 | HR11: 14.023191 | HS11: 15.597816 | HT11: =HQ11+$JF11 -> 17.999533 | HU11: 12.461072 | HV11: 14.023191 | HW11: 15.597816 | HX11: 17.188223 | HY11: =HV11+$JF11 -> 19.561653 | HZ11: 14.023191 | IA11: 15.597816 | IB11: 17.188223 | IC11: 18.602797 | ID11: =IA11+$JF11 -> 21.136278 | IE11: 15.597816 | IF11: 17.188223 | IG11: 18.602797 | IH11: 20.029756 | II11: =IF11+$JF11 -> 22.726685 | IJ11: 17.188223 | IK11: 18.602797 | IL11: 20.029756 | IM11: 21.469099 | IN11: =IK11+$JF11 -> 24.141259 | IO11: 18.602797 | IP11: 20.029756 | IQ11: 21.469099 | IR11: 22.920826 | IS11: =IP11+$JF11 -> 25.568217 | IT11: 20.029756 | IU11: 21.469099 | IV11: 22.920826 | IX11: =IU11+$JF11 -> 27.00756 | JB11: 0.69230769 | JC11: 1.2307692 | JD11: 2.4615385 | JE11: 4.9230769 | JF11: 5.5384615
B12: 500 to 749 | D12: 1.993391 | E12: 2.5426862 | F12: 3.089132 | G12: 3.6487669 | H12: =E12+$JB12 -> 3.1580708 | I12: =SUM(D12:G12)/2.5 -> 4.5095904 | J12: 2.5426862 | K12: 3.089132 | L12: 3.6487669 | M12: 4.2135909 | N12: =K12+$JB12 -> 3.7045166 | O12: 3.089132 | P12: 3.6487669 | Q12: 4.2135909 | R12: 4.7754501 | S12: =P12+$JB12 -> 4.2641515 | T12: 3.6487669 | U12: 4.2135909 | V12: 4.7754501 | W12: 5.3506138 | X12: =U12+$JB12 -> 4.8289755 | Y12: 4.2135909 | Z12: 4.7754501 | AA12: 5.3506138 | AB12: 5.9309666 | AC12: =Z12+$JB12 -> 5.3908347 | AD12: 4.7754501 | AE12: 5.3506138 | AF12: 5.9309666 | AG12: 6.5375275 | AH12: =AE12+$JB12 -> 5.9659984 | AI12: 5.3506138 | AJ12: 5.9309666 | AK12: 6.5375275 | AL12: 7.1494731 | AM12: =AJ12+$JB12 -> 6.5463512 | AN12: 5.9309666 | AO12: 6.5375275 | AP12: 7.1494731 | AQ12: 7.7668033 | AR12: =AO12+$JB12 -> 7.1529121 | AS12: 6.5375275 | AT12: 7.1494731 | AU12: 7.7668033 | AV12: 8.3895181 | AW12: =AT12+$JB12 -> 7.7648577 | AX12: 7.1494731 | AY12: 7.7668033 | AZ12: 8.3895181 | BB12: =AY12+$JB$8 -> 8.8437263 | BC12: 2.0888299 | BD12: 2.6504862 | BE12: 3.2150344 | BF12: 3.790113 | BG12: =BD12+$JC12 -> 3.7274093 | BH12: =SUM(BC12:BF12)/2.5 -> 4.6977854 | BI12: 2.6504862 | BJ12: 3.2150344 | BK12: 3.790113 | BL12: 4.3705221 | BM12: =BJ12+$JC12 -> 4.2919575 | BN12: 3.2150344 | BO12: 3.790113 | BP12: 4.3705221 | BQ12: 4.9509616 | BR12: =BO12+$JC12 -> 4.8670361 | BS12: 3.790113 | BT12: 4.3705221 | BU12: 4.9509616 | BV12: 5.5391393 | BW12: =BT12+$JC12 -> 5.4474452 | BX12: 4.3705221 | BY12: 4.9509616 | BZ12: 5.5391393 | CA12: 6.1355012 | CB12: =BY12+$JC12 -> 6.0278847 | CC12: 4.9509616 | CD12: 5.5391393 | CE12: 6.1355012 | CF12: 6.7430179 | CG12: =CD12+$JC12 -> 6.6160623 | CH12: 5.5391393 | CI12: 6.1355012 | CJ12: 6.7430179 | CK12: 7.3559192 | CL12: =CI12+$JC12 -> 7.2124243 | CM12: 6.1355012 | CN12: 6.7430179 | CO12: 7.3559192 | CP12: 7.9742052 | CQ12: =CN12+$JC12 -> 7.819941 | CR12: 6.7430179 | CS12: 7.3559192 | CT12: 7.9742052 | CU12: 8.5978758 | CV12: =CS12+$JC12 -> 8.4328423 | CW12: 7.3559192 | CX12: 7.9742052 | CY12: 8.5978758 | DA12: =CX12+$JC12 -> 9.0511283 | DB12: 2.2660737 | DC12: 2.8506862 | DD12: 3.4488531 | DE12: 4.052613 | DF12: =DC12+$JB12 -> 3.4660708 | DG12: =SUM(DB12:DE12)/2.5 -> 5.0472904 | DH12: 2.8506862 | DI12: 3.4488531 | DJ12: 4.052613 | DK12: 4.6619659 | DL12: =DI12+$JD12 -> 5.6026993 | DM12: 3.4488531 | DN12: 4.052613 | DO12: 4.6619659 | DP12: 5.2769116 | DQ12: =DN12+$JD12 -> 6.2064592 | DR12: 4.052613 | DS12: 4.6619659 | DT12: 5.2769116 | DU12: 5.889258 | DV12: =DS12+$JD12 -> 6.815812 | DW12: 4.6619659 | DX12: 5.2769116 | DY12: 5.889258 | DZ12: 6.5153512 | EA12: =DX12+$JD12 -> 7.4307578 | EB12: 5.2769116 | EC12: 5.889258 | ED12: 6.5153512 | EE12: 7.1246429 | EF12: =EC12+$JD12 -> 8.0431042 | EG12: 5.889258 | EH12: 6.5153512 | EI12: 7.1246429 | EJ12: 7.7393192 | EK12: =EH12+$JD12 -> 8.6691973 | EL12: 6.5153512 | EM12: 7.1246429 | EN12: 7.7393192 | EO12: 8.3593802 | EP12: =EM12+$JD12 -> 9.2784891 | EQ12: 7.1246429 | ER12: 7.7393192 | ES12: 8.3593802 | ET12: 8.9848258 | EU12: =ER12+$JD12 -> 9.8931654 | EV12: 7.7393192 | EW12: 8.3593802 | EX12: 8.9848258 | EZ12: =EW12+$JD12 -> 10.513226 | FA12: 3.4754112 | FB12: 4.2590984 | FC12: 5.0560197 | FD12: 5.8603711 | FE12: =FB12+$JE12 -> 8.5667907 | FF12: =SUM(FA12:FD12)/2.5 -> 7.4603601 | FG12: 4.2590984 | FH12: 5.0560197 | FI12: 5.8603711 | FJ12: 6.6721525 | FK12: =FH12+$JE12 -> 9.363712 | FL12: 5.0560197 | FM12: 5.8603711 | FN12: 6.6721525 | FO12: 7.4854199 | FP12: =FM12+$JE12 -> 10.168063 | FQ12: 5.8603711 | FR12: 6.6721525 | FS12: 7.4854199 | FT12: 8.3120336 | FU12: =FR12+$JE12 -> 10.979845 | FV12: 6.6721525 | FW12: 7.4854199 | FX12: 8.3120336 | FY12: 9.1400771 | FZ12: =FW12+$JE12 -> 11.793112 | GA12: 7.4854199 | GB12: 8.3120336 | GC12: 9.1400771 | GD12: 9.7856146 | GE12: =GB12+$JE12 -> 12.619726 | GF12: 8.3120336 | GG12: 9.1400771 | GH12: 9.7856146 | GI12: 10.43676 | GJ12: =GG12+$JE12 -> 13.447769 | GK12: 9.1400771 | GL12: 9.7856146 | GM12: 10.43676 | GN12: 11.093513 | GO12: =GL12+$JE12 -> 14.093307 | GP12: 9.7856146 | GQ12: 10.43676 | GR12: 11.093513 | GS12: 11.755873 | GT12: =GQ12+$JE12 -> 14.744452 | GU12: 10.43676 | GV12: 11.093513 | GW12: 11.755873 | GY12: =GV12+$JE12 -> 15.401205 | GZ12: 5.7414849 | HA12: 7.1097846 | HB12: 8.5048728 | HC12: 9.9129841 | HD12: =HA12+$JF12 -> 12.032861 | HE12: =SUM(GZ12:HC12)/2.5 -> 12.507651 | HF12: 7.1097846 | HG12: 8.5048728 | HH12: 9.9129841 | HI12: 11.334118 | HJ12: =HG12+$JF12 -> 13.42795 | HK12: 8.5048728 | HL12: 9.9129841 | HM12: 11.334118 | HN12: 12.762332 | HO12: =HL12+$JF12 -> 14.836061 | HP12: 9.9129841 | HQ12: 11.334118 | HR12: 12.762332 | HS12: 14.201292 | HT12: =HQ12+$JF12 -> 16.257195 | HU12: 11.334118 | HV12: 12.762332 | HW12: 14.201292 | HX12: 15.655428 | HY12: =HV12+$JF12 -> 17.685408 | HZ12: 12.762332 | IA12: 14.201292 | IB12: 15.655428 | IC12: 16.910258 | ID12: =IA12+$JF12 -> 19.124369 | IE12: 14.201292 | IF12: 15.655428 | IG12: 16.910258 | IH12: 18.176079 | II12: =IF12+$JF12 -> 20.578505 | IJ12: 15.655428 | IK12: 16.910258 | IL12: 18.176079 | IM12: 19.452893 | IN12: =IK12+$JF12 -> 21.833334 | IO12: 16.910258 | IP12: 18.176079 | IQ12: 19.452893 | IR12: 20.740699 | IS12: =IP12+$JF12 -> 23.099156 | IT12: 18.176079 | IU12: 19.452893 | IV12: 20.740699 | IX12: =IU12+$JF12 -> 24.37597 | JB12: 0.61538462 | JC12: 1.0769231 | JD12: 2.1538462 | JE12: 4.3076923 | JF12: 4.9230769
B13: 750 to 999 | D13: 1.8598131 | E13: 2.3771159 | F13: 2.8914993 | G13: 3.4185631 | H13: =E13+$JB13 -> 2.9155775 | I13: =SUM(D13:G13)/2.5 -> 4.2187966 | J13: 2.3771159 | K13: 2.8914993 | L13: 3.4185631 | M13: 3.9505261 | N13: =K13+$JB13 -> 3.4299608 | O13: 2.8914993 | P13: 3.4185631 | Q13: 3.9505261 | R13: 4.4794572 | S13: =P13+$JB13 -> 3.9570246 | T13: 3.4185631 | U13: 3.9505261 | V13: 4.4794572 | W13: 5.0211812 | X13: =U13+$JB13 -> 4.4889877 | Y13: 3.9505261 | Z13: 4.4794572 | AA13: 5.0211812 | AB13: 5.5678045 | AC13: =Z13+$JB13 -> 5.0179187 | AD13: 4.4794572 | AE13: 5.0211812 | AF13: 5.5678045 | AG13: 6.0888832 | AH13: =AE13+$JB13 -> 5.5596428 | AI13: 5.0211812 | AJ13: 5.5678045 | AK13: 6.0888832 | AL13: 6.6145773 | AM13: =AJ13+$JB13 -> 6.1062661 | AN13: 5.5678045 | AO13: 6.0888832 | AP13: 6.6145773 | AQ13: 7.1448868 | AR13: =AO13+$JB13 -> 6.6273448 | AS13: 6.0888832 | AT13: 6.6145773 | AU13: 7.1448868 | AV13: 7.6798117 | AW13: =AT13+$JB13 -> 7.1530389 | AX13: 6.6145773 | AY13: 7.1448868 | AZ13: 7.6798117 | BB13: =AY13+$JB$8 -> 8.2218099 | BC13: 1.9556904 | BD13: 2.4850322 | BE13: 3.0170391 | BF13: 3.5591409 | BG13: =BD13+$JC13 -> 3.4081091 | BH13: =SUM(BC13:BF13)/2.5 -> 4.406761 | BI13: 2.4850322 | BJ13: 3.0170391 | BK13: 3.5591409 | BL13: 4.1062797 | BM13: =BJ13+$JC13 -> 3.940116 | BN13: 3.0170391 | BO13: 3.5591409 | BP13: 4.1062797 | BQ13: 4.6533003 | BR13: =BO13+$JC13 -> 4.4822178 | BS13: 3.5591409 | BT13: 4.1062797 | BU13: 4.6533003 | BV13: 5.2076998 | BW13: =BT13+$JC13 -> 5.0293566 | BX13: 4.1062797 | BY13: 4.6533003 | BZ13: 5.2076998 | CA13: 5.7699123 | CB13: =BY13+$JC13 -> 5.5763772 | CC13: 4.6533003 | CD13: 5.2076998 | CE13: 5.7699123 | CF13: 6.2919377 | CG13: =CD13+$JC13 -> 6.1307767 | CH13: 5.2076998 | CI13: 5.7699123 | CJ13: 6.2919377 | CK13: 6.8185784 | CL13: =CI13+$JC13 -> 6.6929892 | CM13: 5.7699123 | CN13: 6.2919377 | CO13: 6.8185784 | CP13: 7.3498345 | CQ13: =CN13+$JC13 -> 7.2150146 | CR13: 6.2919377 | CS13: 6.8185784 | CT13: 7.3498345 | CU13: 7.885706 | CV13: =CS13+$JC13 -> 7.7416553 | CW13: 6.8185784 | CX13: 7.3498345 | CY13: 7.885706 | DA13: =CX13+$JC13 -> 8.2729114 | DB13: 2.1337483 | DC13: 2.685448 | DD13: 3.2501844 | DE13: 3.8202139 | DF13: =DC13+$JB13 -> 3.2239095 | DG13: =SUM(DB13:DE13)/2.5 -> 4.7558378 | DH13: 2.685448 | DI13: 3.2501844 | DJ13: 3.8202139 | DK13: 4.3955363 | DL13: =DI13+$JD13 -> 5.0963383 | DM13: 3.2501844 | DN13: 3.8202139 | DO13: 4.3955363 | DP13: 4.9761517 | DQ13: =DN13+$JD13 -> 5.6663677 | DR13: 3.8202139 | DS13: 4.3955363 | DT13: 4.9761517 | DU13: 5.5540914 | DV13: =DS13+$JD13 -> 6.2416902 | DW13: 4.3955363 | DX13: 4.9761517 | DY13: 5.5540914 | DZ13: 6.1452553 | EA13: =DX13+$JD13 -> 6.8223056 | EB13: 4.9761517 | EC13: 5.5540914 | ED13: 6.1452553 | EE13: 6.6690387 | EF13: =EC13+$JD13 -> 7.4002452 | EG13: 5.5540914 | EH13: 6.1452553 | EI13: 6.6690387 | EJ13: 7.1974375 | EK13: =EH13+$JD13 -> 7.9914092 | EL13: 6.1452553 | EM13: 6.6690387 | EN13: 7.1974375 | EO13: 7.7304517 | EP13: =EM13+$JD13 -> 8.5151926 | EQ13: 6.6690387 | ER13: 7.1974375 | ES13: 7.7304517 | ET13: 8.2680812 | EU13: =ER13+$JD13 -> 9.0435913 | EV13: 7.1974375 | EW13: 7.7304517 | EX13: 8.2680812 | EZ13: =EW13+$JD13 -> 9.5766055 | FA13: 3.1203148 | FB13: 3.8239742 | FC13: 4.5395315 | FD13: 5.261776 | FE13: =FB13+$JE13 -> 7.5162818 | FF13: =SUM(FA13:FD13)/2.5 -> 6.6982386 | FG13: 3.8239742 | FH13: 4.5395315 | FI13: 5.261776 | FJ13: 5.9907076 | FK13: =FH13+$JE13 -> 8.2318392 | FL13: 4.5395315 | FM13: 5.261776 | FN13: 5.9907076 | FO13: 6.7209891 | FP13: =FM13+$JE13 -> 8.9540837 | FQ13: 5.261776 | FR13: 5.9907076 | FS13: 6.7209891 | FT13: 7.4632696 | FU13: =FR13+$JE13 -> 9.6830153 | FV13: 5.9907076 | FW13: 6.7209891 | FX13: 7.4632696 | FY13: 8.2068496 | FZ13: =FW13+$JE13 -> 10.413297 | GA13: 6.7209891 | GB13: 7.4632696 | GC13: 8.2068496 | GD13: 8.7865716 | GE13: =GB13+$JE13 -> 11.155577 | GF13: 7.4632696 | GG13: 8.2068496 | GH13: 8.7865716 | GI13: 9.3713406 | GJ13: =GG13+$JE13 -> 11.899157 | GK13: 8.2068496 | GL13: 8.7865716 | GM13: 9.3713406 | GN13: 9.9611566 | GO13: =GL13+$JE13 -> 12.478879 | GP13: 8.7865716 | GQ13: 9.3713406 | GR13: 9.9611566 | GS13: 10.556019 | GT13: =GQ13+$JE13 -> 13.063648 | GU13: 9.3713406 | GV13: 9.9611566 | GW13: 10.556019 | GY13: =GV13+$JE13 -> 13.653464 | GZ13: 5.2540631 | HA13: 6.5094221 | HB13: 7.789716 | HC13: 9.0819899 | HD13: =HA13+$JF13 -> 10.817114 | HE13: =SUM(GZ13:HC13)/2.5 -> 11.454076 | HF13: 6.5094221 | HG13: 7.789716 | HH13: 9.0819899 | HI13: 10.386244 | HJ13: =HG13+$JF13 -> 12.097408 | HK13: 7.789716 | HL13: 9.0819899 | HM13: 10.386244 | HN13: 11.697141 | HO13: =HL13+$JF13 -> 13.389682 | HP13: 9.0819899 | HQ13: 10.386244 | HR13: 11.697141 | HS13: 13.017361 | HT13: =HQ13+$JF13 -> 14.693936 | HU13: 10.386244 | HV13: 11.697141 | HW13: 13.017361 | HX13: 14.352105 | HY13: =HV13+$JF13 -> 16.004833 | HZ13: 11.697141 | IA13: 13.017361 | IB13: 14.352105 | IC13: 15.45561 | ID13: =IA13+$JF13 -> 17.325053 | IE13: 13.017361 | IF13: 14.352105 | IG13: 15.45561 | IH13: 16.568778 | II13: =IF13+$JF13 -> 18.659797 | IJ13: 14.352105 | IK13: 15.45561 | IL13: 16.568778 | IM13: 17.691608 | IN13: =IK13+$JF13 -> 19.763303 | IO13: 15.45561 | IP13: 16.568778 | IQ13: 17.691608 | IR13: 18.824101 | IS13: =IP13+$JF13 -> 20.87647 | IT13: 16.568778 | IU13: 17.691608 | IV13: 18.824101 | IX13: =IU13+$JF13 -> 21.999301 | JB13: 0.53846154 | JC13: 0.92307692 | JD13: 1.8461538 | JE13: 3.6923077 | JF13: 4.3076923
B14: 1000 to 2499 | D14: 1.7453053 | E14: 2.2350029 | F14: 2.72175 | G14: 3.2207101 | H14: =E14+$JB14 -> 2.6965413 | I14: =SUM(D14:G14)/2.5 -> 3.9691073 | J14: 2.2350029 | K14: 2.72175 | L14: 3.2207101 | M14: 3.7243197 | N14: =K14+$JB14 -> 3.1832885 | O14: 2.72175 | P14: 3.2207101 | Q14: 3.7243197 | R14: 4.2248692 | S14: =P14+$JB14 -> 3.6822486 | T14: 3.2207101 | U14: 3.7243197 | V14: 4.2248692 | W14: 4.7377413 | X14: =U14+$JB14 -> 4.1858582 | Y14: 3.7243197 | Z14: 4.2248692 | AA14: 4.7377413 | AB14: 5.255263 | AC14: =Z14+$JB14 -> 4.6864077 | AD14: 4.2248692 | AE14: 4.7377413 | AF14: 5.255263 | AG14: 5.691474 | AH14: =AE14+$JB14 -> 5.1992798 | AI14: 4.7377413 | AJ14: 5.255263 | AK14: 5.691474 | AL14: 6.1315312 | AM14: =AJ14+$JB14 -> 5.7168014 | AN14: 5.255263 | AO14: 5.691474 | AP14: 6.1315312 | AQ14: 6.5754346 | AR14: =AO14+$JB14 -> 6.1530125 | AS14: 5.691474 | AT14: 6.1315312 | AU14: 6.5754346 | AV14: 7.0231841 | AW14: =AT14+$JB14 -> 6.5930697 | AX14: 6.1315312 | AY14: 6.5754346 | AZ14: 7.0231841 | BB14: =AY14+$JB$8 -> 7.6523577 | BC14: 1.8422019 | BD14: 2.3435117 | BE14: 2.8472322 | BF14: 3.3606511 | BG14: =BD14+$JC14 -> 3.1127425 | BH14: =SUM(BC14:BF14)/2.5 -> 4.1574388 | BI14: 2.3435117 | BJ14: 2.8472322 | BK14: 3.3606511 | BL14: 3.8788521 | BM14: =BJ14+$JC14 -> 3.616463 | BN14: 2.8472322 | BO14: 3.3606511 | BP14: 3.8788521 | BQ14: 4.3968239 | BR14: =BO14+$JC14 -> 4.1298819 | BS14: 3.3606511 | BT14: 3.8788521 | BU14: 4.3968239 | BV14: 4.921922 | BW14: =BT14+$JC14 -> 4.6480829 | BX14: 3.8788521 | BY14: 4.3968239 | BZ14: 4.921922 | CA14: 5.4544331 | CB14: =BY14+$JC14 -> 5.1660547 | CC14: 4.3968239 | CD14: 4.921922 | CE14: 5.4544331 | CF14: 5.9117446 | CG14: =CD14+$JC14 -> 5.6911528 | CH14: 4.921922 | CI14: 5.4544331 | CJ14: 5.9117446 | CK14: 6.3730907 | CL14: =CI14+$JC14 -> 6.2236639 | CM14: 5.4544331 | CN14: 5.9117446 | CO14: 6.3730907 | CP14: 6.8384715 | CQ14: =CN14+$JC14 -> 6.6809754 | CR14: 5.9117446 | CS14: 6.3730907 | CT14: 6.8384715 | CU14: 7.3078868 | CV14: =CS14+$JC14 -> 7.1423215 | CW14: 6.3730907 | CX14: 6.8384715 | CY14: 7.3078868 | DA14: =CX14+$JC14 -> 7.6077022 | DB14: 2.0221527 | DC14: 2.5450282 | DD14: 3.0802707 | DE14: 3.6205416 | DF14: =DC14+$JB14 -> 3.0065666 | DG14: =SUM(DB14:DE14)/2.5 -> 4.5071973 | DH14: 2.5450282 | DI14: 3.0802707 | DJ14: 3.6205416 | DK14: 4.1658408 | DL14: =DI14+$JD14 -> 4.6187322 | DM14: 3.0802707 | DN14: 3.6205416 | DO14: 4.1658408 | DP14: 4.7161684 | DQ14: =DN14+$JD14 -> 5.1590031 | DR14: 3.6205416 | DS14: 4.1658408 | DT14: 4.7161684 | DU14: 5.2639718 | DV14: =DS14+$JD14 -> 5.7043024 | DW14: 4.1658408 | DX14: 4.7161684 | DY14: 5.2639718 | DZ14: 5.8243204 | EA14: =DX14+$JD14 -> 6.2546299 | EB14: 4.7161684 | EC14: 5.2639718 | ED14: 5.8243204 | EE14: 6.3208185 | EF14: =EC14+$JD14 -> 6.8024333 | EG14: 5.2639718 | EH14: 5.8243204 | EI14: 6.3208185 | EJ14: 6.8217012 | EK14: =EH14+$JD14 -> 7.362782 | EL14: 5.8243204 | EM14: 6.3208185 | EN14: 6.8217012 | EO14: 7.3269685 | EP14: =EM14+$JD14 -> 7.85928 | EQ14: 6.3208185 | ER14: 6.8217012 | ES14: 7.3269685 | ET14: 7.8366204 | EU14: =ER14+$JD14 -> 8.3601627 | EV14: 6.8217012 | EW14: 7.3269685 | EX14: 7.8366204 | EZ14: =EW14+$JD14 -> 8.86543 | FA14: 2.8014836 | FB14: 3.4332838 | FC14: 4.0757808 | FD14: 4.7242963 | FE14: =FB14+$JE14 -> 6.5102069 | FF14: =SUM(FA14:FD14)/2.5 -> 6.0139378 | FG14: 3.4332838 | FH14: 4.0757808 | FI14: 4.7242963 | FJ14: 5.3788301 | FK14: =FH14+$JE14 -> 7.1527039 | FL14: 4.0757808 | FM14: 4.7242963 | FN14: 5.3788301 | FO14: 6.0345902 | FP14: =FM14+$JE14 -> 7.8012193 | FQ14: 4.7242963 | FR14: 5.3788301 | FS14: 6.0345902 | FT14: 6.701138 | FU14: =FR14+$JE14 -> 8.4557531 | FV14: 5.3788301 | FW14: 6.0345902 | FX14: 6.701138 | FY14: 7.3688668 | FZ14: =FW14+$JE14 -> 9.1115133 | GA14: 6.0345902 | GB14: 6.701138 | GC14: 7.3688668 | GD14: 7.8894811 | GE14: =GB14+$JE14 -> 9.7780611 | GF14: 6.701138 | GG14: 7.3688668 | GH14: 7.8894811 | GI14: 8.4146376 | GJ14: =GG14+$JE14 -> 10.44579 | GK14: 7.3688668 | GL14: 7.8894811 | GM14: 8.4146376 | GN14: 8.9443364 | GO14: =GL14+$JE14 -> 10.966404 | GP14: 7.8894811 | GQ14: 8.4146376 | GR14: 8.9443364 | GS14: 9.4785774 | GT14: =GQ14+$JE14 -> 11.491561 | GU14: 8.4146376 | GV14: 8.9443364 | GW14: 9.4785774 | GY14: =GV14+$JE14 -> 12.021259 | GZ14: 4.8236363 | HA14: 5.9783119 | HB14: 7.1560515 | HC14: 8.3448379 | HD14: =HA14+$JF14 -> 9.6706196 | HE14: =SUM(GZ14:HC14)/2.5 -> 10.521135 | HF14: 5.9783119 | HG14: 7.1560515 | HH14: 8.3448379 | HI14: 9.5446709 | HJ14: =HG14+$JF14 -> 10.848359 | HK14: 7.1560515 | HL14: 8.3448379 | HM14: 9.5446709 | HN14: 10.750759 | HO14: =HL14+$JF14 -> 12.037146 | HP14: 8.3448379 | HQ14: 9.5446709 | HR14: 10.750759 | HS14: 11.96511 | HT14: =HQ14+$JF14 -> 13.236979 | HU14: 9.5446709 | HV14: 10.750759 | HW14: 11.96511 | HX14: 13.193187 | HY14: =HV14+$JF14 -> 14.443066 | HZ14: 10.750759 | IA14: 11.96511 | IB14: 13.193187 | IC14: 14.2103 | ID14: =IA14+$JF14 -> 15.657418 | IE14: 11.96511 | IF14: 13.193187 | IG14: 14.2103 | IH14: 15.236339 | II14: =IF14+$JF14 -> 16.885495 | IJ14: 13.193187 | IK14: 14.2103 | IL14: 15.236339 | IM14: 16.271305 | IN14: =IK14+$JF14 -> 17.902607 | IO14: 14.2103 | IP14: 15.236339 | IQ14: 16.271305 | IR14: 17.315198 | IS14: =IP14+$JF14 -> 18.928647 | IT14: 15.236339 | IU14: 16.271305 | IV14: 17.315198 | IX14: =IU14+$JF14 -> 19.963613 | JB14: 0.46153846 | JC14: 0.76923077 | JD14: 1.5384615 | JE14: 3.0769231 | JF14: 3.6923077
B15: 2500 to 4999 | D15: 1.6540157 | E15: 2.1181241 | F15: 2.579447 | G15: 3.0523548 | H15: =E15+$JB15 -> 2.5027395 | J15: 2.1181241 | K15: 2.579447 | L15: 3.0523548 | M15: 3.5296797 | N15: =K15+$JB15 -> 2.9640623 | O15: 2.579447 | P15: 3.0523548 | Q15: 3.5296797 | R15: 4.0041148 | S15: =P15+$JB15 -> 3.4369702 | T15: 3.0523548 | U15: 3.5296797 | V15: 4.0041148 | W15: 4.4902391 | X15: =U15+$JB15 -> 3.9142951 | Y15: 3.5296797 | Z15: 4.0041148 | AA15: 4.4902391 | AB15: 4.9807803 | AC15: =Z15+$JB15 -> 4.3887302 | AD15: 4.0041148 | AE15: 4.4902391 | AF15: 4.9807803 | AG15: 5.3942674 | AH15: =AE15+$JB15 -> 4.8748544 | AI15: 4.4902391 | AJ15: 4.9807803 | AK15: 5.3942674 | AL15: 5.8114083 | AM15: =AJ15+$JB15 -> 5.3653957 | AN15: 4.9807803 | AO15: 5.3942674 | AP15: 5.8114083 | AQ15: 6.232203 | AR15: =AO15+$JB15 -> 5.7788828 | AS15: 5.3942674 | AT15: 5.8114083 | AU15: 6.232203 | AV15: 6.6566516 | AW15: =AT15+$JB15 -> 6.1960237 | AX15: 5.8114083 | AY15: 6.232203 | AZ15: 6.6566516 | BB15: =AY15+$JB$8 -> 7.3091261 | BC15: 1.745844 | BD15: 2.2209585 | BE15: 2.6983685 | BF15: 3.1849807 | BG15: =BD15+$JC15 -> 2.8363431 | BI15: 2.2209585 | BJ15: 2.6983685 | BK15: 3.1849807 | BL15: 3.6761359 | BM15: =BJ15+$JC15 -> 3.3137532 | BN15: 2.6983685 | BO15: 3.1849807 | BP15: 3.6761359 | BQ15: 4.1670847 | BR15: =BO15+$JC15 -> 3.8003653 | BS15: 3.1849807 | BT15: 3.6761359 | BU15: 4.1670847 | BV15: 4.664798 | BW15: =BT15+$JC15 -> 4.2915205 | BX15: 3.6761359 | BY15: 4.1670847 | BZ15: 4.664798 | CA15: 5.1695478 | CB15: =BY15+$JC15 -> 4.7824693 | CC15: 4.1670847 | CD15: 4.664798 | CE15: 5.1695478 | CF15: 5.6030355 | CG15: =CD15+$JC15 -> 5.2801826 | CH15: 4.664798 | CI15: 5.1695478 | CJ15: 5.6030355 | CK15: 6.0403561 | CL15: =CI15+$JC15 -> 5.7849324 | CM15: 5.1695478 | CN15: 5.6030355 | CO15: 6.0403561 | CP15: 6.4815096 | CQ15: =CN15+$JC15 -> 6.2184201 | CR15: 5.6030355 | CS15: 6.0403561 | CT15: 6.4815096 | CU15: 6.926496 | CV15: =CS15+$JC15 -> 6.6557407 | CW15: 6.0403561 | CX15: 6.4815096 | CY15: 6.926496 | DA15: =CX15+$JC15 -> 7.0968942 | DB15: 1.9163824 | DC15: 2.4119367 | DD15: 2.9192229 | DE15: 3.431286 | DF15: =DC15+$JB15 -> 2.7965521 | DH15: 2.4119367 | DI15: 2.9192229 | DJ15: 3.431286 | DK15: 3.948126 | DL15: =DI15+$JD15 -> 4.1499921 | DM15: 2.9192229 | DN15: 3.431286 | DO15: 3.948126 | DP15: 4.469743 | DQ15: =DN15+$JD15 -> 4.6620552 | DR15: 3.431286 | DS15: 3.948126 | DT15: 4.469743 | DU15: 4.9889789 | DV15: =DS15+$JD15 -> 5.1788953 | DW15: 3.948126 | DX15: 4.469743 | DY15: 4.9889789 | DZ15: 5.5201159 | EA15: =DX15+$JD15 -> 5.7005122 | EB15: 4.469743 | EC15: 4.9889789 | ED15: 5.5201159 | EE15: 5.9907477 | EF15: =EC15+$JD15 -> 6.2197482 | EG15: 4.9889789 | EH15: 5.5201159 | EI15: 5.9907477 | EJ15: 6.4655449 | EK15: =EH15+$JD15 -> 6.7508851 | EL15: 5.5201159 | EM15: 5.9907477 | EN15: 6.4655449 | EO15: 6.9445075 | EP15: =EM15+$JD15 -> 7.221517 | EQ15: 5.9907477 | ER15: 6.4655449 | ES15: 6.9445075 | ET15: 7.4276355 | EU15: =ER15+$JD15 -> 7.6963142 | EV15: 6.4655449 | EW15: 6.9445075 | EX15: 7.4276355 | EZ15: =EW15+$JD15 -> 8.1752768 | FA15: 2.6549497 | FB15: 3.2537413 | FC15: 3.8626841 | FD15: 4.4773444 | FE15: =FB15+$JE15 -> 5.7152797 | FG15: 3.2537413 | FH15: 3.8626841 | FI15: 4.4773444 | FJ15: 5.0977222 | FK15: =FH15+$JE15 -> 6.3242226 | FL15: 3.8626841 | FM15: 4.4773444 | FN15: 5.0977222 | FO15: 5.7192757 | FP15: =FM15+$JE15 -> 6.9388829 | FQ15: 4.4773444 | FR15: 5.0977222 | FS15: 5.7192757 | FT15: 6.3510668 | FU15: =FR15+$JE15 -> 7.5592606 | FV15: 5.0977222 | FW15: 5.7192757 | FX15: 6.3510668 | FY15: 6.9839905 | FZ15: =FW15+$JE15 -> 8.1808142 | GA15: 5.7192757 | GB15: 6.3510668 | GC15: 6.9839905 | GD15: 7.4774954 | GE15: =GB15+$JE15 -> 8.8126053 | GF15: 6.3510668 | GG15: 6.9839905 | GH15: 7.4774954 | GI15: 7.9753153 | GJ15: =GG15+$JE15 -> 9.445529 | GK15: 6.9839905 | GL15: 7.4774954 | GM15: 7.9753153 | GN15: 8.4774503 | GO15: =GL15+$JE15 -> 9.9390338 | GP15: 7.4774954 | GQ15: 7.9753153 | GR15: 8.4774503 | GS15: 8.9839005 | GT15: =GQ15+$JE15 -> 10.436854 | GU15: 7.9753153 | GV15: 8.4774503 | GW15: 8.9839005 | GY15: =GV15+$JE15 -> 10.938989 | GZ15: 4.571332 | HA15: 5.665678 | HB15: 6.781907 | HC15: 7.9086304 | HD15: =HA15+$JF15 -> 8.7426011 | HF15: 5.665678 | HG15: 6.781907 | HH15: 7.9086304 | HI15: 9.0458482 | HJ15: =HG15+$JF15 -> 9.8588301 | HK15: 6.781907 | HL15: 7.9086304 | HM15: 9.0458482 | HN15: 10.189019 | HO15: =HL15+$JF15 -> 10.985553 | HP15: 7.9086304 | HQ15: 9.0458482 | HR15: 10.189019 | HS15: 11.340046 | HT15: =HQ15+$JF15 -> 12.122771 | HU15: 9.0458482 | HV15: 10.189019 | HW15: 11.340046 | HX15: 12.504106 | HY15: =HV15+$JF15 -> 13.265942 | HZ15: 10.189019 | IA15: 11.340046 | IB15: 12.504106 | IC15: 13.468243 | ID15: =IA15+$JF15 -> 14.416969 | IE15: 11.340046 | IF15: 12.504106 | IG15: 13.468243 | IH15: 14.44086 | II15: =IF15+$JF15 -> 15.58103 | IJ15: 12.504106 | IK15: 13.468243 | IL15: 14.44086 | IM15: 15.421958 | IN15: =IK15+$JF15 -> 16.545166 | IO15: 13.468243 | IP15: 14.44086 | IQ15: 15.421958 | IR15: 16.411536 | IS15: =IP15+$JF15 -> 17.517783 | IT15: 14.44086 | IU15: 15.421958 | IV15: 16.411536 | IX15: =IU15+$JF15 -> 18.498881 | JB15: 0.38461538 | JC15: 0.61538462 | JD15: 1.2307692 | JE15: 2.4615385 | JF15: 3.0769231
B16: 5000 to 7499 | D16: 1.5674917 | E16: 2.0073457 | F16: 2.4445699 | G16: 2.8927832 | H16: =E16+$JB16 -> 2.315038 | J16: 2.0073457 | K16: 2.4445699 | L16: 2.8927832 | M16: 3.3451928 | N16: =K16+$JB16 -> 2.7522622 | O16: 2.4445699 | P16: 2.8927832 | Q16: 3.3451928 | R16: 3.7948737 | S16: =P16+$JB16 -> 3.2004756 | T16: 2.8927832 | U16: 3.3451928 | V16: 3.7948737 | W16: 4.2556426 | X16: =U16+$JB16 -> 3.6528851 | Y16: 3.3451928 | Z16: 3.7948737 | AA16: 4.2556426 | AB16: 4.7206078 | AC16: =Z16+$JB16 -> 4.102566 | AD16: 3.7948737 | AE16: 4.2556426 | AF16: 4.7206078 | AG16: 5.1125527 | AH16: =AE16+$JB16 -> 4.563335 | AI16: 4.2556426 | AJ16: 4.7206078 | AK16: 5.1125527 | AL16: 5.5079688 | AM16: =AJ16+$JB16 -> 5.0283001 | AN16: 4.7206078 | AO16: 5.1125527 | AP16: 5.5079688 | AQ16: 5.906856 | AR16: =AO16+$JB16 -> 5.420245 | AS16: 5.1125527 | AT16: 5.5079688 | AU16: 5.906856 | AV16: 6.3092144 | AW16: =AT16+$JB16 -> 5.8156611 | AX16: 5.5079688 | AY16: 5.906856 | AZ16: 6.3092144 | BB16: =AY16+$JB$8 -> 6.9837791 | BC16: 1.6545164 | BD16: 2.1048019 | BE16: 2.5572731 | BF16: 3.0184757 | BG16: =BD16+$JC16 -> 2.5663403 | BI16: 2.1048019 | BJ16: 2.5572731 | BK16: 3.0184757 | BL16: 3.4839942 | BM16: =BJ16+$JC16 -> 3.0188116 | BN16: 2.5572731 | BO16: 3.0184757 | BP16: 3.4839942 | BQ16: 3.9493273 | BR16: =BO16+$JC16 -> 3.4800142 | BS16: 3.0184757 | BT16: 3.4839942 | BU16: 3.9493273 | BV16: 4.4210816 | BW16: =BT16+$JC16 -> 3.9455327 | BX16: 3.4839942 | BY16: 3.9493273 | BZ16: 4.4210816 | CA16: 4.8995149 | CB16: =BY16+$JC16 -> 4.4108657 | CC16: 3.9493273 | CD16: 4.4210816 | CE16: 4.8995149 | CF16: 5.310418 | CG16: =CD16+$JC16 -> 4.8826201 | CH16: 4.4210816 | CI16: 4.8995149 | CJ16: 5.310418 | CK16: 5.7249622 | CL16: =CI16+$JC16 -> 5.3610534 | CM16: 4.8995149 | CN16: 5.310418 | CO16: 5.7249622 | CP16: 6.1431477 | CQ16: =CN16+$JC16 -> 5.7719564 | CR16: 5.310418 | CS16: 5.7249622 | CT16: 6.1431477 | CU16: 6.5649745 | CV16: =CS16+$JC16 -> 6.1865007 | CW16: 5.7249622 | CX16: 6.1431477 | CY16: 6.5649745 | DA16: =CX16+$JC16 -> 6.6046862 | DB16: 1.8161336 | DC16: 2.2857918 | DD16: 2.7665792 | DE16: 3.2519046 | DF16: =DC16+$JB16 -> 2.5934842 | DH16: 2.2857918 | DI16: 2.7665792 | DJ16: 3.2519046 | DK16: 3.7417681 | DL16: =DI16+$JD16 -> 3.6896561 | DM16: 2.7665792 | DN16: 3.2519046 | DO16: 3.7417681 | DP16: 4.2361697 | DQ16: =DN16+$JD16 -> 4.1749816 | DR16: 3.2519046 | DS16: 3.7417681 | DT16: 4.2361697 | DU16: 4.7283254 | DV16: =DS16+$JD16 -> 4.6648451 | DW16: 3.7417681 | DX16: 4.2361697 | DY16: 4.7283254 | DZ16: 5.231771 | EA16: =DX16+$JD16 -> 5.1592467 | EB16: 4.2361697 | EC16: 4.7283254 | ED16: 5.231771 | EE16: 5.677882 | EF16: =EC16+$JD16 -> 5.6514024 | EG16: 4.7283254 | EH16: 5.231771 | EI16: 5.677882 | EJ16: 6.1279501 | EK16: =EH16+$JD16 -> 6.154848 | EL16: 5.231771 | EM16: 5.677882 | EN16: 6.1279501 | EO16: 6.5819752 | EP16: =EM16+$JD16 -> 6.6009589 | EQ16: 5.677882 | ER16: 6.1279501 | ES16: 6.5819752 | ET16: 7.0399575 | EU16: =ER16+$JD16 -> 7.051027 | EV16: 6.1279501 | EW16: 6.5819752 | EX16: 7.0399575 | EZ16: =EW16+$JD16 -> 7.5050522 | FA16: 2.5160655 | FB16: 3.0835698 | FC16: 3.6607076 | FD16: 4.243277 | FE16: =FB16+$JE16 -> 4.9297237 | FG16: 3.0835698 | FH16: 3.6607076 | FI16: 4.243277 | FJ16: 4.831278 | FK16: =FH16+$JE16 -> 5.5068615 | FL16: 3.6607076 | FM16: 4.243277 | FN16: 4.831278 | FO16: 5.4204062 | FP16: =FM16+$JE16 -> 6.0894309 | FQ16: 4.243277 | FR16: 4.831278 | FS16: 5.4204062 | FT16: 6.0192498 | FU16: =FR16+$JE16 -> 6.6774318 | FV16: 4.831278 | FW16: 5.4204062 | FX16: 6.0192498 | FY16: 6.6191797 | FZ16: =FW16+$JE16 -> 7.26656 | GA16: 5.4204062 | GB16: 6.0192498 | GC16: 6.6191797 | GD16: 7.0869845 | GE16: =GB16+$JE16 -> 7.8654037 | GF16: 6.0192498 | GG16: 6.6191797 | GH16: 7.0869845 | GI16: 7.5588886 | GJ16: =GG16+$JE16 -> 8.4653336 | GK16: 6.6191797 | GL16: 7.0869845 | GM16: 7.5588886 | GN16: 8.034892 | GO16: =GL16+$JE16 -> 8.9331383 | GP16: 7.0869845 | GQ16: 7.5588886 | GR16: 8.034892 | GS16: 8.5149949 | GT16: =GQ16+$JE16 -> 9.4050424 | GU16: 7.5588886 | GV16: 8.034892 | GW16: 8.5149949 | GY16: =GV16+$JE16 -> 9.8810459 | GZ16: 4.3321991 | HA16: 5.3693617 | HB16: 6.4272868 | HC16: 7.4951816 | HD16: =HA16+$JF16 -> 7.8309001 | HF16: 5.3693617 | HG16: 6.4272868 | HH16: 7.4951816 | HI16: 8.5730461 | HJ16: =HG16+$JF16 -> 8.8888253 | HK16: 6.4272868 | HL16: 7.4951816 | HM16: 8.5730461 | HN16: 9.6565759 | HO16: =HL16+$JF16 -> 9.9567201 | HP16: 7.4951816 | HQ16: 8.5730461 | HR16: 9.6565759 | HS16: 10.747575 | HT16: =HQ16+$JF16 -> 11.034585 | HU16: 8.5730461 | HV16: 9.6565759 | HW16: 10.747575 | HX16: 11.850951 | HY16: =HV16+$JF16 -> 12.118114 | HZ16: 9.6565759 | IA16: 10.747575 | IB16: 11.850951 | IC16: 12.764866 | ID16: =IA16+$JF16 -> 13.209114 | IE16: 10.747575 | IF16: 11.850951 | IG16: 12.764866 | IH16: 13.686839 | II16: =IF16+$JF16 -> 14.312489 | IJ16: 11.850951 | IK16: 12.764866 | IL16: 13.686839 | IM16: 14.616867 | IN16: =IK16+$JF16 -> 15.226405 | IO16: 12.764866 | IP16: 13.686839 | IQ16: 14.616867 | IR16: 15.554952 | IS16: =IP16+$JF16 -> 16.148377 | IT16: 13.686839 | IU16: 14.616867 | IV16: 15.554952 | IX16: =IU16+$JF16 -> 17.078406 | JB16: 0.30769231 | JC16: 0.46153846 | JD16: 0.92307692 | JE16: 1.8461538 | JF16: 2.4615385
B17: 7500 to 9999 | D17: 1.4891171 | E17: 1.9069784 | F17: 2.3223414 | G17: 2.7481441 | H17: =E17+$JB17 -> 2.1377477 | J17: 1.9069784 | K17: 2.3223414 | L17: 2.7481441 | M17: 3.1779332 | N17: =K17+$JB17 -> 2.5531106 | O17: 2.3223414 | P17: 2.7481441 | Q17: 3.1779332 | R17: 3.60513 | S17: =P17+$JB17 -> 2.9789133 | T17: 2.7481441 | U17: 3.1779332 | V17: 3.60513 | W17: 4.0428605 | X17: =U17+$JB17 -> 3.4087024 | Y17: 3.1779332 | Z17: 3.60513 | AA17: 4.0428605 | AB17: 4.4845774 | AC17: =Z17+$JB17 -> 3.8358992 | AD17: 3.60513 | AE17: 4.0428605 | AF17: 4.4845774 | AG17: 4.8569251 | AH17: =AE17+$JB17 -> 4.2736297 | AI17: 4.0428605 | AJ17: 4.4845774 | AK17: 4.8569251 | AL17: 5.2325703 | AM17: =AJ17+$JB17 -> 4.7153467 | AN17: 4.4845774 | AO17: 4.8569251 | AP17: 5.2325703 | AQ17: 5.6115132 | AR17: =AO17+$JB17 -> 5.0876943 | AS17: 4.8569251 | AT17: 5.2325703 | AU17: 5.6115132 | AV17: 5.9937536 | AW17: =AT17+$JB17 -> 5.4633396 | AX17: 5.2325703 | AY17: 5.6115132 | AZ17: 5.9937536 | BB17: =AY17+$JB$8 -> 6.6884363 | BC17: 1.5717906 | BD17: 1.9995618 | BE17: 2.4294095 | BF17: 2.8675519 | BG17: =BD17+$JC17 -> 2.3072541 | BI17: 1.9995618 | BJ17: 2.4294095 | BK17: 2.8675519 | BL17: 3.3097945 | BM17: =BJ17+$JC17 -> 2.7371018 | BN17: 2.4294095 | BO17: 2.8675519 | BP17: 3.3097945 | BQ17: 3.7518609 | BR17: =BO17+$JC17 -> 3.1752443 | BS17: 2.8675519 | BT17: 3.3097945 | BU17: 3.7518609 | BV17: 4.2000275 | BW17: =BT17+$JC17 -> 3.6174868 | BX17: 3.3097945 | BY17: 3.7518609 | BZ17: 4.2000275 | CA17: 4.6545392 | CB17: =BY17+$JC17 -> 4.0595532 | CC17: 3.7518609 | CD17: 4.2000275 | CE17: 4.6545392 | CF17: 5.0448971 | CG17: =CD17+$JC17 -> 4.5077198 | CH17: 4.2000275 | CI17: 4.6545392 | CJ17: 5.0448971 | CK17: 5.4387141 | CL17: =CI17+$JC17 -> 4.9622315 | CM17: 4.6545392 | CN17: 5.0448971 | CO17: 5.4387141 | CP17: 5.8359903 | CQ17: =CN17+$JC17 -> 5.3525894 | CR17: 5.0448971 | CS17: 5.4387141 | CT17: 5.8359903 | CU17: 6.2367257 | CV17: =CS17+$JC17 -> 5.7464064 | CW17: 5.4387141 | CX17: 5.8359903 | CY17: 6.2367257 | DA17: =CX17+$JC17 -> 6.1436826 | DB17: 1.725327 | DC17: 2.1715023 | DD17: 2.6282502 | DE17: 3.0893094 | DF17: =DC17+$JB17 -> 2.4022715 | DH17: 2.1715023 | DI17: 2.6282502 | DJ17: 3.0893094 | DK17: 3.5546797 | DL17: =DI17+$JD17 -> 3.2436349 | DM17: 2.6282502 | DN17: 3.0893094 | DO17: 3.5546797 | DP17: 4.0243612 | DQ17: =DN17+$JD17 -> 3.704694 | DR17: 3.0893094 | DS17: 3.5546797 | DT17: 4.0243612 | DU17: 4.4919092 | DV17: =DS17+$JD17 -> 4.1700644 | DW17: 3.5546797 | DX17: 4.0243612 | DY17: 4.4919092 | DZ17: 4.9701825 | EA17: =DX17+$JD17 -> 4.6397459 | EB17: 4.0243612 | EC17: 4.4919092 | ED17: 4.9701825 | EE17: 5.3939879 | EF17: =EC17+$JD17 -> 5.1072938 | EG17: 4.4919092 | EH17: 4.9701825 | EI17: 5.3939879 | EJ17: 5.8215525 | EK17: =EH17+$JD17 -> 5.5855671 | EL17: 4.9701825 | EM17: 5.3939879 | EN17: 5.8215525 | EO17: 6.2528765 | EP17: =EM17+$JD17 -> 6.0093725 | EQ17: 5.3939879 | ER17: 5.8215525 | ES17: 6.2528765 | ET17: 6.6879597 | EU17: =ER17+$JD17 -> 6.4369372 | EV17: 5.8215525 | EW17: 6.2528765 | EX17: 6.6879597 | EZ17: =EW17+$JD17 -> 6.8682611 | FA17: 2.3902622 | FB17: 2.9293913 | FC17: 3.4776722 | FD17: 4.0311132 | FE17: =FB17+$JE17 -> 4.1601606 | FG17: 2.9293913 | FH17: 3.4776722 | FI17: 4.0311132 | FJ17: 4.5897141 | FK17: =FH17+$JE17 -> 4.7084415 | FL17: 3.4776722 | FM17: 4.0311132 | FN17: 4.5897141 | FO17: 5.1493859 | FP17: =FM17+$JE17 -> 5.2618824 | FQ17: 4.0311132 | FR17: 4.5897141 | FS17: 5.1493859 | FT17: 5.7182873 | FU17: =FR17+$JE17 -> 5.8204833 | FV17: 4.5897141 | FW17: 5.1493859 | FX17: 5.7182873 | FY17: 6.2882207 | FZ17: =FW17+$JE17 -> 6.3801551 | GA17: 5.1493859 | GB17: 5.7182873 | GC17: 6.2882207 | GD17: 6.7326352 | GE17: =GB17+$JE17 -> 6.9490566 | GF17: 5.7182873 | GG17: 6.2882207 | GH17: 6.7326352 | GI17: 7.1809441 | GJ17: =GG17+$JE17 -> 7.51899 | GK17: 6.2882207 | GL17: 6.7326352 | GM17: 7.1809441 | GN17: 7.6331474 | GO17: =GL17+$JE17 -> 7.9634045 | GP17: 6.7326352 | GQ17: 7.1809441 | GR17: 7.6331474 | GS17: 8.0892451 | GT17: =GQ17+$JE17 -> 8.4117134 | GU17: 7.1809441 | GV17: 7.6331474 | GW17: 8.0892451 | GY17: =GV17+$JE17 -> 8.8639167 | GZ17: 4.1155891 | HA17: 5.1008936 | HB17: 6.1059225 | HC17: 7.1204226 | HD17: =HA17+$JF17 -> 6.9470474 | HF17: 5.1008936 | HG17: 6.1059225 | HH17: 7.1204226 | HI17: 8.1443938 | HJ17: =HG17+$JF17 -> 7.9520763 | HK17: 6.1059225 | HL17: 7.1204226 | HM17: 8.1443938 | HN17: 9.1737471 | HO17: =HL17+$JF17 -> 8.9665764 | HP17: 7.1204226 | HQ17: 8.1443938 | HR17: 9.1737471 | HS17: 10.210197 | HT17: =HQ17+$JF17 -> 9.9905477 | HU17: 8.1443938 | HV17: 9.1737471 | HW17: 10.210197 | HX17: 11.258403 | HY17: =HV17+$JF17 -> 11.019901 | HZ17: 9.1737471 | IA17: 10.210197 | IB17: 11.258403 | IC17: 12.126623 | ID17: =IA17+$JF17 -> 12.05635 | IE17: 10.210197 | IF17: 11.258403 | IG17: 12.126623 | IH17: 13.002497 | II17: =IF17+$JF17 -> 13.104557 | IJ17: 11.258403 | IK17: 12.126623 | IL17: 13.002497 | IM17: 13.886024 | IN17: =IK17+$JF17 -> 13.972777 | IO17: 12.126623 | IP17: 13.002497 | IQ17: 13.886024 | IR17: 14.777205 | IS17: =IP17+$JF17 -> 14.848651 | IT17: 13.002497 | IU17: 13.886024 | IV17: 14.777205 | IX17: =IU17+$JF17 -> 15.732178 | JB17: 0.23076923 | JC17: 0.30769231 | JD17: 0.61538462 | JE17: 1.2307692 | JF17: 1.8461538
B18: 10,000 + | D18: 1.4146613 | E18: 1.8116295 | F18: 2.2062243 | G18: 2.6107369 | H18: =E18+$JB18 -> 1.9654757 | J18: 1.8116295 | K18: 2.2062243 | L18: 2.6107369 | M18: 3.0190365 | N18: =K18+$JB18 -> 2.3600705 | O18: 2.2062243 | P18: 2.6107369 | Q18: 3.0190365 | R18: 3.4248735 | S18: =P18+$JB18 -> 2.764583 | T18: 2.6107369 | U18: 3.0190365 | V18: 3.4248735 | W18: 3.8407175 | X18: =U18+$JB18 -> 3.1728827 | Y18: 3.0190365 | Z18: 3.4248735 | AA18: 3.8407175 | AB18: 4.2603486 | AC18: =Z18+$JB18 -> 3.5787196 | AD18: 3.4248735 | AE18: 3.8407175 | AF18: 4.2603486 | AG18: 4.6140788 | AH18: =AE18+$JB18 -> 3.9945636 | AI18: 3.8407175 | AJ18: 4.2603486 | AK18: 4.6140788 | AL18: 4.9709418 | AM18: =AJ18+$JB18 -> 4.4141947 | AN18: 4.2603486 | AO18: 4.6140788 | AP18: 4.9709418 | AQ18: 5.3309375 | AR18: =AO18+$JB18 -> 4.767925 | AS18: 4.6140788 | AT18: 4.9709418 | AU18: 5.3309375 | AV18: 5.694066 | AW18: =AT18+$JB18 -> 5.124788 | AX18: 4.9709418 | AY18: 5.3309375 | AZ18: 5.694066 | BB18: =AY18+$JB$8 -> 6.4078606 | BC18: 1.493201 | BD18: 1.8995837 | BE18: 2.307939 | BF18: 2.7241743 | BG18: =BD18+$JC18 -> 2.0534298 | BI18: 1.8995837 | BJ18: 2.307939 | BK18: 2.7241743 | BL18: 3.1443048 | BM18: =BJ18+$JC18 -> 2.4617852 | BN18: 2.307939 | BO18: 2.7241743 | BP18: 3.1443048 | BQ18: 3.5642679 | BR18: =BO18+$JC18 -> 2.8780205 | BS18: 2.7241743 | BT18: 3.1443048 | BU18: 3.5642679 | BV18: 3.9900262 | BW18: =BT18+$JC18 -> 3.2981509 | BX18: 3.1443048 | BY18: 3.5642679 | BZ18: 3.9900262 | CA18: 4.4218122 | CB18: =BY18+$JC18 -> 3.718114 | CC18: 3.5642679 | CD18: 3.9900262 | CE18: 4.4218122 | CF18: 4.7926522 | CG18: =CD18+$JC18 -> 4.1438723 | CH18: 3.9900262 | CI18: 4.4218122 | CJ18: 4.7926522 | CK18: 5.1667784 | CL18: =CI18+$JC18 -> 4.5756584 | CM18: 4.4218122 | CN18: 4.7926522 | CO18: 5.1667784 | CP18: 5.5441908 | CQ18: =CN18+$JC18 -> 4.9464984 | CR18: 4.7926522 | CS18: 5.1667784 | CT18: 5.5441908 | CU18: 5.9248895 | CV18: =CS18+$JC18 -> 5.3206246 | CW18: 5.1667784 | CX18: 5.5441908 | CY18: 5.9248895 | DA18: =CX18+$JC18 -> 5.698037 | DB18: 1.6390606 | DC18: 2.0629271 | DD18: 2.4968377 | DE18: 2.9348439 | DF18: =DC18+$JB18 -> 2.2167733 | DH18: 2.0629271 | DI18: 2.4968377 | DJ18: 2.9348439 | DK18: 3.3769457 | DL18: =DI18+$JD18 -> 2.80453 | DM18: 2.4968377 | DN18: 2.9348439 | DO18: 3.3769457 | DP18: 3.8231432 | DQ18: =DN18+$JD18 -> 3.2425362 | DR18: 2.9348439 | DS18: 3.3769457 | DT18: 3.8231432 | DU18: 4.2673137 | DV18: =DS18+$JD18 -> 3.6846381 | DW18: 3.3769457 | DX18: 3.8231432 | DY18: 4.2673137 | DZ18: 4.7216734 | EA18: =DX18+$JD18 -> 4.1308355 | EB18: 3.8231432 | EC18: 4.2673137 | ED18: 4.7216734 | EE18: 5.1242885 | EF18: =EC18+$JD18 -> 4.575006 | EG18: 4.2673137 | EH18: 4.7216734 | EI18: 5.1242885 | EJ18: 5.5304749 | EK18: =EH18+$JD18 -> 5.0293657 | EL18: 4.7216734 | EM18: 5.1242885 | EN18: 5.5304749 | EO18: 5.9402327 | EP18: =EM18+$JD18 -> 5.4319808 | EQ18: 5.1242885 | ER18: 5.5304749 | ES18: 5.9402327 | ET18: 6.3535617 | EU18: =ER18+$JD18 -> 5.8381672 | EV18: 5.5304749 | EW18: 5.9402327 | EX18: 6.3535617 | EZ18: =EW18+$JD18 -> 6.247925 | FA18: 2.2707491 | FB18: 2.7829218 | FC18: 3.3037886 | FD18: 3.8295575 | FE18: =FB18+$JE18 -> 3.3983064 | FG18: 2.7829218 | FH18: 3.3037886 | FI18: 3.8295575 | FJ18: 4.3602284 | FK18: =FH18+$JE18 -> 3.9191732 | FL18: 3.3037886 | FM18: 3.8295575 | FN18: 4.3602284 | FO18: 4.8919166 | FP18: =FM18+$JE18 -> 4.4449421 | FQ18: 3.8295575 | FR18: 4.3602284 | FS18: 4.8919166 | FT18: 5.432373 | FU18: =FR18+$JE18 -> 4.975613 | FV18: 4.3602284 | FW18: 4.8919166 | FX18: 5.432373 | FY18: 5.9738097 | FZ18: =FW18+$JE18 -> 5.5073012 | GA18: 4.8919166 | GB18: 5.432373 | GC18: 5.9738097 | GD18: 6.3960035 | GE18: =GB18+$JE18 -> 6.0477576 | GF18: 5.432373 | GG18: 5.9738097 | GH18: 6.3960035 | GI18: 6.8218969 | GJ18: =GG18+$JE18 -> 6.5891943 | GK18: 5.9738097 | GL18: 6.3960035 | GM18: 6.8218969 | GN18: 7.2514901 | GO18: =GL18+$JE18 -> 7.0113881 | GP18: 6.3960035 | GQ18: 6.8218969 | GR18: 7.2514901 | GS18: 7.6847829 | GT18: =GQ18+$JE18 -> 7.4372815 | GU18: 6.8218969 | GV18: 7.2514901 | GW18: 7.6847829 | GY18: =GV18+$JE18 -> 7.8668747 | GZ18: 3.9098097 | HA18: 4.8458489 | HB18: 5.8006264 | HC18: 6.7644014 | HD18: =HA18+$JF18 -> 6.0766181 | HF18: 4.8458489 | HG18: 5.8006264 | HH18: 6.7644014 | HI18: 7.7371741 | HJ18: =HG18+$JF18 -> 7.0313956 | HK18: 5.8006264 | HL18: 6.7644014 | HM18: 7.7371741 | HN18: 8.7150598 | HO18: =HL18+$JF18 -> 7.9951707 | HP18: 6.7644014 | HQ18: 7.7371741 | HR18: 8.7150598 | HS18: 9.6996867 | HT18: =HQ18+$JF18 -> 8.9679434 | HU18: 7.7371741 | HV18: 8.7150598 | HW18: 9.6996867 | HX18: 10.695483 | HY18: =HV18+$JF18 -> 9.945829 | HZ18: 8.7150598 | IA18: 9.6996867 | IB18: 10.695483 | IC18: 11.520292 | ID18: =IA18+$JF18 -> 10.930456 | IE18: 9.6996867 | IF18: 10.695483 | IG18: 11.520292 | IH18: 12.352372 | II18: =IF18+$JF18 -> 11.926252 | IJ18: 10.695483 | IK18: 11.520292 | IL18: 12.352372 | IM18: 13.191723 | IN18: =IK18+$JF18 -> 12.751061 | IO18: 11.520292 | IP18: 12.352372 | IQ18: 13.191723 | IR18: 14.038345 | IS18: =IP18+$JF18 -> 13.583141 | IT18: 12.352372 | IU18: 13.191723 | IV18: 14.038345 | IX18: =IU18+$JF18 -> 14.422492 | JB18: 0.15384615 | JC18: 0.15384615 | JD18: 0.30769231 | JE18: 0.61538462 | JF18: 1.2307692
A19: Film & Screenmaking cost | B19: NEW DESIGN | D19: 42.86 | E19: 42.86 | F19: 42.86 | G19: =F19+42.86 -> 85.72 | H19: 42.86 | I19: 42.86 | J19: 85.72 | K19: 85.72 | L19: 85.72 | M19: =L19+$D$19 -> 128.58 | N19: =K19 -> 85.72 | O19: 128.58 | P19: 128.58 | Q19: 128.58 | R19: =Q19+$D$19 -> 171.44 | S19: 128.58 | T19: 171.44 | U19: 171.44 | V19: 171.44 | W19: =V19+$D$19 -> 214.3 | X19: 171.44 | Y19: 214.3 | Z19: 214.3 | AA19: 214.3 | AB19: =AA19+$D$19 -> 257.16 | AC19: 214.3 | AD19: 257.16 | AE19: 257.16 | AF19: 257.16 | AG19: =AF19+$D$19 -> 300.02 | AH19: 257.16 | AI19: 300.02 | AJ19: 300.02 | AK19: 300.02 | AL19: =AK19+$D$19 -> 342.88 | AM19: 300.02 | AN19: 342.88 | AO19: 342.88 | AP19: 342.88 | AQ19: =AP19+$D$19 -> 385.74 | AR19: 342.88 | AS19: 385.74 | AT19: 385.74 | AU19: 385.74 | AV19: =AU19+$D$19 -> 428.6 | AW19: 385.74 | AX19: 428.6 | AY19: 428.6 | AZ19: 428.6 | BB19: 428.6 | BC19: 57.14 | BD19: =BC19 -> 57.14 | BE19: =BD19 -> 57.14 | BF19: =BE19+BC19 -> 114.28 | BG19: =BC19 -> 57.14 | BH19: =BG19 -> 57.14 | BI19: =BG19+BC19 -> 114.28 | BJ19: =BI19 -> 114.28 | BK19: =BI19 -> 114.28 | BL19: =BK19+$BC$19 -> 171.42 | BM19: =BK19 -> 114.28 | BN19: =BM19+BH19 -> 171.42 | BO19: =BN19 -> 171.42 | BP19: =BN19 -> 171.42 | BQ19: =BP19+$BC$19 -> 228.56 | BR19: =BP19 -> 171.42 | BS19: =BR19+BM19 -> 285.7 | BT19: =BS19 -> 285.7 | BU19: =BS19 -> 285.7 | BV19: =BU19+$BC$19 -> 342.84 | BW19: =BU19 -> 285.7 | BX19: =BW19+$BC$19 -> 342.84 | BY19: =BX19 -> 342.84 | BZ19: =BX19 -> 342.84 | CA19: =BZ19+$BC$19 -> 399.98 | CB19: =BZ19 -> 342.84 | CC19: =CB19+$BC$19 -> 399.98 | CD19: =CC19 -> 399.98 | CE19: =CC19 -> 399.98 | CF19: =CE19+$BC$19 -> 457.12 | CG19: =CE19 -> 399.98 | CH19: =CG19+$BC$19 -> 457.12 | CI19: =CH19 -> 457.12 | CJ19: =CH19 -> 457.12 | CK19: =CJ19+$BC$19 -> 514.26 | CL19: =CJ19 -> 457.12 | CM19: =CL19+$BC$19 -> 514.26 | CN19: =CM19 -> 514.26 | CO19: =CM19 -> 514.26 | CP19: =CO19+$BC$19 -> 571.4 | CQ19: =CO19 -> 514.26 | CR19: =CQ19+$BC$19 -> 571.4 | CS19: =CR19 -> 571.4 | CT19: =CR19 -> 571.4 | CU19: =CT19+$BC$19 -> 628.54 | CV19: =CT19 -> 571.4 | CW19: =CV19+$BC$19 -> 628.54 | CX19: =CW19 -> 628.54 | CY19: =CW19 -> 628.54 | DA19: =CY19 -> 628.54 | DB19: 71.43 | DC19: =DB19 -> 71.43 | DD19: =DB19 -> 71.43 | DE19: =DD19+$DB$19 -> 142.86 | DF19: =DB19 -> 71.43 | DG19: =DF19 -> 71.43 | DH19: =DF19+$DB$19 -> 142.86 | DI19: =DH19 -> 142.86 | DJ19: =DH19 -> 142.86 | DK19: =DJ19+$DB$19 -> 214.29 | DL19: =DJ19 -> 142.86 | DM19: =DK19+$DB$19 -> 285.72 | DN19: =DM19 -> 285.72 | DO19: =DM19 -> 285.72 | DP19: =DO19+$DB$19 -> 357.15 | DQ19: =DO19 -> 285.72 | DR19: =DP19+$DB$19 -> 428.58 | DS19: =DR19 -> 428.58 | DT19: =DR19 -> 428.58 | DU19: =DT19+$DB$19 -> 500.01 | DV19: =DT19 -> 428.58 | DW19: =DU19+$DB$19 -> 571.44 | DX19: =DW19 -> 571.44 | DY19: =DW19 -> 571.44 | DZ19: =DY19+$DB$19 -> 642.87 | EA19: =DY19 -> 571.44 | EB19: =DZ19+$DB$19 -> 714.3 | EC19: =EB19 -> 714.3 | ED19: =EB19 -> 714.3 | EE19: =ED19+$DB$19 -> 785.73 | EF19: =ED19 -> 714.3 | EG19: =EE19+$DB$19 -> 857.16 | EH19: =EG19 -> 857.16 | EI19: =EG19 -> 857.16 | EJ19: =EI19+$DB$19 -> 928.59 | EK19: =EI19 -> 857.16 | EL19: =EJ19+$DB$19 -> 1000.02 | EM19: =EL19 -> 1000.02 | EN19: =EL19 -> 1000.02 | EO19: =EN19+$DB$19 -> 1071.45 | EP19: =EN19 -> 1000.02 | EQ19: =EO19+$DB$19 -> 1142.88 | ER19: =EQ19 -> 1142.88 | ES19: =EQ19 -> 1142.88 | ET19: =ES19+$DB$19 -> 1214.31 | EU19: =ES19 -> 1142.88 | EV19: =ET19+$DB$19 -> 1285.74 | EW19: =EV19 -> 1285.74 | EX19: =EV19 -> 1285.74 | EZ19: =EX19 -> 1285.74 | FA19: 92.86 | FB19: =FA19 -> 92.86 | FC19: =FA19 -> 92.86 | FD19: =FC19+$FA$19 -> 185.72 | FE19: =FC19 -> 92.86 | FF19: =FA19 -> 92.86 | FG19: =FF19+$FA$19 -> 185.72 | FH19: =FG19 -> 185.72 | FI19: =FG19 -> 185.72 | FJ19: =FI19+$FA$19 -> 278.58 | FK19: =FI19 -> 185.72 | FL19: =FK19+$FA$19 -> 278.58 | FM19: =FL19 -> 278.58 | FN19: =FL19 -> 278.58 | FO19: =FN19+$FA$19 -> 371.44 | FP19: =FN19 -> 278.58 | FQ19: =FP19+$FA$19 -> 371.44 | FR19: =FQ19 -> 371.44 | FS19: =FQ19 -> 371.44 | FT19: =FS19+$FA$19 -> 464.3 | FU19: =FS19 -> 371.44 | FV19: =FU19+$FA$19 -> 464.3 | FW19: =FV19 -> 464.3 | FX19: =FV19 -> 464.3 | FY19: =FX19+$FA$19 -> 557.16 | FZ19: =FX19 -> 464.3 | GA19: =FZ19+$FA$19 -> 557.16 | GB19: =GA19 -> 557.16 | GC19: =GA19 -> 557.16 | GD19: =GC19+$FA$19 -> 650.02 | GE19: =GC19 -> 557.16 | GF19: =GE19+$FA$19 -> 650.02 | GG19: =GF19 -> 650.02 | GH19: =GF19 -> 650.02 | GI19: =GH19+$FA$19 -> 742.88 | GJ19: =GH19 -> 650.02 | GK19: =GJ19+$FA$19 -> 742.88 | GL19: =GK19 -> 742.88 | GM19: =GK19 -> 742.88 | GN19: =GM19+$FA$19 -> 835.74 | GO19: =GM19 -> 742.88 | GP19: =GO19+$FA$19 -> 835.74 | GQ19: =GP19 -> 835.74 | GR19: =GP19 -> 835.74 | GS19: =GR19+$FA$19 -> 928.6 | GT19: =GR19 -> 835.74 | GU19: =GT19+$FA$19 -> 928.6 | GV19: =GU19 -> 928.6 | GW19: =GU19 -> 928.6 | GY19: =GW19 -> 928.6 | GZ19: 128.57 | HA19: =GZ19 -> 128.57 | HB19: =GZ19 -> 128.57 | HC19: =HB19+$GZ$19 -> 257.14 | HD19: =GZ19 -> 128.57 | HE19: =GZ19 -> 128.57 | HF19: =HE19+$GZ$19 -> 257.14 | HG19: =HF19 -> 257.14 | HH19: =HF19 -> 257.14 | HI19: =HH19+$GZ$19 -> 385.71 | HJ19: =HF19 -> 257.14 | HK19: =HJ19+$GZ$19 -> 385.71 | HL19: =HK19 -> 385.71 | HM19: =HK19 -> 385.71 | HN19: =HM19+$GZ$19 -> 514.28 | HO19: =HK19 -> 385.71 | HP19: =HO19+$GZ$19 -> 514.28 | HQ19: =HP19 -> 514.28 | HR19: =HP19 -> 514.28 | HS19: =HR19+$GZ$19 -> 642.85 | HT19: =HP19 -> 514.28 | HU19: =HT19+$GZ$19 -> 642.85 | HV19: =HU19 -> 642.85 | HW19: =HU19 -> 642.85 | HX19: =HW19+$GZ$19 -> 771.42 | HY19: =HU19 -> 642.85 | HZ19: =HY19+$GZ$19 -> 771.42 | IA19: =HZ19 -> 771.42 | IB19: =HZ19 -> 771.42 | IC19: =IB19+$GZ$19 -> 899.99 | ID19: =HZ19 -> 771.42 | IE19: =ID19+$GZ$19 -> 899.99 | IF19: =IE19 -> 899.99 | IG19: =IE19 -> 899.99 | IH19: =IG19+$GZ$19 -> 1028.56 | II19: =IE19 -> 899.99 | IJ19: =II19+$GZ$19 -> 1028.56 | IK19: =IJ19 -> 1028.56 | IL19: =IJ19 -> 1028.56 | IM19: =IL19+$GZ$19 -> 1157.13 | IN19: =IJ19 -> 1028.56 | IO19: =IN19+$GZ$19 -> 1157.13 | IP19: =IO19 -> 1157.13 | IQ19: =IO19 -> 1157.13 | IR19: =IQ19+$GZ$19 -> 1285.7 | IS19: =IO19 -> 1157.13 | IT19: =IS19+$GZ$19 -> 1285.7 | IU19: =IT19 -> 1285.7 | IV19: =IT19 -> 1285.7 | IX19: =IT19 -> 1285.7
B20: RESET | D20: =D19/2 -> 21.43 | E20: =E19/2 -> 21.43 | F20: =F19/2 -> 21.43 | G20: =G19/2 -> 42.86 | H20: =H19/2 -> 21.43 | I20: =I19/2 -> 21.43 | J20: =J19/2 -> 42.86 | K20: =K19/2 -> 42.86 | ... AZ20: =AZ19/2 -> 214.3 | BB20: =BB19/2 -> 214.3 | BC20: =BC19/2 -> 28.57 | BD20: =BD19/2 -> 28.57 | BE20: =BE19/2 -> 28.57 | BF20: =BF19/2 -> 57.14 | BG20: =BG19/2 -> 28.57 | BH20: =BH19/2 -> 28.57 | BI20: =BI19/2 -> 57.14 | ... CY20: =CY19/2 -> 314.27 | DA20: =DA19/2 -> 314.27 | DB20: =DB19/2 -> 35.715 | DC20: =DC19/2 -> 35.715 | DD20: =DD19/2 -> 35.715 | DE20: =DE19/2 -> 71.43 | DF20: =DF19/2 -> 35.715 | DG20: =DG19/2 -> 35.715 | DH20: =DH19/2 -> 71.43 | ... GW20: =GW19/2 -> 464.3 | GY20: =GY19/2 -> 464.3 | GZ20: =GZ19/2 -> 64.285 | HA20: =HA19/2 -> 64.285 | HB20: =HB19/2 -> 64.285 | HC20: =HC19/2 -> 128.57 | HD20: =HD19/2 -> 64.285 | HE20: =HE19/2 -> 64.285 | HF20: =HF19/2 -> 128.57 | ... IV20: =IV19/2 -> 642.85 | IX20: =IX19/2 -> 642.85
B21: REPEAT <12 MONTHS | D21: 0 | E21: 0 | F21: 0 | G21: 0 | H21: 0 | I21: 0 | J21: 0 | K21: 0 | L21: 0 | M21: 0 | N21: 0 | O21: 0 | P21: 0 | Q21: 0 | R21: 0 | S21: 0 | T21: 0 | U21: 0 | V21: 0 | W21: 0 | X21: 0 | Y21: 0 | Z21: 0 | AA21: 0 | AB21: 0 | AC21: 0 | AD21: 0 | AE21: 0 | AF21: 0 | AG21: 0 | AH21: 0 | AI21: 0 | AJ21: 0 | AK21: 0 | AL21: 0 | AM21: 0 | AN21: 0 | AO21: 0 | AP21: 0 | AQ21: 0 | AR21: 0 | AS21: 0 | AT21: 0 | AU21: 0 | AV21: 0 | AW21: 0 | AX21: 0 | AY21: 0 | AZ21: 0 | BA21: 0 | BB21: 0 | BC21: 0 | BD21: 0 | BE21: 0 | BF21: 0 | BG21: 0 | BH21: 0 | BI21: 0 | BJ21: 0 | BK21: 0 | BL21: 0 | BM21: 0 | BN21: 0 | BO21: 0 | BP21: 0 | BQ21: 0 | BR21: 0 | BS21: 0 | BT21: 0 | BU21: 0 | BV21: 0 | BW21: 0 | BX21: 0 | BY21: 0 | BZ21: 0 | CA21: 0 | CB21: 0 | CC21: 0 | CD21: 0 | CE21: 0 | CF21: 0 | CG21: 0 | CH21: 0 | CI21: 0 | CJ21: 0 | CK21: 0 | CL21: 0 | CM21: 0 | CN21: 0 | CO21: 0 | CP21: 0 | CQ21: 0 | CR21: 0 | CS21: 0 | CT21: 0 | CU21: 0 | CV21: 0 | CW21: 0 | CX21: 0 | CY21: 0 | CZ21: 0 | DA21: 0 | DB21: 0 | DC21: 0 | DD21: 0 | DE21: 0 | DF21: 0 | DG21: 0 | DH21: 0 | DI21: 0 | DJ21: 0 | DK21: 0 | DL21: 0 | DM21: 0 | DN21: 0 | DO21: 0 | DP21: 0 | DQ21: 0 | DR21: 0 | DS21: 0 | DT21: 0 | DU21: 0 | DV21: 0 | DW21: 0 | DX21: 0 | DY21: 0 | DZ21: 0 | EA21: 0 | EB21: 0 | EC21: 0 | ED21: 0 | EE21: 0 | EF21: 0 | EG21: 0 | EH21: 0 | EI21: 0 | EJ21: 0 | EK21: 0 | EL21: 0 | EM21: 0 | EN21: 0 | EO21: 0 | EP21: 0 | EQ21: 0 | ER21: 0 | ES21: 0 | ET21: 0 | EU21: 0 | EV21: 0 | EW21: 0 | EX21: 0 | EY21: 0 | EZ21: 0 | FA21: 0 | FB21: 0 | FC21: 0 | FD21: 0 | FE21: 0 | FF21: 0 | FG21: 0 | FH21: 0 | FI21: 0 | FJ21: 0 | FK21: 0 | FL21: 0 | FM21: 0 | FN21: 0 | FO21: 0 | FP21: 0 | FQ21: 0 | FR21: 0 | FS21: 0 | FT21: 0 | FU21: 0 | FV21: 0 | FW21: 0 | FX21: 0 | FY21: 0 | FZ21: 0 | GA21: 0 | GB21: 0 | GC21: 0 | GD21: 0 | GE21: 0 | GF21: 0 | GG21: 0 | GH21: 0 | GI21: 0 | GJ21: 0 | GK21: 0 | GL21: 0 | GM21: 0 | GN21: 0 | GO21: 0 | GP21: 0 | GQ21: 0 | GR21: 0 | GS21: 0 | GT21: 0 | GU21: 0 | GV21: 0 | GW21: 0 | GX21: 0 | GY21: 0 | GZ21: 0 | HA21: 0 | HB21: 0 | HC21: 0 | HD21: 0 | HE21: 0 | HF21: 0 | HG21: 0 | HH21: 0 | HI21: 0 | HJ21: 0 | HK21: 0 | HL21: 0 | HM21: 0 | HN21: 0 | HO21: 0 | HP21: 0 | HQ21: 0 | HR21: 0 | HS21: 0 | HT21: 0 | HU21: 0 | HV21: 0 | HW21: 0 | HX21: 0 | HY21: 0 | HZ21: 0 | IA21: 0 | IB21: 0 | IC21: 0 | ID21: 0 | IE21: 0 | IF21: 0 | IG21: 0 | IH21: 0 | II21: 0 | IJ21: 0 | IK21: 0 | IL21: 0 | IM21: 0 | IN21: 0 | IO21: 0 | IP21: 0 | IQ21: 0 | IR21: 0 | IS21: 0 | IT21: 0 | IU21: 0 | IV21: 0 | IW21: 0 | IX21: 0
A23: EMBROIDERY
B24: ARRAY = EMBROIDERYCOSTS
B25: array= STITCHCOUNT
A26: ARRAY= EMBQTY | B26: < 2,000 | C26: < 3,000 | D26: < 4,000 | E26: < 5,000 | F26: < 6,000 | G26: < 7,000 | H26: < 8,000 | I26: < 9,000 | J26: < 10,000 | K26: < 11,000 | L26: < 12,000 | M26: < 13,000 | N26: < 14,000 | O26: < 15,000 | P26: <16, 000 | Q26: <17,000 | R26: < 18,000 | S26: < 19,000 | T26: < 20, 000 | U26: < 21,000 | V26: < 22,000 | W26: < 23,000 | X26: < 24,000 | Y26: < 25,000 | Z26: < 26,000 | AA26: < 27,000 | AB26: < 28,000 | AC26: < 29,000 | AD26: < 30,000 | AE26: < 31,000 | AF26: < 32,000 | AG26: < 33,000 | AH26: < 34,000 | AI26: < 35,000 | AJ26: < 36,000 | AK26: < 37,000 | AL26: < 38,000 | AM26: < 39,000 | AN26: < 40,000 | AO26: < 41,000 | AP26: < 42,000 | AQ26: < 43,000 | AR26: < 44,000 | AS26: < 45,000 | AT26: < 46,000 | AU26: < 47,000 | AV26: < 48,000 | AW26: < 49,000 | AX26: < 50,000 | AY26: < 51,000 | AZ26: < 52,000 | BA26: < 53,000 | BB26: < 54,000 | BC26: < 55,000 | BD26: < 56,000 | BE26: < 57,000 | BF26: < 58,000 | BG26: < 59,000 | BH26: < 60,000 | BI26: < 61,000 | BJ26: < 62,000 | BK26: < 63,000 | BL26: < 64,000 | BM26: < 65,000 | BN26: < 66,000 | BO26: < 67,000 | BP26: < 68,000 | BQ26: < 69,000 | BR26: < 70,000 | BS26: < 71,000 | BT26: < 72,000 | BU26: < 73,000 | BV26: < 74,000 | BW26: < 75,000 | BX26: < 76,000 | BY26: < 77,000 | BZ26: < 78,000 | CA26: < 79,000 | CB26: < 80,000 | CC26: < 81,000 | CD26: < 82,000 | CE26: < 83,000 | CF26: < 84,000 | CG26: < 85,000 | CH26: < 86,000 | CI26: < 87,000 | CJ26: < 88,000 | CK26: < 89,000 | CL26: < 90,000 | CM26: < 91,000 | CN26: < 92,000 | CO26: < 93,000 | CP26: < 94,000 | CQ26: < 95,000 | CR26: < 96,000 | CS26: < 97,000 | CT26: < 98,000 | CU26: < 99,000 | CV26: <100,000 | CW26: <101,000 | CX26: <102,000 | CY26: <103,000 | CZ26: <104,000 | DA26: <105,000 | DB26: <106,000 | DC26: <107,000 | DD26: <108,000 | DE26: <109,000 | DF26: <110,000 | DG26: <111,000 | DH26: <112,000 | DI26: <113,000 | DJ26: <114,000 | DK26: <115,000 | DL26: <116,000 | DM26: <117,000 | DN26: <118,000 | DO26: <119,000 | DP26: <120,000 | DQ26: <121,000 | DR26: <122,000 | DS26: <123,000 | DT26: <124,000 | DU26: <125,000 | DV26: <126,000 | DW26: <127,000 | DX26: <128,000 | DY26: <129,000 | DZ26: <130,000 | EA26: <131,000 | EB26: <132,000 | EC26: <133,000 | ED26: <134,000 | EE26: <135,000 | EF26: <136,000 | EG26: <137,000 | EH26: <138,000 | EI26: <139,000 | EJ26: <140,000 | EK26: <141,000 | EL26: <142,000 | EM26: <143,000 | EN26: <144,000 | EO26: <145,000 | EP26: <146,000 | EQ26: <147,000 | ER26: <148,000 | ES26: <149,000 | ET26: <150,000
A27: 1 | B27: 9.1765621 | C27: 9.1765621 | D27: 10.285538 | E27: 11.264349 | F27: 12.568574 | G27: 13.8728 | H27: 15.144484 | I27: 15.928045 | J27: 16.711606 | K27: 17.495167 | L27: 18.278728 | M27: 19.062289 | N27: 19.84585 | O27: 20.629411 | P27: 21.412972 | Q27: 22.196533 | R27: 22.980094 | S27: 23.763655 | T27: 24.547216 | U27: 25.330777 | V27: 26.114338 | W27: 26.897899 | X27: 27.681461 | Y27: 28.465022 | Z27: 29.248583 | AA27: 30.032144 | AB27: 30.815705 | AC27: 31.599266 | AD27: 32.382827 | AE27: 33.166388 | AF27: 33.949949 | AG27: 34.73351 | AH27: 35.517071 | AI27: 36.300632 | AJ27: 37.084193 | AK27: 37.867754 | AL27: 38.651315 | AM27: 39.434876 | AN27: 40.218437 | AO27: 42.563992 | AP27: 43.347553 | AQ27: 44.131114 | AR27: 44.914675 | AS27: 45.698236 | AT27: 46.481797 | AU27: 47.265358 | AV27: 48.048919 | AW27: 47.270486 | AX27: 48.054047 | AY27: 48.837608 | AZ27: 49.621169 | BA27: 50.40473 | BB27: 51.188291 | BC27: 51.971852 | BD27: 52.755413 | BE27: 53.538974 | BF27: 54.322535 | BG27: 55.106096 | BH27: 55.889657 | BI27: 56.673218 | BJ27: 57.456779 | BK27: 58.240341 | BL27: 59.023902 | BM27: 59.807463 | BN27: 60.591024 | BO27: 61.374585 | BP27: 62.158146 | BQ27: 62.941707 | BR27: 63.725268 | BS27: 64.508829 | BT27: 65.29239 | BU27: 66.075951 | BV27: 66.859512 | BW27: 67.643073 | BX27: 68.426634 | BY27: 69.210195 | BZ27: 69.993756 | CA27: 70.777317 | CB27: 71.560878 | CC27: 72.344439 | CD27: 73.128 | CE27: 73.911561 | CF27: 74.695122 | CG27: 75.478683 | CH27: 76.262244 | CI27: 77.045805 | CJ27: 77.829366 | CK27: 78.612927 | CL27: 79.396488 | CM27: 80.180049 | CN27: 80.96361 | CO27: 81.747171 | CP27: 82.530732 | CQ27: 83.314293 | CR27: 84.097854 | CS27: 84.881415 | CT27: 85.664976 | CU27: 86.448537 | CV27: 87.232098 | CW27: 88.309022 | CX27: 89.385945 | CY27: 90.462868 | CZ27: 91.539791 | DA27: 92.616714 | DB27: 93.693637 | DC27: 94.77056 | DD27: 95.847483 | DE27: 96.924406 | DF27: 98.001329 | DG27: =CW27/0.65 -> 135.86003 | DH27: =CX27/0.65 -> 137.51684 | DI27: =CY27/0.65 -> 139.17364 | DJ27: =CZ27/0.65 -> 140.83045 | DK27: =DA27/0.65 -> 142.48725 | DL27: =DB27/0.65 -> 144.14406 | DM27: =DC27/0.65 -> 145.80086 | DN27: =DD27/0.65 -> 147.45767 | ... DP27: =DF27/0.65 -> 150.77128 | DQ27: 109.84748 | DR27: 110.92441 | DS27: 112.00133 | DT27: 113.07825 | DU27: 114.15518 | DV27: 115.2321 | DW27: 116.30902 | DX27: 117.38594 | DY27: 118.46287 | DZ27: 119.53979 | EA27: 120.61671 | EB27: 121.69364 | EC27: 122.77056 | ED27: 123.84748 | EE27: 124.92441 | EF27: 126.00133 | EG27: 127.07825 | EH27: 128.15518 | EI27: 129.2321 | EJ27: 130.30902 | EK27: 131.38594 | EL27: 132.46287 | EM27: 133.53979 | EN27: 134.61671 | EO27: 135.69364 | EP27: 136.77056 | EQ27: 137.84748 | ER27: 138.92441 | ES27: 140.00133 | ET27: 141.07825
A28: 5 | B28: 7.8370821 | C28: 7.8370821 | D28: 8.8193795 | E28: 9.6828769 | F28: 10.843374 | G28: 12.003872 | H28: 13.142186 | I28: 13.827483 | J28: 14.512781 | K28: 15.198078 | L28: 15.883376 | M28: 16.568673 | N28: 17.253971 | O28: 17.939268 | P28: 18.624565 | Q28: 19.309863 | R28: 19.99516 | S28: 20.680458 | T28: 21.365755 | U28: 22.051053 | V28: 22.73635 | W28: 23.421647 | X28: 24.106945 | Y28: 24.792242 | Z28: 25.47754 | AA28: 26.162837 | AB28: 26.848135 | AC28: 27.533432 | AD28: 28.218729 | AE28: 28.904027 | AF28: 29.589324 | AG28: 30.274622 | AH28: 30.959919 | AI28: 31.645217 | AJ28: 32.330514 | AK28: 33.015812 | AL28: 33.701109 | AM28: 34.386406 | AN28: 35.071704 | AO28: 37.122468 | AP28: 37.807765 | AQ28: 38.493063 | AR28: 39.17836 | AS28: 39.863658 | AT28: 40.548955 | AU28: 41.234253 | AV28: 41.91955 | AW28: 41.239381 | AX28: 41.924678 | AY28: 42.609976 | AZ28: 43.295273 | BA28: 43.980571 | BB28: 44.665868 | BC28: 45.351165 | BD28: 46.036463 | BE28: 46.72176 | BF28: 47.407058 | BG28: 48.092355 | BH28: 48.777653 | BI28: 49.46295 | BJ28: 50.148247 | BK28: 50.833545 | BL28: 51.518842 | BM28: 52.20414 | BN28: 52.889437 | BO28: 53.574735 | BP28: 54.260032 | BQ28: 54.945329 | BR28: 55.630627 | BS28: 56.315924 | BT28: 57.001222 | BU28: 57.686519 | BV28: 58.371817 | BW28: 59.057114 | BX28: 59.742412 | BY28: 60.427709 | BZ28: 61.113006 | CA28: 61.798304 | CB28: 62.483601 | CC28: 63.168899 | CD28: 63.854196 | CE28: 64.539494 | CF28: 65.224791 | CG28: 65.910088 | CH28: 66.595386 | CI28: 67.280683 | CJ28: 67.965981 | CK28: 68.651278 | CL28: 69.336576 | CM28: 70.021873 | CN28: 70.707171 | CO28: 71.392468 | CP28: 72.077765 | CQ28: 72.763063 | CR28: 73.44836 | CS28: 74.133658 | CT28: 74.818955 | CU28: 75.504253 | CV28: 76.18955 | CW28: 77.18955 | CX28: 78.18955 | CY28: 79.18955 | CZ28: 80.18955 | DA28: 81.18955 | DB28: 82.18955 | DC28: 83.18955 | DD28: 84.18955 | DE28: 85.18955 | DF28: 86.18955 | DG28: =CW28/0.65 -> 118.75315 | DH28: =CX28/0.65 -> 120.29162 | DI28: =CY28/0.65 -> 121.83008 | DJ28: =CZ28/0.65 -> 123.36854 | DK28: =DA28/0.65 -> 124.907 | DL28: =DB28/0.65 -> 126.44546 | DM28: =DC28/0.65 -> 127.98392 | DN28: =DD28/0.65 -> 129.52238 | ... DP28: =DF28/0.65 -> 132.59931 | DQ28: 97.18955 | DR28: 98.18955 | DS28: 99.18955 | DT28: 100.18955 | DU28: 101.18955 | DV28: 102.18955 | DW28: 103.18955 | DX28: 104.18955 | DY28: 105.18955 | DZ28: 106.18955 | EA28: 107.18955 | EB28: 108.18955 | EC28: 109.18955 | ED28: 110.18955 | EE28: 111.18955 | EF28: 112.18955 | EG28: 113.18955 | EH28: 114.18955 | EI28: 115.18955 | EJ28: 116.18955 | EK28: 117.18955 | EL28: 118.18955 | EM28: 119.18955 | EN28: 120.18955 | EO28: 121.18955 | EP28: 122.18955 | EQ28: 123.18955 | ER28: 124.18955 | ES28: 125.18955 | ET28: 126.18955
A29: 10 | B29: 6.9688147 | C29: 6.9688147 | D29: 7.8742366 | E29: 8.6668013 | F29: 9.7415091 | G29: 10.816217 | H29: 11.876818 | I29: 12.500096 | J29: 13.123375 | K29: 13.746654 | L29: 14.369933 | M29: 14.993212 | N29: 15.616491 | O29: 16.23977 | P29: 16.863049 | Q29: 17.486327 | R29: 18.109606 | S29: 18.732885 | T29: 19.356164 | U29: 19.979443 | V29: 20.602722 | W29: 21.226001 | X29: 21.84928 | Y29: 22.472558 | Z29: 23.095837 | AA29: 23.719116 | AB29: 24.342395 | AC29: 24.965674 | AD29: 25.588953 | AE29: 26.212232 | AF29: 26.83551 | AG29: 27.458789 | AH29: 28.082068 | AI29: 28.705347 | AJ29: 29.328626 | AK29: 29.951905 | AL29: 30.575184 | AM29: 31.198463 | AN29: 31.821741 | AO29: 33.68645 | AP29: 34.309729 | AQ29: 34.933008 | AR29: 35.556286 | AS29: 36.179565 | AT29: 36.802844 | AU29: 37.426123 | AV29: 38.049402 | AW29: 37.431251 | AX29: 38.05453 | AY29: 38.677809 | AZ29: 39.301088 | BA29: 39.924367 | BB29: 40.547646 | BC29: 41.170925 | BD29: 41.794203 | BE29: 42.417482 | BF29: 43.040761 | BG29: 43.66404 | BH29: 44.287319 | BI29: 44.910598 | BJ29: 45.533877 | BK29: 46.157156 | BL29: 46.780434 | BM29: 47.403713 | BN29: 48.026992 | BO29: 48.650271 | BP29: 49.27355 | BQ29: 49.896829 | BR29: 50.520108 | BS29: 51.143386 | BT29: 51.766665 | BU29: 52.389944 | BV29: 53.013223 | BW29: 53.636502 | BX29: 54.259781 | BY29: 54.88306 | BZ29: 55.506339 | CA29: 56.129617 | CB29: 56.752896 | CC29: 57.376175 | CD29: 57.999454 | CE29: 58.622733 | CF29: 59.246012 | CG29: 59.869291 | CH29: 60.49257 | CI29: 61.115848 | CJ29: 61.739127 | CK29: 62.362406 | CL29: 62.985685 | CM29: 63.608964 | CN29: 64.232243 | CO29: 64.855522 | CP29: 65.478801 | CQ29: 66.102079 | CR29: 66.725358 | CS29: 67.348637 | CT29: 67.971916 | CU29: 68.595195 | CV29: 69.218474 | CW29: 70.141551 | CX29: 71.064628 | CY29: 71.987705 | CZ29: 72.910781 | DA29: 73.833858 | DB29: 74.756935 | DC29: 75.680012 | DD29: 76.603089 | DE29: 77.526166 | DF29: 78.449243 | DG29: =CW29/0.65 -> 107.91008 | DH29: =CX29/0.65 -> 109.3302 | DI29: =CY29/0.65 -> 110.75031 | DJ29: =CZ29/0.65 -> 112.17043 | DK29: =DA29/0.65 -> 113.59055 | DL29: =DB29/0.65 -> 115.01067 | DM29: =DC29/0.65 -> 116.43079 | DN29: =DD29/0.65 -> 117.85091 | ... DP29: =DF29/0.65 -> 120.69114 | DQ29: 88.603089 | DR29: 89.526166 | DS29: 90.449243 | DT29: 91.37232 | DU29: 92.295397 | DV29: 93.218474 | DW29: 94.141551 | DX29: 95.064628 | DY29: 95.987705 | DZ29: 96.910781 | EA29: 97.833858 | EB29: 98.756935 | EC29: 99.680012 | ED29: 100.60309 | EE29: 101.52617 | EF29: 102.44924 | EG29: 103.37232 | EH29: 104.2954 | EI29: 105.21847 | EJ29: 106.14155 | EK29: 107.06463 | EL29: 107.9877 | EM29: 108.91078 | EN29: 109.83386 | EO29: 110.75694 | EP29: 111.68001 | EQ29: 112.60309 | ER29: 113.52617 | ES29: 114.44924 | ET29: 115.37232
A30: 15 | B30: 6.5292336 | C30: 6.5292336 | D30: 7.4001049 | E30: 8.158893 | F30: 9.1978891 | G30: 10.236885 | H30: 11.268961 | I30: 11.859624 | J30: 12.450287 | K30: 13.04095 | L30: 13.631614 | M30: 14.222277 | N30: 14.81294 | O30: 15.403604 | P30: 15.994267 | Q30: 16.58493 | R30: 17.175594 | S30: 17.766257 | T30: 18.35692 | U30: 18.947583 | V30: 19.538247 | W30: 20.12891 | X30: 20.719573 | Y30: 21.310237 | Z30: 21.9009 | AA30: 22.491563 | AB30: 23.082227 | AC30: 23.67289 | AD30: 24.263553 | AE30: 24.854217 | AF30: 25.44488 | AG30: 26.035543 | AH30: 26.626206 | AI30: 27.21687 | AJ30: 27.807533 | AK30: 28.398196 | AL30: 28.98886 | AM30: 29.579523 | AN30: 30.170186 | AO30: 31.937048 | AP30: 32.527711 | AQ30: 33.118375 | AR30: 33.709038 | AS30: 34.299701 | AT30: 34.890364 | AU30: 35.481028 | AV30: 36.071691 | AW30: 35.486156 | AX30: 36.076819 | AY30: 36.667483 | AZ30: 37.258146 | BA30: 37.848809 | BB30: 38.439472 | BC30: 39.030136 | BD30: 39.620799 | BE30: 40.211462 | BF30: 40.802126 | BG30: 41.392789 | BH30: 41.983452 | BI30: 42.574116 | BJ30: 43.164779 | BK30: 43.755442 | BL30: 44.346105 | BM30: 44.936769 | BN30: 45.527432 | BO30: 46.118095 | BP30: 46.708759 | BQ30: 47.299422 | BR30: 47.890085 | BS30: 48.480749 | BT30: 49.071412 | BU30: 49.662075 | BV30: 50.252739 | BW30: 50.843402 | BX30: 51.434065 | BY30: 52.024728 | BZ30: 52.615392 | CA30: 53.206055 | CB30: 53.796718 | CC30: 54.387382 | CD30: 54.978045 | CE30: 55.568708 | CF30: 56.159372 | CG30: 56.750035 | CH30: 57.340698 | CI30: 57.931361 | CJ30: 58.522025 | CK30: 59.112688 | CL30: 59.703351 | CM30: 60.294015 | CN30: 60.884678 | CO30: 61.475341 | CP30: 62.066005 | CQ30: 62.656668 | CR30: 63.247331 | CS30: 63.837994 | CT30: 64.428658 | CU30: 65.019321 | CV30: 65.609984 | CW30: 66.456138 | CX30: 67.302292 | CY30: 68.148446 | CZ30: 68.9946 | DA30: 69.840754 | DB30: 70.686907 | DC30: 71.533061 | DD30: 72.379215 | DE30: 73.225369 | DF30: 74.071523 | DG30: =CW30/0.65 -> 102.24021 | DH30: =CX30/0.65 -> 103.54199 | DI30: =CY30/0.65 -> 104.84376 | DJ30: =CZ30/0.65 -> 106.14554 | DK30: =DA30/0.65 -> 107.44731 | DL30: =DB30/0.65 -> 108.74909 | DM30: =DC30/0.65 -> 110.05086 | DN30: =DD30/0.65 -> 111.35264 | ... DP30: =DF30/0.65 -> 113.95619 | DQ30: 83.379215 | DR30: 84.225369 | DS30: 85.071523 | DT30: 85.917677 | DU30: 86.763831 | DV30: 87.609984 | DW30: 88.456138 | DX30: 89.302292 | DY30: 90.148446 | DZ30: 90.9946 | EA30: 91.840754 | EB30: 92.686907 | EC30: 93.533061 | ED30: 94.379215 | EE30: 95.225369 | EF30: 96.071523 | EG30: 96.917677 | EH30: 97.763831 | EI30: 98.609984 | EJ30: 99.456138 | EK30: 100.30229 | EL30: 101.14845 | EM30: 101.9946 | EN30: 102.84075 | EO30: 103.68691 | EP30: 104.53306 | EQ30: 105.37922 | ER30: 106.22537 | ES30: 107.07152 | ET30: 107.91768
A31: 25 | B31: 6.1018422 | C31: 6.1018422 | D31: 6.9389915 | E31: 7.6648629 | F31: 8.6689292 | G31: 9.6729956 | H31: 10.677062 | I31: 11.236016 | J31: 11.794971 | K31: 12.353925 | L31: 12.912879 | M31: 13.471833 | N31: 14.030788 | O31: 14.589742 | P31: 15.148696 | Q31: 15.70765 | R31: 16.266605 | S31: 16.825559 | T31: 17.384513 | U31: 17.943467 | V31: 18.502422 | W31: 19.061376 | X31: 19.62033 | Y31: 20.179284 | Z31: 20.738239 | AA31: 21.297193 | AB31: 21.856147 | AC31: 22.415101 | AD31: 22.974056 | AE31: 23.53301 | AF31: 24.091964 | AG31: 24.650918 | AH31: 25.209873 | AI31: 25.768827 | AJ31: 26.327781 | AK31: 26.886735 | AL31: 27.44569 | AM31: 28.004644 | AN31: 28.563598 | AO31: 30.235333 | AP31: 30.794287 | AQ31: 31.353241 | AR31: 31.912196 | AS31: 32.47115 | AT31: 33.030104 | AU31: 33.589058 | AV31: 34.148013 | AW31: 33.594187 | AX31: 34.153141 | AY31: 34.712095 | AZ31: 35.271049 | BA31: 35.830004 | BB31: 36.388958 | BC31: 36.947912 | BD31: 37.506866 | BE31: 38.065821 | BF31: 38.624775 | BG31: 39.183729 | BH31: 39.742683 | BI31: 40.301638 | BJ31: 40.860592 | BK31: 41.419546 | BL31: 41.9785 | BM31: 42.537455 | BN31: 43.096409 | BO31: 43.655363 | BP31: 44.214317 | BQ31: 44.773272 | BR31: 45.332226 | BS31: 45.89118 | BT31: 46.450134 | BU31: 47.009089 | BV31: 47.568043 | BW31: 48.126997 | BX31: 48.685951 | BY31: 49.244906 | BZ31: 49.80386 | CA31: 50.362814 | CB31: 50.921768 | CC31: 51.480723 | CD31: 52.039677 | CE31: 52.598631 | CF31: 53.157585 | CG31: 53.71654 | CH31: 54.275494 | CI31: 54.834448 | CJ31: 55.393403 | CK31: 55.952357 | CL31: 56.511311 | CM31: 57.070265 | CN31: 57.62922 | CO31: 58.188174 | CP31: 58.747128 | CQ31: 59.306082 | CR31: 59.865037 | CS31: 60.423991 | CT31: 60.982945 | CU31: 61.541899 | CV31: 62.100854 | CW31: 62.870084 | CX31: 63.639315 | CY31: 64.408546 | CZ31: 65.177777 | DA31: 65.947007 | DB31: 66.716238 | DC31: 67.485469 | DD31: 68.2547 | DE31: 69.023931 | DF31: 69.793161 | DG31: =CW31/0.65 -> 96.723207 | DH31: =CX31/0.65 -> 97.906639 | DI31: =CY31/0.65 -> 99.090071 | DJ31: =CZ31/0.65 -> 100.2735 | DK31: =DA31/0.65 -> 101.45693 | DL31: =DB31/0.65 -> 102.64037 | DM31: =DC31/0.65 -> 103.8238 | DN31: =DD31/0.65 -> 105.00723 | ... DP31: =DF31/0.65 -> 107.37409 | DQ31: 78.2547 | DR31: 79.023931 | DS31: 79.793161 | DT31: 80.562392 | DU31: 81.331623 | DV31: 82.100854 | DW31: 82.870084 | DX31: 83.639315 | DY31: 84.408546 | DZ31: 85.177777 | EA31: 85.947007 | EB31: 86.716238 | EC31: 87.485469 | ED31: 88.2547 | EE31: 89.023931 | EF31: 89.793161 | EG31: 90.562392 | EH31: 91.331623 | EI31: 92.100854 | EJ31: 92.870084 | EK31: 93.639315 | EL31: 94.408546 | EM31: 95.177777 | EN31: 95.947007 | EO31: 96.716238 | EP31: 97.485469 | EQ31: 98.2547 | ER31: 99.023931 | ES31: 99.793161 | ET31: 100.56239
A32: 50 | B32: 5.5602311 | C32: 5.5602311 | D32: 6.2891168 | E32: 6.943508 | F32: 7.7934473 | G32: 8.624763 | H32: 9.5119495 | I32: 10.017352 | J32: 10.522754 | K32: 11.028156 | L32: 11.533558 | M32: 12.03896 | N32: 12.544362 | O32: 13.049764 | P32: 13.555167 | Q32: 14.060569 | R32: 14.565971 | S32: 15.071373 | T32: 15.576775 | U32: 16.082177 | V32: 16.587579 | W32: 17.092982 | X32: 17.598384 | Y32: 18.103786 | Z32: 18.609188 | AA32: 19.11459 | AB32: 19.619992 | AC32: 20.125394 | AD32: 20.630796 | AE32: 21.136199 | AF32: 21.641601 | AG32: 22.147003 | AH32: 22.652405 | AI32: 23.157807 | AJ32: 23.663209 | AK32: 24.168611 | AL32: 24.674014 | AM32: 25.179416 | AN32: 25.684818 | AO32: 27.195896 | AP32: 27.701298 | AQ32: 28.2067 | AR32: 28.712102 | AS32: 29.217505 | AT32: 29.722907 | AU32: 30.228309 | AV32: 30.733711 | AW32: 30.233437 | AX32: 30.738839 | AY32: 31.244241 | AZ32: 31.749643 | BA32: 32.255046 | BB32: 32.760448 | BC32: 33.26585 | BD32: 33.771252 | BE32: 34.276654 | BF32: 34.782056 | BG32: 35.287458 | BH32: 35.79286 | BI32: 36.298263 | BJ32: 36.803665 | BK32: 37.309067 | BL32: 37.814469 | BM32: 38.319871 | BN32: 38.825273 | BO32: 39.330675 | BP32: 39.836078 | BQ32: 40.34148 | BR32: 40.846882 | BS32: 41.352284 | BT32: 41.857686 | BU32: 42.363088 | BV32: 42.86849 | BW32: 43.373892 | BX32: 43.879295 | BY32: 44.384697 | BZ32: 44.890099 | CA32: 45.395501 | CB32: 45.900903 | CC32: 46.406305 | CD32: 46.911707 | CE32: 47.41711 | CF32: 47.922512 | CG32: 48.427914 | CH32: 48.933316 | CI32: 49.438718 | CJ32: 49.94412 | CK32: 50.449522 | CL32: 50.954924 | CM32: 51.460327 | CN32: 51.965729 | CO32: 52.471131 | CP32: 52.976533 | CQ32: 53.481935 | CR32: 53.987337 | CS32: 54.492739 | CT32: 54.998142 | CU32: 55.503544 | CV32: 56.008946 | CW32: 56.701253 | CX32: 57.393561 | CY32: 58.085869 | CZ32: 58.778177 | DA32: 59.470484 | DB32: 60.162792 | DC32: 60.8551 | DD32: 61.547407 | DE32: 62.239715 | DF32: 62.932023 | DG32: =CW32/0.65 -> 87.232698 | DH32: =CX32/0.65 -> 88.297786 | DI32: =CY32/0.65 -> 89.362875 | DJ32: =CZ32/0.65 -> 90.427964 | DK32: =DA32/0.65 -> 91.493053 | DL32: =DB32/0.65 -> 92.558141 | DM32: =DC32/0.65 -> 93.62323 | DN32: =DD32/0.65 -> 94.688319 | ... DP32: =DF32/0.65 -> 96.818496 | DQ32: 70.547407 | DR32: 71.239715 | DS32: 71.932023 | DT32: 72.62433 | DU32: 73.316638 | DV32: 74.008946 | DW32: 74.701253 | DX32: 75.393561 | DY32: 76.085869 | DZ32: 76.778177 | EA32: 77.470484 | EB32: 78.162792 | EC32: 78.8551 | ED32: 79.547407 | EE32: 80.239715 | EF32: 80.932023 | EG32: 81.62433 | EH32: 82.316638 | EI32: 83.008946 | EJ32: 83.701253 | EK32: 84.393561 | EL32: 85.085869 | EM32: 85.778177 | EN32: 86.470484 | EO32: 87.162792 | EP32: 87.8551 | EQ32: 88.547407 | ER32: 89.239715 | ES32: 89.932023 | ET32: 90.62433
A33: 75 | B33: 5.049341 | C33: 5.049341 | D33: 5.6736093 | E33: 6.2601986 | F33: 6.959825 | G33: 7.6217723 | H33: 8.3967568 | I33: 8.8514694 | J33: 9.306182 | K33: 9.7608946 | L33: 10.215607 | M33: 10.67032 | N33: 11.125032 | O33: 11.579745 | P33: 12.034458 | Q33: 12.48917 | R33: 12.943883 | S33: 13.398596 | T33: 13.853308 | U33: 14.308021 | V33: 14.762733 | W33: 15.217446 | X33: 15.672159 | Y33: 16.126871 | Z33: 16.581584 | AA33: 17.036296 | AB33: 17.491009 | AC33: 17.945722 | AD33: 18.400434 | AE33: 18.855147 | AF33: 19.30986 | AG33: 19.764572 | AH33: 20.219285 | AI33: 20.673997 | AJ33: 21.12871 | AK33: 21.583423 | AL33: 22.038135 | AM33: 22.492848 | AN33: 22.94756 | AO33: 24.30657 | AP33: 24.761283 | AQ33: 25.215995 | AR33: 25.670708 | AS33: 26.125421 | AT33: 26.580133 | AU33: 27.034846 | AV33: 27.489558 | AW33: 27.039974 | AX33: 27.494687 | AY33: 27.949399 | AZ33: 28.404112 | BA33: 28.858824 | BB33: 29.313537 | BC33: 29.76825 | BD33: 30.222962 | BE33: 30.677675 | BF33: 31.132388 | BG33: 31.5871 | BH33: 32.041813 | BI33: 32.496525 | BJ33: 32.951238 | BK33: 33.405951 | BL33: 33.860663 | BM33: 34.315376 | BN33: 34.770088 | BO33: 35.224801 | BP33: 35.679514 | BQ33: 36.134226 | BR33: 36.588939 | BS33: 37.043652 | BT33: 37.498364 | BU33: 37.953077 | BV33: 38.407789 | BW33: 38.862502 | BX33: 39.317215 | BY33: 39.771927 | BZ33: 40.22664 | CA33: 40.681352 | CB33: 41.136065 | CC33: 41.590778 | CD33: 42.04549 | CE33: 42.500203 | CF33: 42.954916 | CG33: 43.409628 | CH33: 43.864341 | CI33: 44.319053 | CJ33: 44.773766 | CK33: 45.228479 | CL33: 45.683191 | CM33: 46.137904 | CN33: 46.592616 | CO33: 47.047329 | CP33: 47.502042 | CQ33: 47.956754 | CR33: 48.411467 | CS33: 48.86618 | CT33: 49.320892 | CU33: 49.775605 | CV33: 50.230317 | CW33: 50.845702 | CX33: 51.461087 | CY33: 52.076471 | CZ33: 52.691856 | DA33: 53.30724 | DB33: 53.922625 | DC33: 54.53801 | DD33: 55.153394 | DE33: 55.768779 | DF33: 56.384164 | DG33: =CW33/0.65 -> 78.224157 | DH33: =CX33/0.65 -> 79.170903 | DI33: =CY33/0.65 -> 80.117648 | DJ33: =CZ33/0.65 -> 81.064394 | DK33: =DA33/0.65 -> 82.011139 | DL33: =DB33/0.65 -> 82.957885 | DM33: =DC33/0.65 -> 83.90463 | DN33: =DD33/0.65 -> 84.851376 | ... DP33: =DF33/0.65 -> 86.744867 | DQ33: 63.153394 | DR33: 63.768779 | DS33: 64.384164 | DT33: 64.999548 | DU33: 65.614933 | DV33: 66.230317 | DW33: 66.845702 | DX33: 67.461087 | DY33: 68.076471 | DZ33: 68.691856 | EA33: 69.30724 | EB33: 69.922625 | EC33: 70.53801 | ED33: 71.153394 | EE33: 71.768779 | EF33: 72.384164 | EG33: 72.999548 | EH33: 73.614933 | EI33: 74.230317 | EJ33: 74.845702 | EK33: 75.461087 | EL33: 76.076471 | EM33: 76.691856 | EN33: 77.30724 | EO33: 77.922625 | EP33: 78.53801 | EQ33: 79.153394 | ER33: 79.768779 | ES33: 80.384164 | ET33: 80.999548
A34: 100 | B34: 4.5238462 | C34: 4.5238462 | D34: 5.0406564 | E34: 5.5574667 | F34: 6.1028462 | G34: 6.5910872 | H34: 7.2507436 | I34: 7.68756 | J34: 8.1243764 | K34: 8.5611928 | L34: 8.9980092 | M34: 9.4348256 | N34: 9.8716421 | O34: 10.308458 | P34: 10.745275 | Q34: 11.182091 | R34: 11.618908 | S34: 12.055724 | T34: 12.492541 | U34: 12.929357 | V34: 13.366173 | W34: 13.80299 | X34: 14.239806 | Y34: 14.676623 | Z34: 15.113439 | AA34: 15.550255 | AB34: 15.987072 | AC34: 16.423888 | AD34: 16.860705 | AE34: 17.297521 | AF34: 17.734337 | AG34: 18.171154 | AH34: 18.60797 | AI34: 19.044787 | AJ34: 19.481603 | AK34: 19.918419 | AL34: 20.355236 | AM34: 20.792052 | AN34: 21.228869 | AO34: 22.53419 | AP34: 22.971006 | AQ34: 23.407823 | AR34: 23.844639 | AS34: 24.281455 | AT34: 24.718272 | AU34: 25.155088 | AV34: 25.591905 | AW34: 25.160216 | AX34: 25.597033 | AY34: 26.033849 | AZ34: 26.470666 | BA34: 26.907482 | BB34: 27.344298 | BC34: 27.781115 | BD34: 28.217931 | BE34: 28.654748 | BF34: 29.091564 | BG34: 29.528381 | BH34: 29.965197 | BI34: 30.402013 | BJ34: 30.83883 | BK34: 31.275646 | BL34: 31.712463 | BM34: 32.149279 | BN34: 32.586095 | BO34: 33.022912 | BP34: 33.459728 | BQ34: 33.896545 | BR34: 34.333361 | BS34: 34.770177 | BT34: 35.206994 | BU34: 35.64381 | BV34: 36.080627 | BW34: 36.517443 | BX34: 36.954259 | BY34: 37.391076 | BZ34: 37.827892 | CA34: 38.264709 | CB34: 38.701525 | CC34: 39.138342 | CD34: 39.575158 | CE34: 40.011974 | CF34: 40.448791 | CG34: 40.885607 | CH34: 41.322424 | CI34: 41.75924 | CJ34: 42.196056 | CK34: 42.632873 | CL34: 43.069689 | CM34: 43.506506 | CN34: 43.943322 | CO34: 44.380138 | CP34: 44.816955 | CQ34: 45.253771 | CR34: 45.690588 | CS34: 46.127404 | CT34: 46.564221 | CU34: 47.001037 | CV34: 47.437853 | CW34: 48.037853 | CX34: 48.637853 | CY34: 49.237853 | CZ34: 49.837853 | DA34: 50.437853 | DB34: 51.037853 | DC34: 51.637853 | DD34: 52.237853 | DE34: 52.837853 | DF34: 53.437853 | DG34: =CW34/0.65 -> 73.90439 | DH34: =CX34/0.65 -> 74.827467 | DI34: =CY34/0.65 -> 75.750544 | DJ34: =CZ34/0.65 -> 76.673621 | DK34: =DA34/0.65 -> 77.596697 | DL34: =DB34/0.65 -> 78.519774 | DM34: =DC34/0.65 -> 79.442851 | DN34: =DD34/0.65 -> 80.365928 | ... DP34: =DF34/0.65 -> 82.212082 | DQ34: 60.037853 | DR34: 60.637853 | DS34: 61.237853 | DT34: 61.837853 | DU34: 62.437853 | DV34: 63.037853 | DW34: 63.637853 | DX34: 64.237853 | DY34: 64.837853 | DZ34: 65.437853 | EA34: 66.037853 | EB34: 66.637853 | EC34: 67.237853 | ED34: 67.837853 | EE34: 68.437853 | EF34: 69.037853 | EG34: 69.637853 | EH34: 70.237853 | EI34: 70.837853 | EJ34: 71.437853 | EK34: 72.037853 | EL34: 72.637853 | EM34: 73.237853 | EN34: 73.837853 | EO34: 74.437853 | EP34: 75.037853 | EQ34: 75.637853 | ER34: 76.237853 | ES34: 76.837853 | ET34: 77.437853
A35: 250 | B35: 4.0615344 | C35: 4.0615344 | D35: 4.4722954 | E35: 4.9413703 | F35: 5.4104451 | G35: 5.87952 | H35: 6.4069087 | I35: 6.8293325 | J35: 7.2517563 | K35: 7.6741801 | L35: 8.0966039 | M35: 8.5190277 | N35: 8.9414515 | O35: 9.3638753 | P35: 9.7862991 | Q35: 10.208723 | R35: 10.631147 | S35: 11.05357 | T35: 11.475994 | U35: 11.898418 | V35: 12.320842 | W35: 12.743266 | X35: 13.165689 | Y35: 13.588113 | Z35: 14.010537 | AA35: 14.432961 | AB35: 14.855385 | AC35: 15.277808 | AD35: 15.700232 | AE35: 16.122656 | AF35: 16.54508 | AG35: 16.967504 | AH35: 17.389927 | AI35: 17.812351 | AJ35: 18.234775 | AK35: 18.657199 | AL35: 19.079623 | AM35: 19.502046 | AN35: 19.92447 | AO35: 21.186613 | AP35: 21.609037 | AQ35: 22.031461 | AR35: 22.453885 | AS35: 22.876309 | AT35: 23.298732 | AU35: 23.721156 | AV35: 24.14358 | AW35: 23.726284 | AX35: 24.148708 | AY35: 24.571132 | AZ35: 24.993556 | BA35: 25.415979 | BB35: 25.838403 | BC35: 26.260827 | BD35: 26.683251 | BE35: 27.105675 | BF35: 27.528098 | BG35: 27.950522 | BH35: 28.372946 | BI35: 28.79537 | BJ35: 29.217794 | BK35: 29.640217 | BL35: 30.062641 | BM35: 30.485065 | BN35: 30.907489 | BO35: 31.329913 | BP35: 31.752336 | BQ35: 32.17476 | BR35: 32.597184 | BS35: 33.019608 | BT35: 33.442032 | BU35: 33.864455 | BV35: 34.286879 | BW35: 34.709303 | BX35: 35.131727 | BY35: 35.554151 | BZ35: 35.976574 | CA35: 36.398998 | CB35: 36.821422 | CC35: 37.243846 | CD35: 37.66627 | CE35: 38.088693 | CF35: 38.511117 | CG35: 38.933541 | CH35: 39.355965 | CI35: 39.778389 | CJ35: 40.200812 | CK35: 40.623236 | CL35: 41.04566 | CM35: 41.468084 | CN35: 41.890507 | CO35: 42.312931 | CP35: 42.735355 | CQ35: 43.157779 | CR35: 43.580203 | CS35: 44.002626 | CT35: 44.42505 | CU35: 44.847474 | CV35: 45.269898 | CW35: 45.854513 | CX35: 46.439129 | CY35: 47.023744 | CZ35: 47.608359 | DA35: 48.192975 | DB35: 48.77759 | DC35: 49.362206 | DD35: 49.946821 | DE35: 50.531436 | DF35: 51.116052 | DG35: =CW35/0.65 -> 70.545405 | DH35: =CX35/0.65 -> 71.444813 | DI35: =CY35/0.65 -> 72.344222 | DJ35: =CZ35/0.65 -> 73.24363 | DK35: =DA35/0.65 -> 74.143038 | DL35: =DB35/0.65 -> 75.042446 | DM35: =DC35/0.65 -> 75.941855 | DN35: =DD35/0.65 -> 76.841263 | ... DP35: =DF35/0.65 -> 78.64008 | DQ35: 57.546821 | DR35: 58.131436 | DS35: 58.716052 | DT35: 59.300667 | DU35: 59.885282 | DV35: 60.469898 | DW35: 61.054513 | DX35: 61.639129 | DY35: 62.223744 | DZ35: 62.808359 | EA35: 63.392975 | EB35: 63.97759 | EC35: 64.562206 | ED35: 65.146821 | EE35: 65.731436 | EF35: 66.316052 | EG35: 66.900667 | EH35: 67.485282 | EI35: 68.069898 | EJ35: 68.654513 | EK35: 69.239129 | EL35: 69.823744 | EM35: 70.408359 | EN35: 70.992975 | EO35: 71.57759 | EP35: 72.162206 | EQ35: 72.746821 | ER35: 73.331436 | ES35: 73.916052 | ET35: 74.500667
A36: 500 | B36: 3.5733704 | C36: 3.5733704 | D36: 3.899831 | E36: 4.3440722 | F36: 4.8177585 | G36: 5.2914449 | H36: 5.735686 | I36: 6.138704 | J36: 6.541722 | K36: 6.94474 | L36: 7.347758 | M36: 7.750776 | N36: 8.1537939 | O36: 8.5568119 | P36: 8.9598299 | Q36: 9.3628479 | R36: 9.7658659 | S36: 10.168884 | T36: 10.571902 | U36: 10.97492 | V36: 11.377938 | W36: 11.780956 | X36: 12.183974 | Y36: 12.586992 | Z36: 12.99001 | AA36: 13.393028 | AB36: 13.796046 | AC36: 14.199064 | AD36: 14.602082 | AE36: 15.0051 | AF36: 15.408118 | AG36: 15.811136 | AH36: 16.214154 | AI36: 16.617172 | AJ36: 17.02019 | AK36: 17.423208 | AL36: 17.826226 | AM36: 18.229244 | AN36: 18.632262 | AO36: 19.836187 | AP36: 20.239205 | AQ36: 20.642223 | AR36: 21.045241 | AS36: 21.448259 | AT36: 21.851277 | AU36: 22.254295 | AV36: 22.657313 | AW36: 22.259423 | AX36: 22.662441 | AY36: 23.065459 | AZ36: 23.468477 | BA36: 23.871495 | BB36: 24.274513 | BC36: 24.677531 | BD36: 25.080549 | BE36: 25.483567 | BF36: 25.886585 | BG36: 26.289603 | BH36: 26.692621 | BI36: 27.095639 | BJ36: 27.498657 | BK36: 27.901675 | BL36: 28.304693 | BM36: 28.707711 | BN36: 29.110729 | BO36: 29.513747 | BP36: 29.916765 | BQ36: 30.319783 | BR36: 30.722801 | BS36: 31.125819 | BT36: 31.528837 | BU36: 31.931855 | BV36: 32.334873 | BW36: 32.737891 | BX36: 33.140909 | BY36: 33.543927 | BZ36: 33.946945 | CA36: 34.349963 | CB36: 34.752981 | CC36: 35.155999 | CD36: 35.559017 | CE36: 35.962035 | CF36: 36.365053 | CG36: 36.768071 | CH36: 37.171089 | CI36: 37.574107 | CJ36: 37.977125 | CK36: 38.380143 | CL36: 38.783161 | CM36: 39.186179 | CN36: 39.589197 | CO36: 39.992215 | CP36: 40.395233 | CQ36: 40.798251 | CR36: 41.201269 | CS36: 41.604287 | CT36: 42.007305 | CU36: 42.410323 | CV36: 42.813341 | CW36: 43.382571 | CX36: 43.951802 | CY36: 44.521033 | CZ36: 45.090264 | DA36: 45.659495 | DB36: 46.228725 | DC36: 46.797956 | DD36: 47.367187 | DE36: 47.936418 | DF36: 48.505648 | DG36: =CW36/0.65 -> 66.742418 | DH36: =CX36/0.65 -> 67.618157 | DI36: =CY36/0.65 -> 68.493897 | DJ36: =CZ36/0.65 -> 69.369637 | DK36: =DA36/0.65 -> 70.245376 | DL36: =DB36/0.65 -> 71.121116 | DM36: =DC36/0.65 -> 71.996856 | DN36: =DD36/0.65 -> 72.872595 | ... DP36: =DF36/0.65 -> 74.624074 | DQ36: 54.767187 | DR36: 55.336418 | DS36: 55.905648 | DT36: 56.474879 | DU36: 57.04411 | DV36: 57.613341 | DW36: 58.182571 | DX36: 58.751802 | DY36: 59.321033 | DZ36: 59.890264 | EA36: 60.459495 | EB36: 61.028725 | EC36: 61.597956 | ED36: 62.167187 | EE36: 62.736418 | EF36: 63.305648 | EG36: 63.874879 | EH36: 64.44411 | EI36: 65.013341 | EJ36: 65.582571 | EK36: 66.151802 | EL36: 66.721033 | EM36: 67.290264 | EN36: 67.859495 | EO36: 68.428725 | EP36: 68.997956 | EQ36: 69.567187 | ER36: 70.136418 | ES36: 70.705648 | ET36: 71.274879
A37: 750 | B37: 3.0740623 | C37: 3.0740623 | D37: 3.4629816 | E37: 3.7924616 | F37: 4.2111006 | G37: 4.6297395 | H37: 5.0483784 | I37: 5.4313538 | J37: 5.8143292 | K37: 6.1973045 | L37: 6.5802799 | M37: 6.9632553 | N37: 7.3462307 | O37: 7.7292061 | P37: 8.1121814 | Q37: 8.4951568 | R37: 8.8781322 | S37: 9.2611076 | T37: 9.6440829 | U37: 10.027058 | V37: 10.410034 | W37: 10.793009 | X37: 11.175984 | Y37: 11.55896 | Z37: 11.941935 | AA37: 12.324911 | AB37: 12.707886 | AC37: 13.090861 | AD37: 13.473837 | AE37: 13.856812 | AF37: 14.239787 | AG37: 14.622763 | AH37: 15.005738 | AI37: 15.388714 | AJ37: 15.771689 | AK37: 16.154664 | AL37: 16.53764 | AM37: 16.920615 | AN37: 17.30359 | AO37: 18.447388 | AP37: 18.830364 | AQ37: 19.213339 | AR37: 19.596315 | AS37: 19.97929 | AT37: 20.362265 | AU37: 20.745241 | AV37: 21.128216 | AW37: 20.750369 | AX37: 21.133344 | AY37: 21.51632 | AZ37: 21.899295 | BA37: 22.28227 | BB37: 22.665246 | BC37: 23.048221 | BD37: 23.431196 | BE37: 23.814172 | BF37: 24.197147 | BG37: 24.580123 | BH37: 24.963098 | BI37: 25.346073 | BJ37: 25.729049 | BK37: 26.112024 | BL37: 26.494999 | BM37: 26.877975 | BN37: 27.26095 | BO37: 27.643926 | BP37: 28.026901 | BQ37: 28.409876 | BR37: 28.792852 | BS37: 29.175827 | BT37: 29.558803 | BU37: 29.941778 | BV37: 30.324753 | BW37: 30.707729 | BX37: 31.090704 | BY37: 31.473679 | BZ37: 31.856655 | CA37: 32.23963 | CB37: 32.622606 | CC37: 33.005581 | CD37: 33.388556 | CE37: 33.771532 | CF37: 34.154507 | CG37: 34.537482 | CH37: 34.920458 | CI37: 35.303433 | CJ37: 35.686409 | CK37: 36.069384 | CL37: 36.452359 | CM37: 36.835335 | CN37: 37.21831 | CO37: 37.601285 | CP37: 37.984261 | CQ37: 38.367236 | CR37: 38.750212 | CS37: 39.133187 | CT37: 39.516162 | CU37: 39.899138 | CV37: 40.282113 | CW37: 40.835959 | CX37: 41.389805 | CY37: 41.943652 | CZ37: 42.497498 | DA37: 43.051344 | DB37: 43.60519 | DC37: 44.159036 | DD37: 44.712882 | DE37: 45.266728 | DF37: 45.820575 | DG37: =CW37/0.65 -> 62.824553 | DH37: =CX37/0.65 -> 63.676624 | DI37: =CY37/0.65 -> 64.528695 | DJ37: =CZ37/0.65 -> 65.380766 | DK37: =DA37/0.65 -> 66.232837 | DL37: =DB37/0.65 -> 67.084908 | DM37: =DC37/0.65 -> 67.936979 | DN37: =DD37/0.65 -> 68.78905 | ... DP37: =DF37/0.65 -> 70.493192 | DQ37: 51.912882 | DR37: 52.466728 | DS37: 53.020575 | DT37: 53.574421 | DU37: 54.128267 | DV37: 54.682113 | DW37: 55.235959 | DX37: 55.789805 | DY37: 56.343652 | DZ37: 56.897498 | EA37: 57.451344 | EB37: 58.00519 | EC37: 58.559036 | ED37: 59.112882 | EE37: 59.666728 | EF37: 60.220575 | EG37: 60.774421 | EH37: 61.328267 | EI37: 61.882113 | EJ37: 62.435959 | EK37: 62.989805 | EL37: 63.543652 | EM37: 64.097498 | EN37: 64.651344 | EO37: 65.20519 | EP37: 65.759036 | EQ37: 66.312882 | ER37: 66.866728 | ES37: 67.420575 | ET37: 67.974421
A38: 1000 | B38: 2.6645126 | C38: 2.6645126 | D38: 3.0268423 | E38: 3.4191524 | F38: 3.8114625 | G38: 4.1138312 | H38: 4.4761608 | I38: 4.8384905 | J38: 5.2008201 | K38: 5.5631497 | L38: 5.9254794 | M38: 6.287809 | N38: 6.6501387 | O38: 7.0124683 | P38: 7.3747979 | Q38: 7.7371276 | R38: 8.0994572 | S38: 8.4617869 | T38: 8.8241165 | U38: 9.1864462 | V38: 9.5487758 | W38: 9.9111054 | X38: 10.273435 | Y38: 10.635765 | Z38: 10.998094 | AA38: 11.360424 | AB38: 11.722754 | AC38: 12.085083 | AD38: 12.447413 | AE38: 12.809743 | AF38: 13.172072 | AG38: 13.534402 | AH38: 13.896731 | AI38: 14.259061 | AJ38: 14.621391 | AK38: 14.98372 | AL38: 15.34605 | AM38: 15.70838 | AN38: 16.070709 | AO38: 17.15257 | AP38: 17.5149 | AQ38: 17.877229 | AR38: 18.239559 | AS38: 18.601889 | AT38: 18.964218 | AU38: 19.326548 | AV38: 19.688878 | AW38: 19.331676 | AX38: 19.694006 | AY38: 20.056335 | AZ38: 20.418665 | BA38: 20.780995 | BB38: 21.143324 | BC38: 21.505654 | BD38: 21.867984 | BE38: 22.230313 | BF38: 22.592643 | BG38: 22.954973 | BH38: 23.317302 | BI38: 23.679632 | BJ38: 24.041961 | BK38: 24.404291 | BL38: 24.766621 | BM38: 25.12895 | BN38: 25.49128 | BO38: 25.85361 | BP38: 26.215939 | BQ38: 26.578269 | BR38: 26.940599 | BS38: 27.302928 | BT38: 27.665258 | BU38: 28.027587 | BV38: 28.389917 | BW38: 28.752247 | BX38: 29.114576 | BY38: 29.476906 | BZ38: 29.839236 | CA38: 30.201565 | CB38: 30.563895 | CC38: 30.926225 | CD38: 31.288554 | CE38: 31.650884 | CF38: 32.013214 | CG38: 32.375543 | CH38: 32.737873 | CI38: 33.100202 | CJ38: 33.462532 | CK38: 33.824862 | CL38: 34.187191 | CM38: 34.549521 | CN38: 34.911851 | CO38: 35.27418 | CP38: 35.63651 | CQ38: 35.99884 | CR38: 36.361169 | CS38: 36.723499 | CT38: 37.085829 | CU38: 37.448158 | CV38: 37.810488 | CW38: 38.348949 | CX38: 38.887411 | CY38: 39.425872 | CZ38: 39.964334 | DA38: 40.502795 | DB38: 41.041257 | DC38: 41.579719 | DD38: 42.11818 | DE38: 42.656642 | DF38: 43.195103 | DG38: =CW38/0.65 -> 58.998384 | DH38: =CX38/0.65 -> 59.826786 | DI38: =CY38/0.65 -> 60.655188 | DJ38: =CZ38/0.65 -> 61.483591 | DK38: =DA38/0.65 -> 62.311993 | DL38: =DB38/0.65 -> 63.140395 | DM38: =DC38/0.65 -> 63.968798 | DN38: =DD38/0.65 -> 64.7972 | ... DP38: =DF38/0.65 -> 66.454005 | DQ38: 49.11818 | DR38: 49.656642 | DS38: 50.195103 | DT38: 50.733565 | DU38: 51.272026 | DV38: 51.810488 | DW38: 52.348949 | DX38: 52.887411 | DY38: 53.425872 | DZ38: 53.964334 | EA38: 54.502795 | EB38: 55.041257 | EC38: 55.579719 | ED38: 56.11818 | EE38: 56.656642 | EF38: 57.195103 | EG38: 57.733565 | EH38: 58.272026 | EI38: 58.810488 | EJ38: 59.348949 | EK38: 59.887411 | EL38: 60.425872 | EM38: 60.964334 | EN38: 61.502795 | EO38: 62.041257 | EP38: 62.579719 | EQ38: 63.11818 | ER38: 63.656642 | ES38: 64.195103 | ET38: 64.733565
... A42: 10000 | B42: 2.2995996 | C42: 2.2995996 | D42: 2.61859 | E42: 2.9639493 | F42: 3.3093085 | G42: 3.5755612 | H42: 3.8945517 | I42: 4.2135421 | J42: 4.5325325 | K42: 4.8515229 | L42: 5.1705133 | M42: 5.4895037 | N42: 5.8084942 | O42: 6.1274846 | P42: 6.446475 | Q42: 6.7654654 | R42: 7.0844558 | S42: 7.4034462 | T42: 7.7224367 | U42: 8.0414271 | V42: 8.3604175 | W42: 8.6794079 | X42: 8.9983983 | Y42: 9.3173887 | Z42: 9.6363792 | AA42: 9.9553696 | AB42: 10.27436 | AC42: 10.59335 | AD42: 10.912341 | AE42: 11.231331 | AF42: 11.550322 | AG42: 11.869312 | AH42: 12.188302 | AI42: 12.507293 | AJ42: 12.826283 | AK42: 13.145274 | AL42: 13.464264 | AM42: 13.783255 | AN42: 14.102245 | AO42: 15.054088 | AP42: 15.373078 | AQ42: 15.692069 | AR42: 16.011059 | AS42: 16.33005 | AT42: 16.64904 | AU42: 16.968031 | AV42: 17.287021 | AW42: 16.973159 | AX42: 17.292149 | AY42: 17.61114 | AZ42: 17.93013 | BA42: 18.24912 | BB42: 18.568111 | BC42: 18.887101 | BD42: 19.206092 | BE42: 19.525082 | BF42: 19.844072 | BG42: 20.163063 | BH42: 20.482053 | BI42: 20.801044 | BJ42: 21.120034 | BK42: 21.439025 | BL42: 21.758015 | BM42: 22.077005 | BN42: 22.395996 | BO42: 22.714986 | BP42: 23.033977 | BQ42: 23.352967 | BR42: 23.671957 | BS42: 23.990948 | BT42: 24.309938 | BU42: 24.628929 | BV42: 24.947919 | BW42: 25.26691 | BX42: 25.5859 | BY42: 25.90489 | BZ42: 26.223881 | CA42: 26.542871 | CB42: 26.861862 | CC42: 27.180852 | CD42: 27.499842 | CE42: 27.818833 | CF42: 28.137823 | CG42: 28.456814 | CH42: 28.775804 | CI42: 29.094795 | CJ42: 29.413785 | CK42: 29.732775 | CL42: 30.051766 | CM42: 30.370756 | CN42: 30.689747 | CO42: 31.008737 | CP42: 31.327727 | CQ42: 31.646718 | CR42: 31.965708 | CS42: 32.284699 | CT42: 32.603689 | CU42: 32.92268 | CV42: 33.24167 | CW42: 33.718593 | CX42: 34.195516 | CY42: 34.672439 | CZ42: 35.149362 | DA42: 35.626285 | DB42: 36.103208 | DC42: 36.580132 | DD42: 37.057055 | DE42: 37.533978 | DF42: 38.010901 | DG42: =CW42/0.65 -> 51.874759 | DH42: =CX42/0.65 -> 52.608486 | DI42: =CY42/0.65 -> 53.342214 | DJ42: =CZ42/0.65 -> 54.075942 | DK42: =DA42/0.65 -> 54.80967 | DL42: =DB42/0.65 -> 55.543398 | DM42: =DC42/0.65 -> 56.277125 | DN42: =DD42/0.65 -> 57.010853 | ... DP42: =DF42/0.65 -> 58.478309 | DQ42: 43.257055 | DR42: 43.733978 | DS42: 44.210901 | DT42: 44.687824 | DU42: 45.164747 | DV42: 45.64167 | DW42: 46.118593 | DX42: 46.595516 | DY42: 47.072439 | DZ42: 47.549362 | EA42: 48.026285 | EB42: 48.503208 | EC42: 48.980132 | ED42: 49.457055 | EE42: 49.933978 | EF42: 50.410901 | EG42: 50.887824 | EH42: 51.364747 | EI42: 51.84167 | EJ42: 52.318593 | EK42: 52.795516 | EL42: 53.272439 | EM42: 53.749362 | EN42: 54.226285 | EO42: 54.703208 | EP42: 55.180132 | EQ42: 55.657055 | ER42: 56.133978 | ES42: 56.610901 | ET42: 57.087824
A43: ARRAY= STITCHCOUNT2 | B43: < 2,000 | C43: < 3,000 | D43: < 4,000 | E43: < 5,000 | F43: < 6,000 | G43: < 7,000 | H43: < 8,000 | I43: < 9,000 | J43: < 10,000 | K43: < 11,000 | L43: < 12,000 | M43: < 13,000 | N43: < 14,000 | O43: < 15,000 | P43: <16, 000 | Q43: <17,000 | R43: < 18,000 | S43: < 19,000 | T43: < 20, 000 | U43: < 21,000 | V43: < 22,000 | W43: < 23,000 | X43: < 24,000 | Y43: < 25,000 | Z43: < 26,000 | AA43: < 27,000 | AB43: < 28,000 | AC43: < 29,000 | AD43: < 30,000 | AE43: < 31,000 | AF43: < 32,000 | AG43: < 33,000 | AH43: < 34,000 | AI43: < 35,000 | AJ43: < 36,000 | AK43: < 37,000 | AL43: < 38,000 | AM43: < 39,000 | AN43: < 40,000 | AO43: < 41,000 | AP43: < 42,000 | AQ43: < 43,000 | AR43: < 44,000 | AS43: < 45,000 | AT43: < 46,000 | AU43: < 47,000 | AV43: < 48,000 | AW43: < 49,000 | AX43: < 50,000 | AY43: < 51,000 | AZ43: < 52,000 | BA43: < 53,000 | BB43: < 54,000 | BC43: < 55,000 | BD43: < 56,000 | BE43: < 57,000 | BF43: < 58,000 | BG43: < 59,000 | BH43: < 60,000 | BI43: < 61,000 | BJ43: < 62,000 | BK43: < 63,000 | BL43: < 64,000 | BM43: < 65,000 | BN43: < 66,000 | BO43: < 67,000 | BP43: < 68,000 | BQ43: < 69,000 | BR43: < 70,000 | BS43: < 71,000 | BT43: < 72,000 | BU43: < 73,000 | BV43: < 74,000 | BW43: < 75,000 | BX43: < 76,000 | BY43: < 77,000 | BZ43: < 78,000 | CA43: < 79,000 | CB43: < 80,000 | CC43: < 81,000 | CD43: < 82,000 | CE43: < 83,000 | CF43: < 84,000 | CG43: < 85,000 | CH43: < 86,000 | CI43: < 87,000 | CJ43: < 88,000 | CK43: < 89,000 | CL43: < 90,000 | CM43: < 91,000 | CN43: < 92,000 | CO43: < 93,000 | CP43: < 94,000 | CQ43: < 95,000 | CR43: < 96,000 | CS43: < 97,000 | CT43: < 98,000 | CU43: < 99,000 | CV43: <100,000 | CW43: <101,000 | CX43: <102,000 | CY43: <103,000 | CZ43: <104,000 | DA43: <105,000 | DB43: <106,000 | DC43: <107,000 | DD43: <108,000 | DE43: <109,000 | DF43: <110,000 | DG43: <111,000 | DH43: <112,000 | DI43: <113,000 | DJ43: <114,000 | DK43: <115,000 | DL43: <116,000 | DM43: <117,000 | DN43: <118,000 | DO43: <119,000 | DP43: <120,000 | DQ43: <121,000 | DR43: <122,000 | DS43: <123,000 | DT43: <124,000 | DU43: <125,000 | DV43: <126,000 | DW43: <127,000 | DX43: <128,000 | DY43: <129,000 | DZ43: <130,000 | EA43: <131,000 | EB43: <132,000 | EC43: <133,000 | ED43: <134,000 | EE43: <135,000 | EF43: <136,000 | EG43: <137,000 | EH43: <138,000 | EI43: <139,000 | EJ43: <140,000 | EK43: <141,000 | EL43: <142,000 | EM43: <143,000 | EN43: <144,000 | EO43: <145,000 | EP43: <146,000 | EQ43: <147,000 | ER43: <148,000 | ES43: <149,000 | ET43: <150,000
A44: New Digitising | B44: 42.857143 | C44: 42.857143 | D44: 42.857143 | E44: 42.857143 | F44: 42.857143 | G44: 42.857143 | H44: 42.857143 | I44: 42.857143 | J44: 42.857143 | K44: 50 | L44: 50 | M44: 50 | N44: 50 | O44: 50 | P44: 50 | Q44: 50 | R44: 50 | S44: 50 | T44: 50 | U44: 57.142857 | V44: 57.142857 | W44: 57.142857 | X44: 57.142857 | Y44: 57.142857 | Z44: 57.142857 | AA44: 57.142857 | AB44: 57.142857 | AC44: 57.142857 | AD44: 57.142857 | AE44: 64.285714 | AF44: 64.285714 | AG44: 64.285714 | AH44: 64.285714 | AI44: 64.285714 | AJ44: 64.285714 | AK44: 64.285714 | AL44: 64.285714 | AM44: 64.285714 | AN44: 64.285714 | AO44: 71.428571 | AP44: 71.428571 | AQ44: 71.428571 | AR44: 71.428571 | AS44: 71.428571 | AT44: 71.428571 | AU44: 71.428571 | AV44: 71.428571 | AW44: 71.428571 | AX44: 71.428571 | AY44: 78.571429 | AZ44: 78.571429 | BA44: 78.571429 | BB44: 78.571429 | BC44: 78.571429 | BD44: 78.571429 | BE44: 78.571429 | BF44: 78.571429 | BG44: 78.571429 | BH44: 78.571429 | BI44: 85.714286 | BJ44: 85.714286 | BK44: 85.714286 | BL44: 85.714286 | BM44: 85.714286 | BN44: 85.714286 | BO44: 85.714286 | BP44: 85.714286 | BQ44: 85.714286 | BR44: 85.714286 | BS44: 92.857143 | BT44: 92.857143 | BU44: 92.857143 | BV44: 92.857143 | BW44: 92.857143 | BX44: 92.857143 | BY44: 92.857143 | BZ44: 92.857143 | CA44: 92.857143 | CB44: 92.857143 | CC44: 100 | CD44: 100 | CE44: 100 | CF44: 100 | CG44: 100 | CH44: 100 | CI44: 100 | CJ44: 100 | CK44: 100 | CL44: 100 | CM44: 107.14286 | CN44: 107.14286 | CO44: 107.14286 | CP44: 107.14286 | CQ44: 107.14286 | CR44: 107.14286 | CS44: 107.14286 | CT44: 107.14286 | CU44: 107.14286 | CV44: 107.14286 | CW44: 114.28571 | CX44: 114.28571 | CY44: 114.28571 | CZ44: 114.28571 | DA44: 114.28571 | DB44: 114.28571 | DC44: 114.28571 | DD44: 114.28571 | DE44: 114.28571 | DF44: 114.28571 | DG44: 121.42857 | DH44: 121.42857 | DI44: 121.42857 | DJ44: 121.42857 | DK44: 121.42857 | DL44: 121.42857 | DM44: 121.42857 | DN44: 121.42857 | DO44: 121.42857 | DP44: 121.42857 | DQ44: 128.57 | DR44: 128.57 | DS44: 128.57 | DT44: 128.57 | DU44: 128.57 | DV44: 128.57 | DW44: 128.57 | DX44: 128.57 | DY44: 128.57 | DZ44: 128.57 | EA44: 135.71 | EB44: 135.71 | EC44: 135.71 | ED44: 135.71 | EE44: 135.71 | EF44: 135.71 | EG44: 135.71 | EH44: 135.71 | EI44: 135.71 | EJ44: 135.71 | EK44: 142.86 | EL44: 142.86 | EM44: 142.86 | EN44: 142.86 | EO44: 142.86 | EP44: 142.86 | EQ44: 142.86 | ER44: 142.86 | ES44: 142.86 | ET44: 142.86
A45: Minor Change | B45: =B44/2 -> 21.428571 | C45: =C44/2 -> 21.428571 | D45: =D44/2 -> 21.428571 | E45: =E44/2 -> 21.428571 | F45: =F44/2 -> 21.428571 | G45: =G44/2 -> 21.428571 | H45: =H44/2 -> 21.428571 | I45: =I44/2 -> 21.428571 | ... ET45: =ET44/2 -> 71.43
A46: Repeat - no change | B46: 0 | C46: 0 | D46: 0 | E46: 0 | F46: 0 | G46: 0 | H46: 0 | I46: 0 | J46: 0 | K46: 0 | L46: 0 | M46: 0 | N46: 0 | O46: 0 | P46: 0 | Q46: 0 | R46: 0 | S46: 0 | T46: 0 | U46: 0 | V46: 0 | W46: 0 | X46: 0 | Y46: 0 | Z46: 0 | AA46: 0 | AB46: 0 | AC46: 0 | AD46: 0 | AE46: 0 | AF46: 0 | AG46: 0 | AH46: 0 | AI46: 0 | AJ46: 0 | AK46: 0 | AL46: 0 | AM46: 0 | AN46: 0 | AO46: 0 | AP46: 0 | AQ46: 0 | AR46: 0 | AS46: 0 | AT46: 0 | AU46: 0 | AV46: 0 | AW46: 0 | AX46: 0 | AY46: 0 | AZ46: 0 | BA46: 0 | BB46: 0 | BC46: 0 | BD46: 0 | BE46: 0 | BF46: 0 | BG46: 0 | BH46: 0 | BI46: 0 | BJ46: 0 | BK46: 0 | BL46: 0 | BM46: 0 | BN46: 0 | BO46: 0 | BP46: 0 | BQ46: 0 | BR46: 0 | BS46: 0 | BT46: 0 | BU46: 0 | BV46: 0 | BW46: 0 | BX46: 0 | BY46: 0 | BZ46: 0 | CA46: 0 | CB46: 0 | CC46: 0 | CD46: 0 | CE46: 0 | CF46: 0 | CG46: 0 | CH46: 0 | CI46: 0 | CJ46: 0 | CK46: 0 | CL46: 0 | CM46: 0 | CN46: 0 | CO46: 0 | CP46: 0 | CQ46: 0 | CR46: 0 | CS46: 0 | CT46: 0 | CU46: 0 | CV46: 0 | CW46: 0 | CX46: 0 | CY46: 0 | CZ46: 0 | DA46: 0 | DB46: 0 | DC46: 0 | DD46: 0 | DE46: 0 | DF46: 0 | DG46: 0 | DH46: 0 | DI46: 0 | DJ46: 0 | DK46: 0 | DL46: 0 | DM46: 0 | DN46: 0 | DO46: 0 | DP46: 0 | DQ46: 0 | DR46: 0 | DS46: 0 | DT46: 0 | DU46: 0 | DV46: 0 | DW46: 0 | DX46: 0 | DY46: 0 | DZ46: 0 | EA46: 0 | EB46: 0 | EC46: 0 | ED46: 0 | EE46: 0 | EF46: 0 | EG46: 0 | EH46: 0 | EI46: 0 | EJ46: 0 | EK46: 0 | EL46: 0 | EM46: 0 | EN46: 0 | EO46: 0 | EP46: 0 | EQ46: 0 | ER46: 0 | ES46: 0 | ET46: 0
A48: ARRAY = DIGITISINGOPTIONS | D48: ARRAY= DIGITISINGCOSTS
A50: CAPS | C50: SPECIAL THREAD | E50: SPECIAL HOOPS | H50: NAMES & NUMBERS
A51: STANDARD | B51: 0 | C51: STANDARD | D51: 0 | E51: NO | F51: 0 | H51: N/A | I51: 0
A52: PUFF FOAM | B52: 2.2 | C52: RECYCLED POLY | D52: =EMBROIDERY!F12*17% -> 1.5329444 | E52: YES | H52: Initials < 35mm high | I52: 7.6923077
A53: DOUBLE PUFF | B53: 4 | C53: METALLIC | D53: =EMBROIDERY!F12*20% -> 1.803464 | H53: Initials 35-60mm high | I53: 9.2307692
A54: FUSIBLE BACKING | B54: 2.85 | H54: Numbers <35mm high | I54: 7.6923077
H55: Numbers35-60mm high | I55: 9.2307692
H56: Single Names < 35mm high | I56: 9.2307692
H57: Single Names 36- 60mm high | I57: 13.846154
H58: Double Names < 35mm high | I58: 15.384615
H59: Double Names 36-60mm high | I59: 20
A61: PRINTED TRANSFERS
A62: ARRAY = TRANSFERCOST
A63: ARRAY= TRANSFERNAME | C63: DTF TRANSFERN/A | D63: DTF TRANSFERXS | E63: DTF TRANSFERSM | F63: DTF TRANSFERLC | G63: DTF TRANSFER A5 | H63: DTF TRANSFER A5 LONG | I63: DTF TRANSFERA4 | J63: DTF TRANSFERA4 LONG | K63: DTF TRANSFERSQ | L63: DTF TRANSFERA3 | M63: COLOURFLEX N/A | N63: COLOURFLEX XS | O63: COLOURFLEX SM | P63: COLOURFLEX LC | Q63: COLOURFLEX A5 | R63: COLOURFLEX A5 LONG | S63: COLOURFLEX A4 | T63: COLOURFLEX A4 LONG | U63: COLOURFLEX SQ | V63: COLOURFLEX A3 | W63: SUPACOLOUR WEARABLEN/A | X63: SUPACOLOUR WEARABLEXS | Y63: SUPACOLOUR WEARABLESM | Z63: SUPACOLOUR WEARABLELC | AA63: SUPACOLOUR WEARABLE A5 | AB63: SUPACOLOUR WEARABLE A5 LONG | AC63: SUPACOLOUR WEARABLEA4 | AD63: SUPACOLOUR WEARABLEA4 LONG | AE63: SUPACOLOUR WEARABLESQ | AF63: SUPACOLOUR WEARABLEA3 | AG63: SUPACOLOUR METALLICN/A | AH63: SUPACOLOUR METALLICXS | AI63: SUPACOLOUR METALLICSM | AJ63: SUPACOLOUR METALLICLC | AK63: SUPACOLOUR METALLIC A5 | AL63: SUPACOLOUR METALLIC A5 LONG | AM63: SUPACOLOUR METALLICA4 | AN63: SUPACOLOUR METALLICA4 LONG | AO63: SUPACOLOUR METALLICSQ | AP63: SUPACOLOUR METALLICA3 | AQ63: SUB-BLOCKER TRANSFERN/A | AR63: SUB-BLOCKER TRANSFERXS | AS63: SUB-BLOCKER TRANSFERSM | AT63: SUB-BLOCKER TRANSFERLC | AU63: SUB-BLOCKER TRANSFER A5 | AV63: SUB-BLOCKER TRANSFER A5 LONG | AW63: SUB-BLOCKER TRANSFERA4 | AX63: SUB-BLOCKER TRANSFERA4 LONG | AY63: SUB-BLOCKER TRANSFERSQ | AZ63: SUB-BLOCKER TRANSFERA3 | BA63: NAME | BB63: SIZE
A64: ARRAY = TRANSFERQTY | B64: 5 | C64: 0 | D64: =D65*2 -> 7.317042 | E64: =E65*2 -> 7.9610061 | F64: =F65*2 -> 10.021691 | G64: =G65*2 -> 16.429134 | H64: =H65*2 -> 16.429134 | I64: =I65*2 -> 23.249471 | J64: =J65*2 -> 23.249471 | K64: =K65*2 -> 29.158789 | ... AZ64: =AZ65*2 -> 0
B65: 10 | C65: 0 | D65: 3.658521 | E65: 3.980503 | F65: 5.0108456 | G65: 8.2145669 | H65: 8.2145669 | I65: 11.624736 | J65: 11.624736 | K65: 14.579394 | L65: 20.981155 | M65: 0 | N65: 3.5979126 | O65: 3.8230295 | P65: 4.6320432 | Q65: 7.0942588 | R65: 7.0942588 | S65: 10.787582 | T65: 10.787582 | U65: 18.174229 | V65: 18.174229 | W65: 0 | X65: 6.3818681 | Y65: 7.2855678 | Z65: 7.9899267 | AA65: 10.637289 | AB65: 10.637289 | AC65: 12.571099 | AD65: 12.571099 | AE65: 15.954689 | AF65: 19.12967 | AG65: 0 | AH65: 7.3241026 | AI65: 8.4338095 | AJ65: 9.3089744 | AK65: 12.628095 | AL65: 12.628095 | AM65: 15.089524 | AN65: 15.089524 | AO65: 19.30641 | AP65: 23.304689 | AQ65: 0
B66: 20 | C66: 0 | D66: 3.4755949 | E66: 3.7814779 | F66: 4.7603033 | G66: 7.8038386 | H66: 7.8038386 | I66: 11.043499 | J66: 11.043499 | K66: 13.850425 | L66: 19.932097 | M66: 0 | N66: 3.418017 | O66: 3.631878 | P66: 4.400441 | Q66: 6.7395459 | R66: 6.7395459 | S66: 10.248203 | T66: 10.248203 | U66: 17.265518 | V66: 17.265518 | W66: 0 | X66: 5.7579121 | Y66: 6.5167399 | Z66: 7.0895604 | AA66: 9.3215751 | AB66: 9.3215751 | AC66: 10.891905 | AD66: 10.891905 | AE66: 13.700073 | AF66: 16.379304 | AG66: 0 | AH66: 6.5393407 | AI66: 7.465641 | AJ66: 8.1992674 | AK66: 10.978168 | AL66: 10.978168 | AM66: 12.992381 | AN66: 12.992381 | AO66: 16.501575 | AP66: 19.830696 | AQ66: 0
B67: 50 | C67: 0 | D67: 3.3018152 | E67: 3.592404 | F67: 4.5222881 | G67: 7.4136467 | H67: 7.4136467 | I67: 10.491324 | J67: 10.491324 | K67: 13.157903 | L67: 18.935492 | M67: 0 | N67: 3.2471161 | O67: 3.4502841 | P67: 4.180419 | Q67: 6.4025686 | R67: 6.4025686 | S67: 9.735793 | T67: 9.735793 | U67: 16.402242 | V67: 16.402242 | W67: 0 | X67: 4.6834066 | Y67: 5.3492308 | Z67: 6.6264103 | AA67: 8.1381319 | AB67: 8.1381319 | AC67: 9.8433333 | AD67: 9.8433333 | AE67: 12.349158 | AF67: 14.638974 | AG67: 0 | AH67: 5.1850916 | AI67: 6.0150549 | AJ67: 7.6331136 | AK67: 9.5116484 | AL67: 9.5116484 | AM67: 11.683333 | AN67: 11.683333 | AO67: 14.806447 | AP67: 17.65315 | AQ67: 0
B68: 100 | C68: 0 | D68: 3.1367244 | E68: 3.4127838 | F68: 4.2961737 | G68: 7.0429643 | H68: 7.0429643 | I68: 9.9667577 | J68: 9.9667577 | K68: 12.500008 | L68: 17.988718 | M68: 0 | N68: 3.0847603 | O68: 3.2777699 | P68: 3.971398 | Q68: 6.0824402 | R68: 6.0824402 | S68: 9.2490034 | T68: 9.2490034 | U68: 15.58213 | V68: 15.58213 | W68: 0 | X68: 4.3743956 | Y68: 5.0050183 | Z68: 5.8157143 | AA68: 6.6264103 | AB68: 6.6264103 | AC68: 7.7428571 | AD68: 7.7428571 | AE68: 9.540989 | AF68: 11.120513 | AG68: 0 | AH68: 4.7671429 | AI68: 5.5871062 | AJ68: 6.6004762 | AK68: 7.6331136 | AL68: 7.6331136 | AM68: 9.039304 | AN68: 9.039304 | AO68: 11.31652 | AP68: 13.275458 | AQ68: 0
B69: 250 | C69: 0 | D69: 2.9798882 | E69: 3.2421446 | F69: 4.081365 | G69: 6.6908161 | H69: 6.6908161 | I69: 9.4684198 | J69: 9.4684198 | K69: 11.875008 | L69: 17.089282 | M69: 0 | N69: 2.9305223 | O69: 3.1138814 | P69: 3.7728281 | Q69: 5.7783181 | R69: 5.7783181 | S69: 8.7865532 | T69: 8.7865532 | U69: 14.803023 | V69: 14.803023 | W69: 0 | X69: 4.1013187 | Y69: 4.6448718 | Z69: 5.5711722 | AA69: 6.1599267 | AB69: 6.1599267 | AC69: 6.9228938 | AD69: 6.9228938 | AE69: 8.4731502 | AF69: 9.8433333 | AG69: 0 | AH69: 4.4614652 | AI69: 5.1432234 | AJ69: 6.3173993 | AK69: 7.0284249 | AL69: 7.0284249 | AM69: 8.0326007 | AN69: 8.0326007 | AO69: 9.9622711 | AP69: 11.683333 | AQ69: 0
B70: 500 | C70: 0 | D70: 2.8308938 | E70: 3.0800374 | F70: 3.8772968 | G70: 6.3562753 | H70: 6.3562753 | I70: 8.9949988 | J70: 8.9949988 | K70: 11.281257 | L70: 16.234818 | M70: 0 | N70: 2.7839962 | O70: 2.9581873 | P70: 3.5841867 | Q70: 5.4894022 | R70: 5.4894022 | S70: 8.3472255 | T70: 8.3472255 | U70: 14.062872 | V70: 14.062872 | W70: 0 | X70: 3.8953114 | Y70: 4.4229304 | Z70: 5.3492308 | AA70: 5.8157143 | AB70: 5.8157143 | AC70: 6.697619 | AD70: 6.697619 | AE70: 8.1096703 | AF70: 9.3801832 | AG70: 0 | AH70: 4.200989 | AI70: 4.8508791 | AJ70: 6.0150549 | AK70: 6.6004762 | AL70: 6.6004762 | AM70: 7.7428571 | AN70: 7.7428571 | AO70: 9.5183883 | AP70: 11.094579 | AQ70: 0
B71: 750 | C71: 0 | D71: 2.6893491 | E71: 2.9260355 | F71: 3.683432 | G71: 6.0384615 | H71: 6.0384615 | I71: 8.5452489 | J71: 8.5452489 | K71: 10.717195 | L71: 15.423077 | M71: 0 | N71: 2.6447964 | O71: 2.810278 | P71: 3.4049774 | Q71: 5.2149321 | R71: 5.2149321 | S71: 7.9298643 | T71: 7.9298643 | U71: 13.359729 | V71: 13.359729 | W71: 0 | X71: 3.7923077 | Y71: 4.3039927 | Z71: 5.230293 | AA71: 5.6967766 | AB71: 5.6967766 | AC71: 6.4597436 | AD71: 6.4597436 | AE71: 7.7235897 | AF71: 9.0200366 | AG71: 0 | AH71: 4.0594505 | AI71: 4.7060073 | AJ71: 5.8768498 | AK71: 6.4589377 | AL71: 6.4589377 | AM71: 7.4664469 | AN71: 7.4664469 | AO71: 9.0200366 | AP71: 10.606227 | AQ71: 0
B72: SET UP | C72: 71.43 | D72: 71.43 | E72: 71.43 | F72: 71.43 | G72: 71.43 | H72: 71.43 | I72: 71.43 | J72: 71.43 | K72: 71.43 | L72: 71.43 | M72: 71.43 | N72: 71.43 | O72: 71.43 | P72: 71.43 | Q72: 71.43 | R72: 71.43 | S72: 71.43 | T72: 71.43 | U72: 71.43 | V72: 71.43 | W72: 71.43 | X72: 71.43 | Y72: 71.43 | Z72: 71.43 | AA72: 71.43 | AB72: 71.43 | AC72: 71.43 | AD72: 71.43 | AE72: 71.43 | AF72: 71.43 | AG72: 71.43 | AH72: 71.43 | AI72: 71.43 | AJ72: 71.43 | AK72: 71.43 | AL72: 71.43 | AM72: 71.43 | AN72: 71.43 | AO72: 71.43 | AP72: 71.43 | AQ72: 71.43 | AR72: 71.43 | AS72: 71.43 | AT72: 71.43 | AU72: 71.43 | AV72: 71.43 | AW72: 71.43 | AX72: 71.43 | AY72: 71.43 | AZ72: 71.43
B73: ARRAY= TRANSFERSETUP | C73: 35.72 | D73: 35.72 | E73: 35.72 | F73: 35.72 | G73: 35.72 | H73: 35.72 | I73: 35.72 | J73: 35.72 | K73: 35.72 | L73: 35.72 | M73: 35.72 | N73: 35.72 | O73: 35.72 | P73: 35.72 | Q73: 35.72 | R73: 35.72 | S73: 35.72 | T73: 35.72 | U73: 35.72 | V73: 35.72 | W73: 35.72 | X73: 35.72 | Y73: 35.72 | Z73: 35.72 | AA73: 35.72 | AB73: 35.72 | AC73: 35.72 | AD73: 35.72 | AE73: 35.72 | AF73: 35.72 | AG73: 35.72 | AH73: 35.72 | AI73: 35.72 | AJ73: 35.72 | AK73: 35.72 | AL73: 35.72 | AM73: 35.72 | AN73: 35.72 | AO73: 35.72 | AP73: 35.72 | AQ73: 35.72 | AR73: 35.72 | AS73: 35.72 | AT73: 35.72 | AU73: 35.72 | AV73: 35.72 | AW73: 35.72 | AX73: 35.72 | AY73: 35.72 | AZ73: 35.72
A75: ARRAY = VINYLCOST
A76: ARRAY= VINYLSIZE | C76: A7 | D76: A6 | E76: A5 | F76: A5 LONG | G76: A4 | H76: A4 LONG | I76: SQ | J76: A3- 300x420mm | K76: N/A | P76: NAME | Q76: SIZE | AB76: <35MM HIGH | AC76: 36-60MM HIGH
A77: ARRAY = VINYLQTY | B77: Cotton Vinyl | C77: 6.9115385 | D77: 11.515385 | E77: 20.723077 | F77: 20.723077 | G77: 39.138462 | H77: 39.138462 | I77: 35.7 | J77: 75.969231 | K77: 0 | P77: COTTON | Q77: N/A | R77: =P77&Q77 -> COTTONN/A | S77: =P77&Q78 -> COTTONA7- 105x75mm | T77: =P77&Q79 -> COTTONA6- 150x105mm | U77: =P77&Q80 -> COTTONA5- 210x150mm | V77: =P77&Q81 -> COTTONA4- 210x300mm | AA77: N/A | AB77: 0 | AC77: 0
B78: Polyester | C78: 7.3961538 | D78: 12.484615 | E78: 22.661538 | F78: 22.661538 | G78: 43.015385 | H78: 43.015385 | I78: 39.3 | J78: 83.723077 | K78: 0 | P78: POLYESTER | Q78: A7- 105x75mm | AA78: SINGLE NAMES | AB78: 7 | AC78: 10
B79: Sub Blocker | C79: 7.8807692 | D79: 13.453846 | E79: 24.6 | F79: 24.6 | G79: 46.892308 | H79: 46.892308 | I79: 42.9 | J79: 91.476923 | K79: 0 | P79: SUB-BLOCKER | Q79: A6- 150x105mm | AA79: DOUBLE NAMES | AB79: 10 | AC79: 15
B80: Metallic | C80: 8.1230769 | D80: 13.938462 | E80: 25.569231 | F80: 25.569231 | G80: 48.830769 | H80: 48.830769 | I80: 44.7 | J80: 95.353846 | K80: 0 | P80: METALLIC | Q80: A5- 210x150mm | AA80: INITIALS | AB80: 5 | AC80: 7
B81: Stretch Sports | C81: 8.1230769 | D81: 13.938462 | E81: 25.569231 | F81: 25.569231 | G81: 48.830769 | H81: 48.830769 | I81: 44.7 | J81: 95.353846 | K81: 0 | P81: STRETCH SPORTS | Q81: A4- 210x300mm
B82: Nylon | C82: 8.1230769 | D82: 13.938462 | E82: 25.569231 | F82: 25.569231 | G82: 48.830769 | H82: 48.830769 | I82: 44.7 | J82: 95.353846 | K82: 0 | P82: NYLON | Q82: A3- 300x420mm | AB82: 10CM | AC82: 15CM | AD82: 20CM | AE82: 25CM
B83: Reflective | C83: 8.85 | D83: 15.392308 | E83: 28.476923 | F83: 28.476923 | G83: 54.646154 | H83: 54.646154 | I83: 50.1 | J83: 106.98462 | K83: 0 | P83: REFLECTIVE | AA83: N/A
B84: Brick | C84: 8.85 | D84: 15.392308 | E84: 28.476923 | F84: 28.476923 | G84: 54.646154 | H84: 54.646154 | I84: 50.1 | J84: 106.98462 | K84: 0 | P84: BRICK | AA84: SINGLE NUMBERS | AB84: 5 | AC84: 7 | AD84: 9 | AE84: 11
B85: Foil | C85: 8.85 | D85: 15.392308 | E85: 28.476923 | F85: 28.476923 | G85: 54.646154 | H85: 54.646154 | I85: 50.1 | J85: 106.98462 | K85: 0 | P85: FOIL | AA85: DOUBLE NUMBERS | AB85: 8 | AC85: 10 | AD85: 12 | AE85: 14
Y86: TRIPLE NUMBERS | Z86: 11 | AA86: 13 | AB86: 15 | AC86: 17
B88: SET UP
B89: ARRAY= VINYLSETUP
B90: ARRAY= TRANSFERSETUP
C91: WOODEN BOX
A92: PRINT - OTHER | C92: A6- | D92: A5- | E92: A4- | F92: A3-
B93: 1
B94: 5
B95: 10
B96: 15
B97: 25
B98: 50
B99: 75
B100: 100
B101: 250
B102: 500
B103: 750
B104: 1000
... B108: 10000
A110: UMBRELLAS & WOODEN BOXES | L110: WOODEN BOXES
C111: 1 COLOUR | D111: 2 COLOURS | E111: 3 COLOURS | F111: 4 COLOURS | G111: 5 COLOURS | H111: 6 COLOURS | I111: HANDLING | J111: LASER ETCH HANDLE | L111: A61 COLOUR | M111: A62 COLOURS | N111: A63 COLOURS | O111: A51 COLOUR | P111: A52 COLOURS | Q111: A53 COLOLOURS | R111: A4 1 COLOUR | S111: A4 2 COLOURS | T111: A43 COLOURS | U111: A31 COLOUR | V111: A32 COLOURS | W111: A33 COLOURS
A112: PRINT PRICE | B112: 1 | C112: 15.38 | D112: 23.08 | E112: 30.769231 | F112: 38.461538 | G112: 46.153846 | H112: 53.846154 | I112: 3.8461538 | J112: 7.6923077 | L112: 39.244874 | M112: =L112*2 -> 78.489748 | N112: =L112*3 -> 117.73462 | O112: 43.605415 | P112: =O112*2 -> 87.210831 | Q112: =O112*3 -> 130.81625 | R112: 65.408123 | S112: =R112*2 -> 130.81625 | T112: =R112*3 -> 196.22437 | U112: 98.112185 | V112: =U112*2 -> 196.22437 | W112: =U112*3 -> 294.33655
B113: 5 | C113: 8.46 | D113: 14.62 | E113: 20.769231 | F113: 26.923077 | G113: 33.076923 | H113: 39.230769 | I113: 3.0769231 | J113: 6.1346154 | L113: 21.802708 | M113: =L113*2 -> 43.605415 | N113: =L113*3 -> 65.408123 | O113: 24.225231 | P113: =O113*2 -> 48.450462 | Q113: =O113*3 -> 72.675692 | R113: 36.337846 | S113: =R113*2 -> 72.675692 | T113: =R113*3 -> 109.01354 | U113: 54.506769 | V113: =U113*2 -> 109.01354 | W113: =U113*3 -> 163.52031
...

Sheet READ THIS FIRST
B1: Colour Evolution Ltd 25 Exmouth St, Eden Terrace Auckland 1021 Ph 09-300-7478 Email: orders@colourevolution.co.nz | L1: Colour Evolution Ltd/ANB 8b Trugood Drive East Tamaki Auckland 2013 Ph 09 265 1750 Email: sales@colourevolution.co.nz Website: anythingneedingbranding.co.nz
B2: Please be aware that pricing given here is indicative only and subject to confirmation by Colour Evolution, some rounding will occur due to discount format.
B3: Your Colour Evolution Discount rate is: | F3: 0.35 | L3: UNLOCK PROTECTION PASSWORD - COLOUR
B4: THE QUOTE PROCESS | L4: HELP US TO HELP YOU!!!
B5: If you are unable to find the information you need here or if your order is complex just contact us with the following information and we can assist with a quote; For Screenprint - How many prints/garments is there? What size are the prints and what placement What style code or colour and fabric are the garments - do you want us to quote to supply them or will you supply them What colour(s) is the print? Are there colour changes? Attach the best image you have avaiable of the artwork, ideally vectored pdf if you can. The better the quality the better we easier it is for us to determine the number of colours required etc. For Embroidery - How many items? Send an image of the design, advise a size for the embroidery and what type of garment the design is going on. For Laser - How many items? Send an image ofthe design, advise a size for the Laser etch and advise what type of garment/item Now email everything in one email please. We will come back to you if we have any further questions, otherwise you should recieve a quote within 4-6 hours. Once your have decided to proceed with the order, just email us to Proceed or Go Ahead! (That's great! or Perfect! is NOT APPROVAL TO PROCEED and we will not action anything) | L5: Ok so here is where we need your help the most! We receive a large number of orders and quote requests daily via email, and often they will include the subject line - "New print job", "Order", "For Embroidery" etc...., this is a sure way to ensure your email disappears into the abyss when we are trying to retrieve or check information from previous communications. Please, please, please, use a subject line that relates to your order ie: MAXWELL JONES PRINT ORDER or SOUTHERN RIDERS embroidery. ALL THE INFORMATION: We spend a lot of time going back to ask customers for PMS Colours! Print Sizes! Delivery Addresses! All of this time causes DELAYS to our processes, and not just a delay to your order but to ALL orders as it slows everything we need to do. It is imposible for us to schedule an order for "a box of tees" and "some hoodies & jackets", your order will not be scheduled until we have all the information. Also ensure we have the correct details for invocing the correct entity and the appropriate email address for invoices and statements. Ensure we know this BEFORE we process your order not after we have already invoiced the order. As much as is possible, send all information in ONE email. READ OUR CONFIRMATION NOTICES!!! Once your order is in the system we will send you a Sales Order Confirmation, on this document it will advise an estimated despatch date. Please READ the information contained here. Please do not reply to this email asking when your order will be ready! If you have not received a confirmation notice within 48 hours something could be wrong, please contact us to check that your order is in process. SENDING STOCK TO US We receive stock all day every day, from a lot of suppliers and from a lot of customers. If we receive your garments BEFORE we have your order in our system then we have nothing to allocate the stock to. The items will sit on our shelf of unallocated stock until such time as the goods are matched up with an order. This can mean a delay in the process as our support staff are busily allocating stock to orders that are prepared in the system. It also means we are spending time checking and rechecking for orders to come in. Please do not send stock to us until all the order details are confirmed and you are ready to place your order with us. I know you are in a hurry to get started and think we need the garments straight away but we need your order details first, the garments second. As long as the garments arrive within 3-4 days of our scheduled despatch date it will not cause delay to your order. However, if we have NOT received your garments within 4 days of the due date the order will be put on HOLD until the stock has arrived and then rescheduled for production once the stock arrives. Please ensure there is a valid reference job name or order number on the documentation that relates to your order. We have thousands of boxes and satchels coming in and out every month and "playing guess the parcel" is not as much fun as you might think! It means our stock receivers need to pull our office staff away from processing orders to help identify the mystery parcel. ORDER STOCK THROUGH US: If you have access to the supplier stock records, please check availability before placing an order with us, inwards freight costs will be on charged if charged by the supplier.
B6: THE ORDER PROCESS
B7: Once you have your order ready for us, please check the information below has been included, then send to orders@colourevolution.co.nz or sales@colourevolution.co.nz. IF YOU HAVE BEEN QUOTED PRICING , PLEASE ADVISE THE QUOTE NUMBER ON YOUR ORDER!! PMS(Pantone Solid Coated) or Thread colours, Print or Embroidery sizing, Artwork in correct format, vectored pdf for screenprint and laser. If this is a repeat job please ensure this is clearly stated and provide an image of the artwork or a copy of previous invoice so we can check we have the correct details. Garment details and sizes if we are supplying Delivery address, or confirm if you will pick up, and if the delivery date is CRITICAL it is essential that this is highlighted on confirmation of your order, even if you have previously discussed it! If we have received all the required information and are able to proceed with your order we will schedule your job and send you a Sales Order Confirmation advising you of an "Estimated Due date" this is the date we ESTIMATE for despatch. It is not a guaranteed date, if you have a CRITICAL DATE order then that should have been advised to us well PRIOR to this point. If you are supplying the blank stock for yourorder, we MUST receive ALL of the stock at least three (3) full days prior to the due date. If the stock has not arrived in time yourorder will be rescheduled. If the stock has still not arrived three days prior to the rescheduled date the job will be put on HOLD and will be rescheduled once all stock has been received. Once your order is completed and despatch (or ready for collection) we will issue an invoice. This invoice is your advice that the order has either been despatched via courier or is ready to collect. If your order is being sent via courier then you will also receive a notification email from the Courier service advising they have your order onboard. Please refer to this email for tracking details.

Sheet PRINT APPAREL
B1: Your Colour Evolution Discount Rate is set at | F1: ='READ THIS FIRST'!F3 -> 0.35 | G1: Your required margin rate is set at (%) (To change your margin go to Trade Customer Set up Page) | J1: ='READ THIS FIRST'!J3 -> 0 | K1: =(100-J1)/100 -> 1 | L1: DO NOT ADJUST SETTINGS HERE - REFER TO "TRADE CUSTOMER" SHEET
B2: Green fields contain drop down lists, click on the field and then on the arrow to view drop down options
B3: Editable fields are Bright Green
B5: SCREENPRINT- APPAREL - QUICK PRICE
B6: SELECT | C6: Step 1-Enter Order Quantity > | E6: 20 | F6: Step 2 - Select Print Style Hover Mouse over to see options > | I6: STANDARD | N6: Step 3 -Print Sizes: A6 - Anything up to a maximum size of 100mm x 100mm A5 - Fits within 150mm x 210mm OR 105mm x 300mm A4 -Fits within 210mm x 300mm OR 150mm x 450mm A3 - Larger than A4 up to a maximum size of 300mm x 450mm A2 - Larger than A3 up to a maximum size of 450mm x 690mm SCROLL DOWN TO SEE TEMPLATE IMAGES | P6: Step 4 -Number of Colours: Select the number of colours for printing. Note that Fluro, Metallic or Puff finishes will incur additional cost. Please contact our office for a quote. | R6: Step 5 -Set up: All new designs will incur a film and screenmaking cost (Set up cost). Repeat prints will incur a "Reset" fee. | T6: Step 6 -Underbase: An underbase will be required on most dark colours items if printing a lighter ink colour ie printing pink or yellow on black.
F7: Location 1 | G7: Location 2 | H7: Location 3 | I7: Location 4 | J7: Location 5 | K7: Location 6
C8: Enter Placement area or Design Name >
C9: Step 3 - Select Print Size > | F9: A4 | G9: A4 | H9: A4 | I9: A3 | J9: A2 | K9: N/A
C10: Step 4 - Select # of Colours > | F10: 1 COLOUR | G10: 2 COLOURS | H10: 1 COLOUR | I10: 1 COLOUR | J10: 1 COLOUR | K10: 6 COLOURS
C11: Step 5 - Set up - Is this a New Design or Reset(All repeats) | F11: NEW DESIGN | G11: NEW DESIGN | H11: NEW DESIGN | I11: NEW DESIGN | J11: NEW DESIGN | K11: NEW DESIGN
C12: Step 6 - Will an underbase screen be required? - if REPEAT job set to NO | F12: NO | G12: NO | H12: NO | I12: NO | J12: NO | K12: NO
B13: HIDDEN ROW | F13: =F9&F7 -> A4Location 1 | G13: =G9&G7 -> A4Location 2 | H13: =H9&H7 -> A4Location 3 | I13: =I9&I7 -> A3Location 4 | J13: =J9&J7 -> A2Location 5 | K13: =K9&K7 -> N/ALocation 6
B14: HIDDEN ROW | F14: =F9&F10&$I$6 -> A41 COLOURSTANDARD | G14: =G9&G10&$I$6 -> A42 COLOURSSTANDARD | H14: =H9&H10&$I$6 -> A41 COLOURSTANDARD | I14: =I9&I10&$I$6 -> A31 COLOURSTANDARD | J14: =J9&J10&$I$6 -> A21 COLOURSTANDARD | K14: =K9&K10&$I$6 -> N/A6 COLOURSSTANDARD
B15: HIDDEN ROW | C15: Standard Set up Cost | F15: =INDEX(SCREENCOST,MATCH(F11,PRINTSCREEN,0),MATCH(F14,PRINTCOLOURS,0)) -> 46.4295 | G15: =INDEX(SCREENCOST,MATCH(G11,PRINTSCREEN,0),MATCH(G14,PRINTCOLOURS,0)) -> 92.859 | H15: =INDEX(SCREENCOST,MATCH(H11,PRINTSCREEN,0),MATCH(H14,PRINTCOLOURS,0)) -> 46.4295 | I15: =INDEX(SCREENCOST,MATCH(I11,PRINTSCREEN,0),MATCH(I14,PRINTCOLOURS,0)) -> 60.359 | J15: =INDEX(SCREENCOST,MATCH(J11,PRINTSCREEN,0),MATCH(J14,PRINTCOLOURS,0)) -> 83.5705 | K15: =INDEX(SCREENCOST,MATCH(K11,PRINTSCREEN,0),MATCH(K14,PRINTCOLOURS,0)) -> 0
B16: HIDDEN ROW | C16: Underbase Cost | F16: =INDEX(UNDERBASE,MATCH(F12,ADDSCREEB,0),MATCH(F9,SCREENSIZE,0)) -> 0 | G16: =INDEX(UNDERBASE,MATCH(G12,ADDSCREEB,0),MATCH(G9,SCREENSIZE,0)) -> 0 | H16: =INDEX(UNDERBASE,MATCH(H12,ADDSCREEB,0),MATCH(H9,SCREENSIZE,0)) -> 0 | I16: =INDEX(UNDERBASE,MATCH(I12,ADDSCREEB,0),MATCH(I9,SCREENSIZE,0)) -> 0 | J16: =INDEX(UNDERBASE,MATCH(J12,ADDSCREEB,0),MATCH(J9,SCREENSIZE,0)) -> 0 | K16: =INDEX(UNDERBASE,MATCH(K12,ADDSCREEB,0),MATCH(K9,SCREENSIZE,0)) -> 0
C17: Unit COST EXCLUDING Set Up | F17: =INDEX(BREAKDOWNTABLE,MATCH($C17,BREAKDOWN,0),MATCH(F$55,BREAKCOLOURS,0)) -> 6.177723 | G17: =INDEX(BREAKDOWNTABLE,MATCH($C17,BREAKDOWN,0),MATCH(G$55,BREAKCOLOURS,0)) -> 7.9157788 | H17: =INDEX(BREAKDOWNTABLE,MATCH($C17,BREAKDOWN,0),MATCH(H$55,BREAKCOLOURS,0)) -> 6.177723 | I17: =INDEX(BREAKDOWNTABLE,MATCH($C17,BREAKDOWN,0),MATCH(I$55,BREAKCOLOURS,0)) -> 8.5992249 | J17: =INDEX(BREAKDOWNTABLE,MATCH($C17,BREAKDOWN,0),MATCH(J$55,BREAKCOLOURS,0)) -> 13.901948 | K17: =INDEX(BREAKDOWNTABLE,MATCH($C17,BREAKDOWN,0),MATCH(K$55,BREAKCOLOURS,0)) -> 0
C18: Total Set up (film & Screen) Costs | F18: =INDEX(BREAKDOWNTABLE,MATCH($C18,BREAKDOWN,0),MATCH(F$55,BREAKCOLOURS,0)) -> 46.4295 | G18: =INDEX(BREAKDOWNTABLE,MATCH($C18,BREAKDOWN,0),MATCH(G$55,BREAKCOLOURS,0)) -> 92.859 | H18: =INDEX(BREAKDOWNTABLE,MATCH($C18,BREAKDOWN,0),MATCH(H$55,BREAKCOLOURS,0)) -> 46.4295 | I18: =INDEX(BREAKDOWNTABLE,MATCH($C18,BREAKDOWN,0),MATCH(I$55,BREAKCOLOURS,0)) -> 60.359 | J18: =INDEX(BREAKDOWNTABLE,MATCH($C18,BREAKDOWN,0),MATCH(J$55,BREAKCOLOURS,0)) -> 83.5705 | K18: =INDEX(BREAKDOWNTABLE,MATCH($C18,BREAKDOWN,0),MATCH(K$55,BREAKCOLOURS,0)) -> 0
B19: Unit COST Including Set up | F19: =INDEX(BREAKDOWNTABLE,MATCH($B19,BREAKDOWN,0),MATCH(F$55,BREAKCOLOURS,0)) -> 8.499198 | G19: =INDEX(BREAKDOWNTABLE,MATCH($B19,BREAKDOWN,0),MATCH(G$55,BREAKCOLOURS,0)) -> 12.558729 | H19: =INDEX(BREAKDOWNTABLE,MATCH($B19,BREAKDOWN,0),MATCH(H$55,BREAKCOLOURS,0)) -> 8.499198 | I19: =INDEX(BREAKDOWNTABLE,MATCH($B19,BREAKDOWN,0),MATCH(I$55,BREAKCOLOURS,0)) -> 11.617175 | J19: =INDEX(BREAKDOWNTABLE,MATCH($B19,BREAKDOWN,0),MATCH(J$55,BREAKCOLOURS,0)) -> 18.080473 | K19: =INDEX(BREAKDOWNTABLE,MATCH($B19,BREAKDOWN,0),MATCH(K$55,BREAKCOLOURS,0)) -> 0 | L19: =SUM(F19:K19) -> 59.254773 | M19: TOTAL UNIT COST | N19: Pricing is indicative only and subject to confirmation by Colour Evolution Ltd, some rounding may occur.
B20: Total Cost Including Set Up | F20: =INDEX(BREAKDOWNTABLE,MATCH($B20,BREAKDOWN,0),MATCH(F$55,BREAKCOLOURS,0)) -> 169.98396 | G20: =INDEX(BREAKDOWNTABLE,MATCH($B20,BREAKDOWN,0),MATCH(G$55,BREAKCOLOURS,0)) -> 251.17458 | H20: =INDEX(BREAKDOWNTABLE,MATCH($B20,BREAKDOWN,0),MATCH(H$55,BREAKCOLOURS,0)) -> 169.98396 | I20: =INDEX(BREAKDOWNTABLE,MATCH($B20,BREAKDOWN,0),MATCH(I$55,BREAKCOLOURS,0)) -> 232.3435 | J20: =INDEX(BREAKDOWNTABLE,MATCH($B20,BREAKDOWN,0),MATCH(J$55,BREAKCOLOURS,0)) -> 361.60946 | K20: =INDEX(BREAKDOWNTABLE,MATCH($B20,BREAKDOWN,0),MATCH(K$55,BREAKCOLOURS,0)) -> 0 | L20: =SUM(F20:K20) -> 1185.0955 | M20: TOTAL COST
B21: ALL PRICING IS EXCLUDING GST AND SUBJECT TO CONFIRMATION BY COLOUR EVOLUTION
C23: SCREENPRINT APPAREL - PRICE BREAK COMPARISON
E24: Select # of Colours > | G24: 2 COLOURS | H24: Select Style of Print > | I24: STANDARD | J24: Set up > | K24: NEW DESIGN | L24: If you do not want to include set up - set to NO SET UP | N24: Below are our standard quantity breaks, you may edit these to suit
B25: HIDDEN | D25: =INDEX(SCREENCOST,MATCH($K$24,PRINTSCREEN,0),MATCH($T31,PRINTCOLOURS,0)) -> 92.859 | E25: =INDEX(SCREENCOST,MATCH($K$24,PRINTSCREEN,0),MATCH($T31,PRINTCOLOURS,0)) -> 92.859 | F25: =INDEX(SCREENCOST,MATCH($K$24,PRINTSCREEN,0),MATCH($T31,PRINTCOLOURS,0)) -> 92.859 | G25: =INDEX(SCREENCOST,MATCH($K$24,PRINTSCREEN,0),MATCH($T31,PRINTCOLOURS,0)) -> 92.859 | H25: =INDEX(SCREENCOST,MATCH($K$24,PRINTSCREEN,0),MATCH($T31,PRINTCOLOURS,0)) -> 92.859 | I25: =INDEX(SCREENCOST,MATCH($K$24,PRINTSCREEN,0),MATCH($T31,PRINTCOLOURS,0)) -> 92.859 | J25: =INDEX(SCREENCOST,MATCH($K$24,PRINTSCREEN,0),MATCH($T31,PRINTCOLOURS,0)) -> 92.859 | K25: =INDEX(SCREENCOST,MATCH($K$24,PRINTSCREEN,0),MATCH($T31,PRINTCOLOURS,0)) -> 92.859 | ... S25: =INDEX(SCREENCOST,MATCH($K$24,PRINTSCREEN,0),MATCH($T31,PRINTCOLOURS,0)) -> 92.859
B26: HIDDEN | D26: =INDEX(SCREENCOST,MATCH($K$24,PRINTSCREEN,0),MATCH($T32,PRINTCOLOURS,0)) -> 74.282 | E26: =INDEX(SCREENCOST,MATCH($K$24,PRINTSCREEN,0),MATCH($T32,PRINTCOLOURS,0)) -> 74.282 | F26: =INDEX(SCREENCOST,MATCH($K$24,PRINTSCREEN,0),MATCH($T32,PRINTCOLOURS,0)) -> 74.282 | G26: =INDEX(SCREENCOST,MATCH($K$24,PRINTSCREEN,0),MATCH($T32,PRINTCOLOURS,0)) -> 74.282 | H26: =INDEX(SCREENCOST,MATCH($K$24,PRINTSCREEN,0),MATCH($T32,PRINTCOLOURS,0)) -> 74.282 | I26: =INDEX(SCREENCOST,MATCH($K$24,PRINTSCREEN,0),MATCH($T32,PRINTCOLOURS,0)) -> 74.282 | J26: =INDEX(SCREENCOST,MATCH($K$24,PRINTSCREEN,0),MATCH($T32,PRINTCOLOURS,0)) -> 74.282 | K26: =INDEX(SCREENCOST,MATCH($K$24,PRINTSCREEN,0),MATCH($T32,PRINTCOLOURS,0)) -> 74.282 | ... S26: =INDEX(SCREENCOST,MATCH($K$24,PRINTSCREEN,0),MATCH($T32,PRINTCOLOURS,0)) -> 74.282
B27: HIDDEN | D27: =INDEX(SCREENCOST,MATCH($K$24,PRINTSCREEN,0),MATCH($T33,PRINTCOLOURS,0)) -> 55.718 | E27: =INDEX(SCREENCOST,MATCH($K$24,PRINTSCREEN,0),MATCH($T33,PRINTCOLOURS,0)) -> 55.718 | F27: =INDEX(SCREENCOST,MATCH($K$24,PRINTSCREEN,0),MATCH($T33,PRINTCOLOURS,0)) -> 55.718 | G27: =INDEX(SCREENCOST,MATCH($K$24,PRINTSCREEN,0),MATCH($T33,PRINTCOLOURS,0)) -> 55.718 | H27: =INDEX(SCREENCOST,MATCH($K$24,PRINTSCREEN,0),MATCH($T33,PRINTCOLOURS,0)) -> 55.718 | I27: =INDEX(SCREENCOST,MATCH($K$24,PRINTSCREEN,0),MATCH($T33,PRINTCOLOURS,0)) -> 55.718 | J27: =INDEX(SCREENCOST,MATCH($K$24,PRINTSCREEN,0),MATCH($T33,PRINTCOLOURS,0)) -> 55.718 | K27: =INDEX(SCREENCOST,MATCH($K$24,PRINTSCREEN,0),MATCH($T33,PRINTCOLOURS,0)) -> 55.718 | ... S27: =INDEX(SCREENCOST,MATCH($K$24,PRINTSCREEN,0),MATCH($T33,PRINTCOLOURS,0)) -> 55.718
B28: HIDDEN | D28: =INDEX(SCREENCOST,MATCH($K$24,PRINTSCREEN,0),MATCH($T34,PRINTCOLOURS,0)) -> 120.718 | E28: =INDEX(SCREENCOST,MATCH($K$24,PRINTSCREEN,0),MATCH($T34,PRINTCOLOURS,0)) -> 120.718 | F28: =INDEX(SCREENCOST,MATCH($K$24,PRINTSCREEN,0),MATCH($T34,PRINTCOLOURS,0)) -> 120.718 | G28: =INDEX(SCREENCOST,MATCH($K$24,PRINTSCREEN,0),MATCH($T34,PRINTCOLOURS,0)) -> 120.718 | H28: =INDEX(SCREENCOST,MATCH($K$24,PRINTSCREEN,0),MATCH($T34,PRINTCOLOURS,0)) -> 120.718 | I28: =INDEX(SCREENCOST,MATCH($K$24,PRINTSCREEN,0),MATCH($T34,PRINTCOLOURS,0)) -> 120.718 | J28: =INDEX(SCREENCOST,MATCH($K$24,PRINTSCREEN,0),MATCH($T34,PRINTCOLOURS,0)) -> 120.718 | K28: =INDEX(SCREENCOST,MATCH($K$24,PRINTSCREEN,0),MATCH($T34,PRINTCOLOURS,0)) -> 120.718 | ... S28: =INDEX(SCREENCOST,MATCH($K$24,PRINTSCREEN,0),MATCH($T34,PRINTCOLOURS,0)) -> 120.718
B29: HIDDEN | D29: =INDEX(SCREENCOST,MATCH($K$24,PRINTSCREEN,0),MATCH($T35,PRINTCOLOURS,0)) -> 167.141 | E29: =INDEX(SCREENCOST,MATCH($K$24,PRINTSCREEN,0),MATCH($T35,PRINTCOLOURS,0)) -> 167.141 | F29: =INDEX(SCREENCOST,MATCH($K$24,PRINTSCREEN,0),MATCH($T35,PRINTCOLOURS,0)) -> 167.141 | G29: =INDEX(SCREENCOST,MATCH($K$24,PRINTSCREEN,0),MATCH($T35,PRINTCOLOURS,0)) -> 167.141 | H29: =INDEX(SCREENCOST,MATCH($K$24,PRINTSCREEN,0),MATCH($T35,PRINTCOLOURS,0)) -> 167.141 | I29: =INDEX(SCREENCOST,MATCH($K$24,PRINTSCREEN,0),MATCH($T35,PRINTCOLOURS,0)) -> 167.141 | J29: =INDEX(SCREENCOST,MATCH($K$24,PRINTSCREEN,0),MATCH($T35,PRINTCOLOURS,0)) -> 167.141 | K29: =INDEX(SCREENCOST,MATCH($K$24,PRINTSCREEN,0),MATCH($T35,PRINTCOLOURS,0)) -> 167.141 | ... S29: =INDEX(SCREENCOST,MATCH($K$24,PRINTSCREEN,0),MATCH($T35,PRINTCOLOURS,0)) -> 167.141
D30: 1 | E30: 5 | F30: 10 | G30: 15 | H30: 20 | I30: 25 | J30: 50 | K30: 75 | L30: 100 | M30: 250 | N30: 750 | O30: 1000 | P30: 2500 | Q30: 5000 | R30: 7500 | S30: 10000
C31: A4 | D31: =(INDEX(PRINTPRICE,MATCH(D$30,PRINTQTY,1),MATCH($T31,PRINTCOLOURS,0)))+(D25/D$30) -> 144.27291 | E31: =(INDEX(PRINTPRICE,MATCH(E$30,PRINTQTY,1),MATCH($T31,PRINTCOLOURS,0)))+(E25/E$30) -> 40.064046 | F31: =(INDEX(PRINTPRICE,MATCH(F$30,PRINTQTY,1),MATCH($T31,PRINTCOLOURS,0)))+(F25/F$30) -> 21.513377 | G31: =(INDEX(PRINTPRICE,MATCH(G$30,PRINTQTY,1),MATCH($T31,PRINTCOLOURS,0)))+(G25/G$30) -> 14.106379 | H31: =(INDEX(PRINTPRICE,MATCH(H$30,PRINTQTY,1),MATCH($T31,PRINTCOLOURS,0)))+(H25/H$30) -> 12.558729 | I31: =(INDEX(PRINTPRICE,MATCH(I$30,PRINTQTY,1),MATCH($T31,PRINTCOLOURS,0)))+(I25/I$30) -> 8.9821232 | J31: =(INDEX(PRINTPRICE,MATCH(J$30,PRINTQTY,1),MATCH($T31,PRINTCOLOURS,0)))+(J25/J$30) -> 5.8270098 | K31: =(INDEX(PRINTPRICE,MATCH(K$30,PRINTQTY,1),MATCH($T31,PRINTCOLOURS,0)))+(K25/K$30) -> 4.6023873 | ... S31: =(INDEX(PRINTPRICE,MATCH(S$30,PRINTQTY,1),MATCH($T31,PRINTCOLOURS,0)))+(S25/S$30) -> 1.6322304 | T31: =C31&$G$24&$I$24 -> A42 COLOURSSTANDARD
C32: A5 | D32: =(INDEX(PRINTPRICE,MATCH(D$30,PRINTQTY,1),MATCH($T32,PRINTCOLOURS,0)))+(D26/D$30) -> 120.5592 | E32: =(INDEX(PRINTPRICE,MATCH(E$30,PRINTQTY,1),MATCH($T32,PRINTCOLOURS,0)))+(E26/E$30) -> 33.56517 | F32: =(INDEX(PRINTPRICE,MATCH(F$30,PRINTQTY,1),MATCH($T32,PRINTCOLOURS,0)))+(F26/F$30) -> 18.568476 | G32: =(INDEX(PRINTPRICE,MATCH(G$30,PRINTQTY,1),MATCH($T32,PRINTCOLOURS,0)))+(G26/G$30) -> 12.257376 | H32: =(INDEX(PRINTPRICE,MATCH(H$30,PRINTQTY,1),MATCH($T32,PRINTCOLOURS,0)))+(H26/H$30) -> 11.019342 | I32: =(INDEX(PRINTPRICE,MATCH(I$30,PRINTQTY,1),MATCH($T32,PRINTCOLOURS,0)))+(I26/I$30) -> 7.8269 | J32: =(INDEX(PRINTPRICE,MATCH(J$30,PRINTQTY,1),MATCH($T32,PRINTCOLOURS,0)))+(J26/J$30) -> 5.1997917 | K32: =(INDEX(PRINTPRICE,MATCH(K$30,PRINTQTY,1),MATCH($T32,PRINTCOLOURS,0)))+(K26/K$30) -> 4.1436742 | ... S32: =(INDEX(PRINTPRICE,MATCH(S$30,PRINTQTY,1),MATCH($T32,PRINTCOLOURS,0)))+(S26/S$30) -> 1.5075885 | T32: =C32&$G$24&$I$24 -> A52 COLOURSSTANDARD
C33: A6 | D33: =(INDEX(PRINTPRICE,MATCH(D$30,PRINTQTY,1),MATCH($T33,PRINTCOLOURS,0)))+(D27/D$30) -> 101.24851 | E33: =(INDEX(PRINTPRICE,MATCH(E$30,PRINTQTY,1),MATCH($T33,PRINTCOLOURS,0)))+(E27/E$30) -> 29.363191 | F33: =(INDEX(PRINTPRICE,MATCH(F$30,PRINTQTY,1),MATCH($T33,PRINTCOLOURS,0)))+(F27/F$30) -> 16.530506 | G33: =(INDEX(PRINTPRICE,MATCH(G$30,PRINTQTY,1),MATCH($T33,PRINTCOLOURS,0)))+(G27/G$30) -> 10.892948 | H33: =(INDEX(PRINTPRICE,MATCH(H$30,PRINTQTY,1),MATCH($T33,PRINTCOLOURS,0)))+(H27/H$30) -> 9.9643152 | I33: =(INDEX(PRINTPRICE,MATCH(I$30,PRINTQTY,1),MATCH($T33,PRINTCOLOURS,0)))+(I27/I$30) -> 6.9633782 | J33: =(INDEX(PRINTPRICE,MATCH(J$30,PRINTQTY,1),MATCH($T33,PRINTCOLOURS,0)))+(J27/J$30) -> 4.7312234 | K33: =(INDEX(PRINTPRICE,MATCH(K$30,PRINTQTY,1),MATCH($T33,PRINTCOLOURS,0)))+(K27/K$30) -> 3.8027205 | ... S33: =(INDEX(PRINTPRICE,MATCH(S$30,PRINTQTY,1),MATCH($T33,PRINTCOLOURS,0)))+(S27/S$30) -> 1.4396176 | T33: =C33&$G$24&$I$24 -> A62 COLOURSSTANDARD
C34: A3 | D34: =(INDEX(PRINTPRICE,MATCH(D$30,PRINTQTY,1),MATCH($T34,PRINTCOLOURS,0)))+(D28/D$30) -> 183.61385 | E34: =(INDEX(PRINTPRICE,MATCH(E$30,PRINTQTY,1),MATCH($T34,PRINTCOLOURS,0)))+(E28/E$30) -> 56.376156 | F34: =(INDEX(PRINTPRICE,MATCH(F$30,PRINTQTY,1),MATCH($T34,PRINTCOLOURS,0)))+(F28/F$30) -> 29.802383 | G34: =(INDEX(PRINTPRICE,MATCH(G$30,PRINTQTY,1),MATCH($T34,PRINTCOLOURS,0)))+(G28/G$30) -> 18.982116 | H34: =(INDEX(PRINTPRICE,MATCH(H$30,PRINTQTY,1),MATCH($T34,PRINTCOLOURS,0)))+(H28/H$30) -> 16.970149 | I34: =(INDEX(PRINTPRICE,MATCH(I$30,PRINTQTY,1),MATCH($T34,PRINTCOLOURS,0)))+(I28/I$30) -> 13.129687 | J34: =(INDEX(PRINTPRICE,MATCH(J$30,PRINTQTY,1),MATCH($T34,PRINTCOLOURS,0)))+(J28/J$30) -> 8.5000478 | K34: =(INDEX(PRINTPRICE,MATCH(K$30,PRINTQTY,1),MATCH($T34,PRINTCOLOURS,0)))+(K28/K$30) -> 6.412539 | ... S34: =(INDEX(PRINTPRICE,MATCH(S$30,PRINTQTY,1),MATCH($T34,PRINTCOLOURS,0)))+(S28/S$30) -> 2.1595344 | T34: =C34&$G$24&$I$24 -> A32 COLOURSSTANDARD
C35: A2 | D35: =(INDEX(PRINTPRICE,MATCH(D$30,PRINTQTY,1),MATCH($T35,PRINTCOLOURS,0)))+(D29/D$30) -> 270.20076 | E35: =(INDEX(PRINTPRICE,MATCH(E$30,PRINTQTY,1),MATCH($T35,PRINTCOLOURS,0)))+(E29/E$30) -> 81.528002 | F35: =(INDEX(PRINTPRICE,MATCH(F$30,PRINTQTY,1),MATCH($T35,PRINTCOLOURS,0)))+(F29/F$30) -> 43.859659 | G35: =(INDEX(PRINTPRICE,MATCH(G$30,PRINTQTY,1),MATCH($T35,PRINTCOLOURS,0)))+(G29/G$30) -> 28.680261 | H35: =(INDEX(PRINTPRICE,MATCH(H$30,PRINTQTY,1),MATCH($T35,PRINTCOLOURS,0)))+(H29/H$30) -> 25.894578 | I35: =(INDEX(PRINTPRICE,MATCH(I$30,PRINTQTY,1),MATCH($T35,PRINTCOLOURS,0)))+(I29/I$30) -> 19.69187 | J35: =(INDEX(PRINTPRICE,MATCH(J$30,PRINTQTY,1),MATCH($T35,PRINTCOLOURS,0)))+(J29/J$30) -> 13.135838 | K35: =(INDEX(PRINTPRICE,MATCH(K$30,PRINTQTY,1),MATCH($T35,PRINTCOLOURS,0)))+(K29/K$30) -> 10.28328 | ... S35: =(INDEX(PRINTPRICE,MATCH(S$30,PRINTQTY,1),MATCH($T35,PRINTCOLOURS,0)))+(S29/S$30) -> 3.7871212 | T35: =C35&$G$24&$I$24 -> A22 COLOURSSTANDARD
C36: Our price breaks are at 1, 5,10,15,25, 50, 75, 100, 250, 500, 750, 1000, 2500, 5000, 7500, 10000
B40: BREAKDOWN TABLE | F40: =#REF! -> #REF! | G40: =#REF! -> #REF! | H40: =#REF! -> #REF! | I40: =#REF! -> #REF! | J40: =#REF! -> #REF! | K40: =#REF! -> #REF! | P40: UMBRELLAS | Q40: HANDLING | R40: LASER ETCH HANDLE | T40: wooden box | U40: Set Up
E41: Unit COST EXCLUDING Set Up | F41: =INDEX(PRINTPRICE2,MATCH(#REF!,PRINTQTY,1),MATCH(#REF!,PRINTCOLOURS,0)) -> #REF! | G41: =INDEX(PRINTPRICE2,MATCH(#REF!,PRINTQTY,1),MATCH(#REF!,PRINTCOLOURS,0)) -> #REF! | H41: =INDEX(PRINTPRICE2,MATCH(#REF!,PRINTQTY,1),MATCH(#REF!,PRINTCOLOURS,0)) -> #REF! | I41: =INDEX(PRINTPRICE2,MATCH(#REF!,PRINTQTY,1),MATCH(#REF!,PRINTCOLOURS,0)) -> #REF! | J41: =INDEX(PRINTPRICE2,MATCH(#REF!,PRINTQTY,1),MATCH(#REF!,PRINTCOLOURS,0)) -> #REF! | K41: =INDEX(PRINTPRICE2,MATCH(#REF!,PRINTQTY,1),MATCH(#REF!,PRINTCOLOURS,0)) -> #REF! | P41: N/A | Q41: YES | R41: YES
E42: Unit COST Including Set up | F42: =F41+F43/#REF! -> #REF! | G42: =G41+G43/#REF! -> #REF! | H42: =H41+H43/#REF! -> #REF! | I42: =I41+I43/#REF! -> #REF! | J42: =J41+J43/#REF! -> #REF! | K42: =K41+K43/#REF! -> #REF! | P42: 1 COLOUR | Q42: NO | R42: NO | T42: A6
E43: Total Set up (film & Screen) Costs | F43: =#REF!+#REF! -> #REF! | G43: =#REF!+#REF! -> #REF! | H43: =#REF!+#REF! -> #REF! | I43: =#REF!+#REF! -> #REF! | J43: =#REF!+#REF! -> #REF! | K43: =#REF!+#REF! -> #REF! | P43: 2 COLOURS | T43: A5
E44: Total COST EXCLUDING Set Up | F44: =F41*#REF! -> #REF! | G44: =G41*#REF! -> #REF! | H44: =H41*#REF! -> #REF! | I44: =I41*#REF! -> #REF! | J44: =J41*#REF! -> #REF! | K44: =K41*#REF! -> #REF! | P44: 3 COLOURS | T44: A4
E45: Total Cost Including Set Up | F45: =F44+F43 -> #REF! | G45: =G44+G43 -> #REF! | H45: =H44+H43 -> #REF! | I45: =I44+I43 -> #REF! | J45: =J44+J43 -> #REF! | K45: =K44+K43 -> #REF! | P45: 4 COLOURS | T45: A3
E46: Unit SELL price EXCLUDING Set Up | F46: #REF! | G46: #REF! | H46: #REF! | I46: #REF! | J46: #REF! | K46: #REF! | P46: 5 COLOURS
E47: Unit SELL price Including Set UP | F47: #REF! | G47: #REF! | H47: #REF! | I47: #REF! | J47: #REF! | K47: #REF! | P47: 6 COLOURS
E48: TOTAL SELL Price EXCLUDING Set UP | F48: #REF! | G48: #REF! | H48: #REF! | I48: #REF! | J48: #REF! | K48: #REF!
E49: TOTAL SELL Price including Set UP | F49: #REF! | G49: #REF! | H49: #REF! | I49: #REF! | J49: #REF! | K49: #REF!
B55: BREAKDOWN TABLE | F55: =F13 -> A4Location 1 | G55: =G13 -> A4Location 2 | H55: =H13 -> A4Location 3 | I55: =I13 -> A3Location 4 | J55: =J13 -> A2Location 5 | K55: =K13 -> N/ALocation 6 | W55: TOTE BAGS
E56: Unit COST EXCLUDING Set Up | F56: =INDEX(PRINTPRICE,MATCH($E$6,PRINTQTY,1),MATCH(F14,PRINTCOLOURS,0)) -> 6.177723 | G56: =INDEX(PRINTPRICE,MATCH($E$6,PRINTQTY,1),MATCH(G14,PRINTCOLOURS,0)) -> 7.9157788 | H56: =INDEX(PRINTPRICE,MATCH($E$6,PRINTQTY,1),MATCH(H14,PRINTCOLOURS,0)) -> 6.177723 | I56: =INDEX(PRINTPRICE,MATCH($E$6,PRINTQTY,1),MATCH(I14,PRINTCOLOURS,0)) -> 8.5992249 | J56: =INDEX(PRINTPRICE,MATCH($E$6,PRINTQTY,1),MATCH(J14,PRINTCOLOURS,0)) -> 13.901948 | K56: =INDEX(PRINTPRICE,MATCH($E$6,PRINTQTY,1),MATCH(K14,PRINTCOLOURS,0)) -> 0 | R56: PRINT SIZE | S56: # COLOURS | T56: PRINT STYLE | U56: THREAD | V56: SPECIALTY HOOPS | Y56: TOTEBAGS
E57: Unit COST Including Set up | F57: =F56+F58/$E$6 -> 8.499198 | G57: =G56+G58/$E$6 -> 12.558729 | H57: =H56+H58/$E$6 -> 8.499198 | I57: =I56+I58/$E$6 -> 11.617175 | J57: =J56+J58/$E$6 -> 18.080473 | K57: =K56+K58/$E$6 -> 0 | R57: N/A | S57: 1 COLOUR | T57: LIGHT | U57: STANDARD | V57: NO | W57: A4 | X57: 1 COLOUR | Y57: WHITE COTTON OR NATURAL CALICO
E58: Total Set up (film & Screen) Costs | F58: =F15+F16 -> 46.4295 | G58: =G15+G16 -> 92.859 | H58: =H15+H16 -> 46.4295 | I58: =I15+I16 -> 60.359 | J58: =J15+J16 -> 83.5705 | K58: =K15+K16 -> 0 | R58: A6 | S58: 2 COLOURS | T58: STANDARD | U58: METALLIC | V58: YES | W58: A3 | X58: 2 COLOURS | Y58: DARK COTTON OR HEAVY CALICO
E59: Total COST EXCLUDING Set Up | F59: =F56*$E$6 -> 123.55446 | G59: =G56*$E$6 -> 158.31558 | H59: =H56*$E$6 -> 123.55446 | I59: =I56*$E$6 -> 171.9845 | J59: =J56*$E$6 -> 278.03896 | K59: =K56*$E$6 -> 0 | R59: A5 | S59: 3 COLOURS | T59: POLY | X59: 3 COLOURS | Y59: JUTE OR DARK CANVAS
E60: Total Cost Including Set Up | F60: =F59+F58 -> 169.98396 | G60: =G59+G58 -> 251.17458 | H60: =H59+H58 -> 169.98396 | I60: =I59+I58 -> 232.3435 | J60: =J59+J58 -> 361.60946 | K60: =K59+K58 -> 0 | R60: A4 | S60: 4 COLOURS | T60: BLOCKER | X60: 4 COLOURS
E61: Unit SELL price EXCLUDING Set Up | F61: 4.6160579 | G61: 4.6160579 | H61: 4.6160579 | I61: 0 | J61: 0 | K61: 0 | R61: A3 | S61: 5 COLOURS | T61: SPECIALTY | X61: 5 COLOURS
E62: Unit SELL price Including Set UP | F62: 6.7589222 | G62: 5.3303615 | H62: 4.6160579 | I62: 0 | J62: 0 | K62: 0 | R62: A2 | S62: 6 COLOURS | T62: WATERBASED | X62: 6 COLOURS
E63: TOTAL SELL Price EXCLUDING Set UP | F63: 461.60579 | G63: 461.60579 | H63: 461.60579 | I63: 0 | J63: 0 | K63: 0 | S63: 7 COLOURS
E64: TOTAL SELL Price including Set UP | F64: 675.89222 | G64: 533.03615 | H64: 461.60579 | I64: 0 | J64: 0 | K64: 0 | S64: 8 COLOURS
S65: 9 COLOURS | U65: A6 | V65: A5 | W65: A4 | X65: A3 | Y65: A2 | Z65: N/A
S66: 10 COLOURS | T66: NO | U66: 0 | V66: 0 | W66: 0 | X66: 0 | Y66: 0 | Z66: 0
T67: YES | U67: =AT88 -> 27.859 | V67: =CS88 -> 37.141 | W67: =ER88 -> 46.4295 | X67: =GQ88 -> 60.359 | Y67: =IP88 -> 83.5705 | Z67: 0
D71: RESET | E71: N/A1 COLOURLIGHT | F71: N/A1 COLOURSTANDARD | G71: N/A1 COLOURPOLY | H71: N/A1 COLOURWATERBASED | I71: N/A1 COLOURSPECIALTY | J71: N/A2 COLOURSLIGHT | K71: N/A2 COLOURSSTANDARD | L71: N/A2 COLOURSPOLY | M71: N/A2 COLOURSWATERBASED | N71: N/A3 COLOURSLIGHT | O71: N/A3 COLOURSSTANDARD | P71: N/A3 COLOURSPOLY | Q71: N/A3 COLOURSWATERBASED | R71: N/A4 COLOURSLIGHT | S71: N/A4 COLOURSSTANDARD | T71: N/A4 COLOURSPOLY | U71: N/A4 COLOURSWATERBASED | V71: N/A5 COLOURSLIGHT | W71: N/A5 COLOURSSTANDARD | X71: N/A5 COLOURSPOLY | Y71: N/A5 COLOURSWATERBASED | Z71: N/A6 COLOURSLIGHT | AA71: N/A6 COLOURSSTANDARD | AB71: N/A6 COLOURSPOLY | AC71: N/A6 COLOURSWATERBASED | AD71: N/A7 COLOURSLIGHT | AE71: N/A7 COLOURSSTANDARD | AF71: N/A7 COLOURSPOLY | AG71: N/A7 COLOURSWATERBASED | AH71: N/A8 COLOURSLIGHT | AI71: N/A8 COLOURSSTANDARD | AJ71: N/A8 COLOURSPOLY | AK71: N/A8 COLOURSWATERBASED | AL71: N/A9 COLOURSLIGHT | AM71: N/A9 COLOURSSTANDARD | AN71: N/A9 COLOURSPOLY | AO71: N/A9 COLOURSWATERBASED | AP71: N/A10 COLOURSLIGHT | AQ71: N/A10 COLOURSSTANDARD | AR71: N/A10 COLOURSPOLY | AS71: N/A10 COLOURSWATERBASED | AT71: A61 COLOURLIGHT | AU71: A61 COLOURSTANDARD | AV71: A61 COLOURPOLY | AW71: A61 COLOURBLOCKER | AX71: A61 COLOURWATERBASED | AY71: A61 COLOURSPECIALTY | AZ71: A62 COLOURSLIGHT | BA71: A62 COLOURSSTANDARD | BB71: A62 COLOURSPOLY | BC71: A62 COLOURSBLOCKER | BD71: A62 COLOURSWATERBASED | BE71: A63 COLOURSLIGHT | BF71: A63 COLOURSSTANDARD | BG71: A63 COLOURSPOLY | BH71: A63 COLOURSBLOCKER | BI71: A63 COLOURSWATERBASED | BJ71: A64 COLOURSLIGHT | BK71: A64 COLOURSSTANDARD | BL71: A64 COLOURSPOLY | BM71: A64 COLOURSBLOCKER | BN71: A64 COLOURSWATERBASED | BO71: A65 COLOURSLIGHT | BP71: A65 COLOURSSTANDARD | BQ71: A65 COLOURSPOLY | BR71: A65 COLOURSBLOCKER | BS71: A65 COLOURSWATERBASED | BT71: A66 COLOURSLIGHT | BU71: A66 COLOURSSTANDARD | BV71: A66 COLOURSPOLY | BW71: A66 COLOURSBLOCKER | BX71: A66 COLOURSWATERBASED | BY71: A67 COLOURSLIGHT | BZ71: A67 COLOURSSTANDARD | CA71: A67 COLOURSPOLY | CB71: A67 COLOURSBLOCKER | CC71: A67 COLOURSWATERBASED | CD71: A68 COLOURSLIGHT | CE71: A68 COLOURSSTANDARD | CF71: A68 COLOURSPOLY | CG71: A68 COLOURSBLOCKER | CH71: A68 COLOURSWATERBASED | CI71: A69 COLOURSLIGHT | CJ71: A69 COLOURSSTANDARD | CK71: A69 COLOURSPOLY | CL71: A69 COLOURSBLOCKER | CM71: A69 COLOURSWATERBASED | CN71: A610 COLOURSLIGHT | CO71: A610 COLOURSSTANDARD | CP71: A610 COLOURSPOLY | CQ71: A610 COLOURSBLOCKER | CR71: A610 COLOURSWATERBASED | CS71: A51 COLOURLIGHT | CT71: A51 COLOURSTANDARD | CU71: A51 COLOURPOLY | CV71: A51 COLOURBLOCKER | CW71: A51 COLOURWATERBASED | CX71: A51 COLOURSPECIALTY | CY71: A52 COLOURSLIGHT | CZ71: A52 COLOURSSTANDARD | DA71: A52 COLOURSPOLY | DB71: A52 COLOURSBLOCKER | DC71: A52 COLOURSWATERBASED | DD71: A53 COLOURSLIGHT | DE71: A53 COLOURSSTANDARD | DF71: A53 COLOURSPOLY | DG71: A53 COLOURSBLOCKER | DH71: A53 COLOURSWATERBASED | DI71: A54 COLOURSLIGHT | DJ71: A54 COLOURSSTANDARD | DK71: A54 COLOURSPOLY | DL71: A54 COLOURSBLOCKER | DM71: A54 COLOURSWATERBASED | DN71: A55 COLOURSLIGHT | DO71: A55 COLOURSSTANDARD | DP71: A55 COLOURSPOLY | DQ71: A55 COLOURSBLOCKER | DR71: A55 COLOURSWATERBASED | DS71: A56 COLOURSLIGHT | DT71: A56 COLOURSSTANDARD | DU71: A56 COLOURSPOLY | DV71: A56 COLOURSBLOCKER | DW71: A56 COLOURSWATERBASED | DX71: A57 COLOURSLIGHT | DY71: A57 COLOURSSTANDARD | DZ71: A57 COLOURSPOLY | EA71: A57 COLOURSBLOCKER | EB71: A57 COLOURSWATERBASED | EC71: A58 COLOURSLIGHT | ED71: A58 COLOURSSTANDARD | EE71: A58 COLOURSPOLY | EF71: A58 COLOURSBLOCKER | EG71: A58 COLOURSWATERBASED | EH71: A59 COLOURSLIGHT | EI71: A59 COLOURSSTANDARD | EJ71: A59 COLOURSPOLY | EK71: A59 COLOURSBLOCKER | EL71: A59 COLOURSWATERBASED | EM71: A510 COLOURSLIGHT | EN71: A510 COLOURSSTANDARD | EO71: A510 COLOURSPOLY | EP71: A510 COLOURSBLOCKER | EQ71: A510 COLOURSWATERBASED | ER71: A41 COLOURLIGHT | ES71: A41 COLOURSTANDARD | ET71: A41 COLOURPOLY | EU71: A41 COLOURBLOCKER | EV71: A41 COLOURWATERBASED | EW71: A41 COLOURSPECIALTY | EX71: A42 COLOURSLIGHT | EY71: A42 COLOURSSTANDARD | EZ71: A42 COLOURSPOLY | FA71: A42 COLOURSBLOCKER | FB71: A42 COLOURSWATERBASED | FC71: A43 COLOURSLIGHT | FD71: A43 COLOURSSTANDARD | FE71: A43 COLOURSPOLY | FF71: A43 COLOURSBLOCKER | FG71: A43 COLOURSWATERBASED | FH71: A44 COLOURSLIGHT | FI71: A44 COLOURSSTANDARD | FJ71: A44 COLOURSPOLY | FK71: A44 COLOURSBLOCKER | FL71: A44 COLOURSWATERBASED | FM71: A45 COLOURSLIGHT | FN71: A45 COLOURSSTANDARD | FO71: A45 COLOURSPOLY | FP71: A45 COLOURSBLOCKER | FQ71: A45 COLOURSWATERBASED | FR71: A46 COLOURSLIGHT | FS71: A46 COLOURSSTANDARD | FT71: A46 COLOURSPOLY | FU71: A46 COLOURSBLOCKER | FV71: A46 COLOURSWATERBASED | FW71: A47 COLOURSLIGHT | FX71: A47 COLOURSSTANDARD | FY71: A47 COLOURSPOLY | FZ71: A47 COLOURSBLOCKER | GA71: A47 COLOURSWATERBASED | GB71: A48 COLOURSLIGHT | GC71: A48 COLOURSSTANDARD | GD71: A48 COLOURSPOLY | GE71: A48 COLOURSBLOCKER | GF71: A48 COLOURSWATERBASED | GG71: A49 COLOURSLIGHT | GH71: A49 COLOURSSTANDARD | GI71: A49 COLOURSPOLY | GJ71: A49 COLOURSBLOCKER | GK71: A49 COLOURSWATERBASED | GL71: A410 COLOURSLIGHT | GM71: A410 COLOURSSTANDARD | GN71: A410 COLOURSPOLY | GO71: A410 COLOURSBLOCKER | GP71: A410 COLOURSWATERBASED | GQ71: A31 COLOURLIGHT | GR71: A31 COLOURSTANDARD | GS71: A31 COLOURPOLY | GT71: A31 COLOURBLOCKER | GU71: A31 COLOURWATERBASED | GV71: A31 COLOURSPECIALTY | GW71: A32 COLOURSLIGHT | GX71: A32 COLOURSSTANDARD | GY71: A32 COLOURSPOLY | GZ71: A32 COLOURSBLOCKER | HA71: A32 COLOURSWATERBASED | HB71: A33 COLOURSLIGHT | HC71: A33 COLOURSSTANDARD | HD71: A33 COLOURSPOLY | HE71: A33 COLOURSBLOCKER | HF71: A33 COLOURSWATERBASED | HG71: A34 COLOURSLIGHT | HH71: A34 COLOURSSTANDARD | HI71: A34 COLOURSPOLY | HJ71: A34 COLOURSBLOCKER | HK71: A34 COLOURSWATERBASED | HL71: A35 COLOURSLIGHT | HM71: A35 COLOURSSTANDARD | HN71: A35 COLOURSPOLY | HO71: A35 COLOURSBLOCKER | HP71: A35 COLOURSWATERBASED | HQ71: A36 COLOURSLIGHT | HR71: A36 COLOURSSTANDARD | HS71: A36 COLOURSPOLY | HT71: A36 COLOURSBLOCKER | HU71: A36 COLOURSWATERBASED | HV71: A37 COLOURSLIGHT | HW71: A37 COLOURSSTANDARD | HX71: A37 COLOURSPOLY | HY71: A37 COLOURSBLOCKER | HZ71: A37 COLOURSWATERBASED | IA71: A38 COLOURSLIGHT | IB71: A38 COLOURSSTANDARD | IC71: A38 COLOURSPOLY | ID71: A38 COLOURSBLOCKER | IE71: A38 COLOURSWATERBASED | IF71: A39 COLOURSLIGHT | IG71: A39 COLOURSSTANDARD | IH71: A39 COLOURSPOLY | II71: A39 COLOURSBLOCKER | IJ71: A39 COLOURSWATERBASED | IK71: A310 COLOURSLIGHT | IL71: A310 COLOURSSTANDARD | IM71: A310 COLOURSPOLY | IN71: A310 COLOURSBLOCKER | IO71: A310 COLOURSWATERBASED | IP71: A21 COLOURLIGHT | IQ71: A21 COLOURSTANDARD | IR71: A21 COLOURPOLY | IS71: A21 COLOURBLOCKER | IT71: A21 COLOURWATERBASED | IU71: A21 COLOURSPECIALTY | IV71: A22 COLOURSLIGHT | IW71: A22 COLOURSSTANDARD | IX71: A22 COLOURSPOLY | IY71: A22 COLOURSBLOCKER | IZ71: A22 COLOURSWATERBASED | JA71: A23 COLOURSLIGHT | JB71: A23 COLOURSSTANDARD | JC71: A23 COLOURSPOLY | JD71: A23 COLOURSBLOCKER | JE71: A23 COLOURSWATERBASED | JF71: A24 COLOURSLIGHT | JG71: A24 COLOURSSTANDARD | JH71: A24 COLOURSPOLY | JI71: A24 COLOURSBLOCKER | JJ71: A24 COLOURSWATERBASED | JK71: A25 COLOURSLIGHT | JL71: A25 COLOURSSTANDARD | JM71: A25 COLOURSPOLY | JN71: A25 COLOURSBLOCKER | JO71: A25 COLOURSWATERBASED | JP71: A26 COLOURSLIGHT | JQ71: A26 COLOURSSTANDARD | JR71: A26 COLOURSPOLY | JS71: A26 COLOURSBLOCKER | JT71: A26 COLOURSWATERBASED | JU71: A27 COLOURSLIGHT | JV71: A27 COLOURSSTANDARD | JW71: A27 COLOURSPOLY | JX71: A27 COLOURSBLOCKER | JY71: A27 COLOURSWATERBASED | JZ71: A28 COLOURSLIGHT | KA71: A28 COLOURSSTANDARD | KB71: A28 COLOURSPOLY | KC71: A28 COLOURSBLOCKER | KD71: A28 COLOURSWATERBASED | KE71: A29 COLOURSLIGHT | KF71: A29 COLOURSSTANDARD | KG71: A29 COLOURSPOLY | KH71: A29 COLOURSBLOCKER | KI71: A29 COLOURSWATERBASED | KJ71: A210 COLOURSLIGHT | KK71: A210 COLOURSSTANDARD | KL71: A210 COLOURSPOLY | KM71: A210 COLOURSBLOCKER | KN71: A210 COLOURSWATERBASED | KR71: A6WB | KS71: A5WB | KT71: A4WB | KU71: A3WB | KV71: A2WB
